Workbook
Name AccessoFonte: '01_Liste'!$Q$2:$Q$5
Name Affidabilita: '01_Liste'!$N$2:$N$6
Name AzioniLog: '01_Liste'!$R$2:$R$6
Name BarrieraOOpportunita: '01_Liste'!$Z$2:$Z$3
Name Booleane: '01_Liste'!$T$2:$T$4
Name CategorieBarriere: '01_Liste'!$H$2:$H$9
Name EsitoVerifica: '01_Liste'!$AA$2:$AA$4
Name FaseSviluppo: '01_Liste'!$D$2:$D$8
Name FrequenzeAgg: '01_Liste'!$P$2:$P$7
Name Geografie: '01_Liste'!$K$2:$K$8
Name IntensitaImpatto: '01_Liste'!$W$2:$W$4
Name KPI_Tecnici: '01_Liste'!$J$2:$J$9
Name LivelloAnalisi: '01_Liste'!$C$2:$C$4
Name MacroCategorie: '01_Liste'!$A$2:$A$6
Name MetricheCosto: '01_Liste'!$E$2:$E$9
Name Orizzonti: '01_Liste'!$X$2:$X$4
Name SettoriEconomici: '01_Liste'!$F$2:$F$9
Name SourceIDs: '02_Fonti'!$A$4:$A$14
Name StatiPolicy: '01_Liste'!$Y$2:$Y$5
Name StatoMonitoraggio: '01_Liste'!$B$2:$B$6
Name TassonomiaUE: '01_Liste'!$O$2:$O$5
Name TechIDs: '03_Tecnologie'!$A$4:$A$14
Name TipiAttore: '01_Liste'!$I$2:$I$11
Name TipiFonte: '01_Liste'!$M$2:$M$9
Name TipiPolicy: '01_Liste'!$G$2:$G$9
Name Trend: '01_Liste'!$V$2:$V$5
Name TRL: '01_Liste'!$S$2:$S$10
Name Valute: '01_Liste'!$U$2:$U$5

Sheet 00_Executive
A1: ERMES | Executive finale con ranking e semafori
A2: Vista per decisori: ranking sintetico delle tecnologie osservate, semafori per attrattivita, policy fit e copertura dati. Il punteggio executive combina strategia/mercato (25%), maturita tecnologica (15%), prontezza industriale (15%), competitivita economica (20%), sostenibilita/policy fit (20%) e copertura informativa (5%).
B4: Score medio portafoglio | F4: Tecnologie in verde | J4: Tecnologie in giallo | N4: Tecnologie in rosso
B5: =IFERROR(AVERAGE('99_Exec_Helper'!$T$5:$T$35),0) -> 68.291667 | F5: =COUNTIF('99_Exec_Helper'!$V$5:$V$35,"VERDE") -> 4 | J5: =COUNTIF('99_Exec_Helper'!$V$5:$V$35,"GIALLO") -> 5 | N5: =COUNTIF('99_Exec_Helper'!$V$5:$V$35,"ROSSO") -> 3
B7: Indice medio 0-100 | F7: Accelerare / selezionare | J7: Selettive / da pilotare | N7: Presidiare / phase-out
B9: Tecnologie globali / multi-mercato | F9: Copertura dati media | J9: Fossili in rosso | N9: Leader portafoglio
B10: =COUNTIFS('99_Exec_Helper'!$D$5:$D$35,"Entrambi / globale",'99_Exec_Helper'!$V$5:$V$35,"VERDE")+COUNTIFS('99_Exec_Helper'!$D$5:$D$35,"Globale",'99_Exec_Helper'!$V$5:$V$35,"VERDE")+COUNTIFS('99_Exec_Helper'!$D$5:$D$35,"Misto",'99_Exec_Helper'!$V$5:$V$35,"VERDE") -> 0 | F10: =IFERROR(AVERAGE('99_Exec_Helper'!$J$5:$J$35),0) -> 0.84027778 | J10: =COUNTIFS('99_Exec_Helper'!$C$5:$C$35,"Fossili",'99_Exec_Helper'!$V$5:$V$35,"ROSSO") -> 2 | N10: =INDEX('99_Exec_Helper'!$B$5:$B$35,MATCH(1,'99_Exec_Helper'!$U$5:$U$35,0))&CHAR(10)&TEXT(INDEX('99_Exec_Helper'!$T$5:$T$35,MATCH(1,'99_Exec_Helper'!$U$5:$U$35,0)),"0.0") -> Fotovoltaico 90
B12: Mercato ampio + semaforo verde | F12: Copertura aree osservatorio | J12: Tecnologie fossili penalizzate | N12: Prima nel ranking
A14: Sintesi decisionale: watchlist e ranking finale
A15: Leggi cosi: VERDE = accelerare, GIALLO = selezionare / pilotare, ROSSO = presidiare o mantenere per motivi di continuita / sicurezza.
A16: Top 3 da accelerare | J16: Ultimi 3 / da presidiare
A17: Rank | B17: Tecnologia | C17: Score | D17: Semaforo | E17: Posizionamento | J17: Rank | K17: Tecnologia | L17: Score | M17: Semaforo | N17: Posizionamento
A18: 1 | B18: =IFERROR(INDEX('99_Exec_Helper'!$B$5:$B$35,MATCH($A18,'99_Exec_Helper'!$U$5:$U$35,0)),"") -> Fotovoltaico | C18: =IFERROR(INDEX('99_Exec_Helper'!$T$5:$T$35,MATCH($A18,'99_Exec_Helper'!$U$5:$U$35,0)),"") -> 90.1 | D18: =IFERROR(INDEX('99_Exec_Helper'!$V$5:$V$35,MATCH($A18,'99_Exec_Helper'!$U$5:$U$35,0)),"") -> VERDE | E18: =IFERROR(INDEX('99_Exec_Helper'!$Z$5:$Z$35,MATCH($A18,'99_Exec_Helper'!$U$5:$U$35,0)),"") -> Leader | J18: =MAX('99_Exec_Helper'!$U$5:$U$35)-3+ROW()-17 -> 10 | K18: =IFERROR(INDEX('99_Exec_Helper'!$B$5:$B$35,MATCH($J18,'99_Exec_Helper'!$U$5:$U$35,0)),"") -> Carbone | L18: =IFERROR(INDEX('99_Exec_Helper'!$T$5:$T$35,MATCH($J18,'99_Exec_Helper'!$U$5:$U$35,0)),"") -> 52.8 | M18: =IFERROR(INDEX('99_Exec_Helper'!$V$5:$V$35,MATCH($J18,'99_Exec_Helper'!$U$5:$U$35,0)),"") -> ROSSO | N18: =IFERROR(INDEX('99_Exec_Helper'!$Z$5:$Z$35,MATCH($J18,'99_Exec_Helper'!$U$5:$U$35,0)),"") -> Presidio
A19: 2 | B19: =IFERROR(INDEX('99_Exec_Helper'!$B$5:$B$35,MATCH($A19,'99_Exec_Helper'!$U$5:$U$35,0)),"") -> Eolico | C19: =IFERROR(INDEX('99_Exec_Helper'!$T$5:$T$35,MATCH($A19,'99_Exec_Helper'!$U$5:$U$35,0)),"") -> 88.1 | D19: =IFERROR(INDEX('99_Exec_Helper'!$V$5:$V$35,MATCH($A19,'99_Exec_Helper'!$U$5:$U$35,0)),"") -> VERDE | E19: =IFERROR(INDEX('99_Exec_Helper'!$Z$5:$Z$35,MATCH($A19,'99_Exec_Helper'!$U$5:$U$35,0)),"") -> Leader | J19: =MAX('99_Exec_Helper'!$U$5:$U$35)-3+ROW()-17 -> 11 | K19: =IFERROR(INDEX('99_Exec_Helper'!$B$5:$B$35,MATCH($J19,'99_Exec_Helper'!$U$5:$U$35,0)),"") -> Olio | L19: =IFERROR(INDEX('99_Exec_Helper'!$T$5:$T$35,MATCH($J19,'99_Exec_Helper'!$U$5:$U$35,0)),"") -> 46.1 | M19: =IFERROR(INDEX('99_Exec_Helper'!$V$5:$V$35,MATCH($J19,'99_Exec_Helper'!$U$5:$U$35,0)),"") -> ROSSO | N19: =IFERROR(INDEX('99_Exec_Helper'!$Z$5:$Z$35,MATCH($J19,'99_Exec_Helper'!$U$5:$U$35,0)),"") -> Presidio
A20: 3 | B20: =IFERROR(INDEX('99_Exec_Helper'!$B$5:$B$35,MATCH($A20,'99_Exec_Helper'!$U$5:$U$35,0)),"") -> Idroelettrico | C20: =IFERROR(INDEX('99_Exec_Helper'!$T$5:$T$35,MATCH($A20,'99_Exec_Helper'!$U$5:$U$35,0)),"") -> 83.2 | D20: =IFERROR(INDEX('99_Exec_Helper'!$V$5:$V$35,MATCH($A20,'99_Exec_Helper'!$U$5:$U$35,0)),"") -> VERDE | E20: =IFERROR(INDEX('99_Exec_Helper'!$Z$5:$Z$35,MATCH($A20,'99_Exec_Helper'!$U$5:$U$35,0)),"") -> Core | J20: =MAX('99_Exec_Helper'!$U$5:$U$35)-3+ROW()-17 -> 12 | K20: =IFERROR(INDEX('99_Exec_Helper'!$B$5:$B$35,MATCH($J20,'99_Exec_Helper'!$U$5:$U$35,0)),"") -> 0 | L20: =IFERROR(INDEX('99_Exec_Helper'!$T$5:$T$35,MATCH($J20,'99_Exec_Helper'!$U$5:$U$35,0)),"") -> 35.5 | M20: =IFERROR(INDEX('99_Exec_Helper'!$V$5:$V$35,MATCH($J20,'99_Exec_Helper'!$U$5:$U$35,0)),"") -> ROSSO | N20: =IFERROR(INDEX('99_Exec_Helper'!$Z$5:$Z$35,MATCH($J20,'99_Exec_Helper'!$U$5:$U$35,0)),"") -> Presidio
A23: Ranking integrale del portafoglio tecnologico
A24: Il ranking e dinamico e si aggiorna dalle anagrafiche e dai fogli analitici tramite 99_Exec_Helper.
A26: Rank | B26: Tecnologia | C26: Macro-categoria | D26: Mercato di riferimento | E26: Score executive | F26: Posizionamento | G26: Semaforo exec | H26: Semaforo policy | I26: Semaforo dati | J26: TRL | K26: Costo / competitivita | L26: Raccomandazione
A27: 1 | B27: =IFERROR(INDEX('99_Exec_Helper'!$B$5:$B$35,MATCH($A27,'99_Exec_Helper'!$U$5:$U$35,0)),"") -> Fotovoltaico | C27: =IFERROR(INDEX('99_Exec_Helper'!$C$5:$C$35,MATCH($A27,'99_Exec_Helper'!$U$5:$U$35,0)),"") -> Rinnovabili | D27: =IFERROR(INDEX('99_Exec_Helper'!$D$5:$D$35,MATCH($A27,'99_Exec_Helper'!$U$5:$U$35,0)),"") -> 0 | E27: =IFERROR(INDEX('99_Exec_Helper'!$T$5:$T$35,MATCH($A27,'99_Exec_Helper'!$U$5:$U$35,0)),"") -> 90.1 | F27: =IFERROR(INDEX('99_Exec_Helper'!$Z$5:$Z$35,MATCH($A27,'99_Exec_Helper'!$U$5:$U$35,0)),"") -> Leader | G27: =IFERROR(INDEX('99_Exec_Helper'!$V$5:$V$35,MATCH($A27,'99_Exec_Helper'!$U$5:$U$35,0)),"") -> VERDE | H27: =IFERROR(INDEX('99_Exec_Helper'!$X$5:$X$35,MATCH($A27,'99_Exec_Helper'!$U$5:$U$35,0)),"") -> VERDE | I27: =IFERROR(INDEX('99_Exec_Helper'!$W$5:$W$35,MATCH($A27,'99_Exec_Helper'!$U$5:$U$35,0)),"") -> VERDE | J27: =IFERROR(INDEX('99_Exec_Helper'!$F$5:$F$35,MATCH($A27,'99_Exec_Helper'!$U$5:$U$35,0)),"") -> 9 | K27: =IFERROR(INDEX('99_Exec_Helper'!$H$5:$H$35,MATCH($A27,'99_Exec_Helper'!$U$5:$U$35,0)),"") -> Molto competitivo | L27: =IFERROR(INDEX('99_Exec_Helper'!$Y$5:$Y$35,MATCH($A27,'99_Exec_Helper'!$U$5:$U$35,0)),"") -> ACCELERARE
A28: 2 | B28: =IFERROR(INDEX('99_Exec_Helper'!$B$5:$B$35,MATCH($A28,'99_Exec_Helper'!$U$5:$U$35,0)),"") -> Eolico | C28: =IFERROR(INDEX('99_Exec_Helper'!$C$5:$C$35,MATCH($A28,'99_Exec_Helper'!$U$5:$U$35,0)),"") -> Rinnovabili | D28: =IFERROR(INDEX('99_Exec_Helper'!$D$5:$D$35,MATCH($A28,'99_Exec_Helper'!$U$5:$U$35,0)),"") -> 0 | E28: =IFERROR(INDEX('99_Exec_Helper'!$T$5:$T$35,MATCH($A28,'99_Exec_Helper'!$U$5:$U$35,0)),"") -> 88.1 | F28: =IFERROR(INDEX('99_Exec_Helper'!$Z$5:$Z$35,MATCH($A28,'99_Exec_Helper'!$U$5:$U$35,0)),"") -> Leader | G28: =IFERROR(INDEX('99_Exec_Helper'!$V$5:$V$35,MATCH($A28,'99_Exec_Helper'!$U$5:$U$35,0)),"") -> VERDE | H28: =IFERROR(INDEX('99_Exec_Helper'!$X$5:$X$35,MATCH($A28,'99_Exec_Helper'!$U$5:$U$35,0)),"") -> VERDE | I28: =IFERROR(INDEX('99_Exec_Helper'!$W$5:$W$35,MATCH($A28,'99_Exec_Helper'!$U$5:$U$35,0)),"") -> VERDE | J28: =IFERROR(INDEX('99_Exec_Helper'!$F$5:$F$35,MATCH($A28,'99_Exec_Helper'!$U$5:$U$35,0)),"") -> 9 | K28: =IFERROR(INDEX('99_Exec_Helper'!$H$5:$H$35,MATCH($A28,'99_Exec_Helper'!$U$5:$U$35,0)),"") -> Competitivo | L28: =IFERROR(INDEX('99_Exec_Helper'!$Y$5:$Y$35,MATCH($A28,'99_Exec_Helper'!$U$5:$U$35,0)),"") -> ACCELERARE
A29: 3 | B29: =IFERROR(INDEX('99_Exec_Helper'!$B$5:$B$35,MATCH($A29,'99_Exec_Helper'!$U$5:$U$35,0)),"") -> Idroelettrico | C29: =IFERROR(INDEX('99_Exec_Helper'!$C$5:$C$35,MATCH($A29,'99_Exec_Helper'!$U$5:$U$35,0)),"") -> Rinnovabili | D29: =IFERROR(INDEX('99_Exec_Helper'!$D$5:$D$35,MATCH($A29,'99_Exec_Helper'!$U$5:$U$35,0)),"") -> 0 | E29: =IFERROR(INDEX('99_Exec_Helper'!$T$5:$T$35,MATCH($A29,'99_Exec_Helper'!$U$5:$U$35,0)),"") -> 83.2 | F29: =IFERROR(INDEX('99_Exec_Helper'!$Z$5:$Z$35,MATCH($A29,'99_Exec_Helper'!$U$5:$U$35,0)),"") -> Core | G29: =IFERROR(INDEX('99_Exec_Helper'!$V$5:$V$35,MATCH($A29,'99_Exec_Helper'!$U$5:$U$35,0)),"") -> VERDE | H29: =IFERROR(INDEX('99_Exec_Helper'!$X$5:$X$35,MATCH($A29,'99_Exec_Helper'!$U$5:$U$35,0)),"") -> VERDE | I29: =IFERROR(INDEX('99_Exec_Helper'!$W$5:$W$35,MATCH($A29,'99_Exec_Helper'!$U$5:$U$35,0)),"") -> VERDE | J29: =IFERROR(INDEX('99_Exec_Helper'!$F$5:$F$35,MATCH($A29,'99_Exec_Helper'!$U$5:$U$35,0)),"") -> 9 | K29: =IFERROR(INDEX('99_Exec_Helper'!$H$5:$H$35,MATCH($A29,'99_Exec_Helper'!$U$5:$U$35,0)),"") -> 40-120 EUR/MWh | L29: =IFERROR(INDEX('99_Exec_Helper'!$Y$5:$Y$35,MATCH($A29,'99_Exec_Helper'!$U$5:$U$35,0)),"") -> ACCELERARE
A30: 4 | B30: =IFERROR(INDEX('99_Exec_Helper'!$B$5:$B$35,MATCH($A30,'99_Exec_Helper'!$U$5:$U$35,0)),"") -> Geotermico | C30: =IFERROR(INDEX('99_Exec_Helper'!$C$5:$C$35,MATCH($A30,'99_Exec_Helper'!$U$5:$U$35,0)),"") -> Rinnovabili | D30: =IFERROR(INDEX('99_Exec_Helper'!$D$5:$D$35,MATCH($A30,'99_Exec_Helper'!$U$5:$U$35,0)),"") -> 0 | E30: =IFERROR(INDEX('99_Exec_Helper'!$T$5:$T$35,MATCH($A30,'99_Exec_Helper'!$U$5:$U$35,0)),"") -> 80.5 | F30: =IFERROR(INDEX('99_Exec_Helper'!$Z$5:$Z$35,MATCH($A30,'99_Exec_Helper'!$U$5:$U$35,0)),"") -> Core | G30: =IFERROR(INDEX('99_Exec_Helper'!$V$5:$V$35,MATCH($A30,'99_Exec_Helper'!$U$5:$U$35,0)),"") -> VERDE | H30: =IFERROR(INDEX('99_Exec_Helper'!$X$5:$X$35,MATCH($A30,'99_Exec_Helper'!$U$5:$U$35,0)),"") -> VERDE | I30: =IFERROR(INDEX('99_Exec_Helper'!$W$5:$W$35,MATCH($A30,'99_Exec_Helper'!$U$5:$U$35,0)),"") -> VERDE | J30: =IFERROR(INDEX('99_Exec_Helper'!$F$5:$F$35,MATCH($A30,'99_Exec_Helper'!$U$5:$U$35,0)),"") -> 8 | K30: =IFERROR(INDEX('99_Exec_Helper'!$H$5:$H$35,MATCH($A30,'99_Exec_Helper'!$U$5:$U$35,0)),"") -> 45-120 EUR/MWh | L30: =IFERROR(INDEX('99_Exec_Helper'!$Y$5:$Y$35,MATCH($A30,'99_Exec_Helper'!$U$5:$U$35,0)),"") -> ACCELERARE
A31: 5 | B31: =IFERROR(INDEX('99_Exec_Helper'!$B$5:$B$35,MATCH($A31,'99_Exec_Helper'!$U$5:$U$35,0)),"") -> Idrogeno verde | C31: =IFERROR(INDEX('99_Exec_Helper'!$C$5:$C$35,MATCH($A31,'99_Exec_Helper'!$U$5:$U$35,0)),"") -> Vettori innovativi | D31: =IFERROR(INDEX('99_Exec_Helper'!$D$5:$D$35,MATCH($A31,'99_Exec_Helper'!$U$5:$U$35,0)),"") -> 0 | E31: =IFERROR(INDEX('99_Exec_Helper'!$T$5:$T$35,MATCH($A31,'99_Exec_Helper'!$U$5:$U$35,0)),"") -> 77.3 | F31: =IFERROR(INDEX('99_Exec_Helper'!$Z$5:$Z$35,MATCH($A31,'99_Exec_Helper'!$U$5:$U$35,0)),"") -> Core | G31: =IFERROR(INDEX('99_Exec_Helper'!$V$5:$V$35,MATCH($A31,'99_Exec_Helper'!$U$5:$U$35,0)),"") -> GIALLO | H31: =IFERROR(INDEX('99_Exec_Helper'!$X$5:$X$35,MATCH($A31,'99_Exec_Helper'!$U$5:$U$35,0)),"") -> GIALLO | I31: =IFERROR(INDEX('99_Exec_Helper'!$W$5:$W$35,MATCH($A31,'99_Exec_Helper'!$U$5:$U$35,0)),"") -> VERDE | J31: =IFERROR(INDEX('99_Exec_Helper'!$F$5:$F$35,MATCH($A31,'99_Exec_Helper'!$U$5:$U$35,0)),"") -> 7-8 | K31: =IFERROR(INDEX('99_Exec_Helper'!$H$5:$H$35,MATCH($A31,'99_Exec_Helper'!$U$5:$U$35,0)),"") -> Fuel cost-driven | L31: =IFERROR(INDEX('99_Exec_Helper'!$Y$5:$Y$35,MATCH($A31,'99_Exec_Helper'!$U$5:$U$35,0)),"") -> SELEZIONARE / PILOTARE
A32: 6 | B32: =IFERROR(INDEX('99_Exec_Helper'!$B$5:$B$35,MATCH($A32,'99_Exec_Helper'!$U$5:$U$35,0)),"") -> Solare Termico | C32: =IFERROR(INDEX('99_Exec_Helper'!$C$5:$C$35,MATCH($A32,'99_Exec_Helper'!$U$5:$U$35,0)),"") -> Rinnovabili | D32: =IFERROR(INDEX('99_Exec_Helper'!$D$5:$D$35,MATCH($A32,'99_Exec_Helper'!$U$5:$U$35,0)),"") -> 0 | E32: =IFERROR(INDEX('99_Exec_Helper'!$T$5:$T$35,MATCH($A32,'99_Exec_Helper'!$U$5:$U$35,0)),"") -> 71.2 | F32: =IFERROR(INDEX('99_Exec_Helper'!$Z$5:$Z$35,MATCH($A32,'99_Exec_Helper'!$U$5:$U$35,0)),"") -> Selettiva | G32: =IFERROR(INDEX('99_Exec_Helper'!$V$5:$V$35,MATCH($A32,'99_Exec_Helper'!$U$5:$U$35,0)),"") -> GIALLO | H32: =IFERROR(INDEX('99_Exec_Helper'!$X$5:$X$35,MATCH($A32,'99_Exec_Helper'!$U$5:$U$35,0)),"") -> VERDE | I32: =IFERROR(INDEX('99_Exec_Helper'!$W$5:$W$35,MATCH($A32,'99_Exec_Helper'!$U$5:$U$35,0)),"") -> VERDE | J32: =IFERROR(INDEX('99_Exec_Helper'!$F$5:$F$35,MATCH($A32,'99_Exec_Helper'!$U$5:$U$35,0)),"") -> 8 | K32: =IFERROR(INDEX('99_Exec_Helper'!$H$5:$H$35,MATCH($A32,'99_Exec_Helper'!$U$5:$U$35,0)),"") -> 110-220 EUR/MWh | L32: =IFERROR(INDEX('99_Exec_Helper'!$Y$5:$Y$35,MATCH($A32,'99_Exec_Helper'!$U$5:$U$35,0)),"") -> SELEZIONARE / PILOTARE
A33: 7 | B33: =IFERROR(INDEX('99_Exec_Helper'!$B$5:$B$35,MATCH($A33,'99_Exec_Helper'!$U$5:$U$35,0)),"") -> Gas Naturale | C33: =IFERROR(INDEX('99_Exec_Helper'!$C$5:$C$35,MATCH($A33,'99_Exec_Helper'!$U$5:$U$35,0)),"") -> Fossili | D33: =IFERROR(INDEX('99_Exec_Helper'!$D$5:$D$35,MATCH($A33,'99_Exec_Helper'!$U$5:$U$35,0)),"") -> 0 | E33: =IFERROR(INDEX('99_Exec_Helper'!$T$5:$T$35,MATCH($A33,'99_Exec_Helper'!$U$5:$U$35,0)),"") -> 65.3 | F33: =IFERROR(INDEX('99_Exec_Helper'!$Z$5:$Z$35,MATCH($A33,'99_Exec_Helper'!$U$5:$U$35,0)),"") -> Selettiva | G33: =IFERROR(INDEX('99_Exec_Helper'!$V$5:$V$35,MATCH($A33,'99_Exec_Helper'!$U$5:$U$35,0)),"") -> GIALLO | H33: =IFERROR(INDEX('99_Exec_Helper'!$X$5:$X$35,MATCH($A33,'99_Exec_Helper'!$U$5:$U$35,0)),"") -> GIALLO | I33: =IFERROR(INDEX('99_Exec_Helper'!$W$5:$W$35,MATCH($A33,'99_Exec_Helper'!$U$5:$U$35,0)),"") -> VERDE | J33: =IFERROR(INDEX('99_Exec_Helper'!$F$5:$F$35,MATCH($A33,'99_Exec_Helper'!$U$5:$U$35,0)),"") -> 9 | K33: =IFERROR(INDEX('99_Exec_Helper'!$H$5:$H$35,MATCH($A33,'99_Exec_Helper'!$U$5:$U$35,0)),"") -> 70-120 EUR/MWh | L33: =IFERROR(INDEX('99_Exec_Helper'!$Y$5:$Y$35,MATCH($A33,'99_Exec_Helper'!$U$5:$U$35,0)),"") -> SELEZIONARE / PILOTARE
A34: 8 | B34: =IFERROR(INDEX('99_Exec_Helper'!$B$5:$B$35,MATCH($A34,'99_Exec_Helper'!$U$5:$U$35,0)),"") -> Biomasse | C34: =IFERROR(INDEX('99_Exec_Helper'!$C$5:$C$35,MATCH($A34,'99_Exec_Helper'!$U$5:$U$35,0)),"") -> Rinnovabili | D34: =IFERROR(INDEX('99_Exec_Helper'!$D$5:$D$35,MATCH($A34,'99_Exec_Helper'!$U$5:$U$35,0)),"") -> 0 | E34: =IFERROR(INDEX('99_Exec_Helper'!$T$5:$T$35,MATCH($A34,'99_Exec_Helper'!$U$5:$U$35,0)),"") -> 64.7 | F34: =IFERROR(INDEX('99_Exec_Helper'!$Z$5:$Z$35,MATCH($A34,'99_Exec_Helper'!$U$5:$U$35,0)),"") -> Selettiva | G34: =IFERROR(INDEX('99_Exec_Helper'!$V$5:$V$35,MATCH($A34,'99_Exec_Helper'!$U$5:$U$35,0)),"") -> GIALLO | H34: =IFERROR(INDEX('99_Exec_Helper'!$X$5:$X$35,MATCH($A34,'99_Exec_Helper'!$U$5:$U$35,0)),"") -> GIALLO | I34: =IFERROR(INDEX('99_Exec_Helper'!$W$5:$W$35,MATCH($A34,'99_Exec_Helper'!$U$5:$U$35,0)),"") -> VERDE | J34: =IFERROR(INDEX('99_Exec_Helper'!$F$5:$F$35,MATCH($A34,'99_Exec_Helper'!$U$5:$U$35,0)),"") -> 8 | K34: =IFERROR(INDEX('99_Exec_Helper'!$H$5:$H$35,MATCH($A34,'99_Exec_Helper'!$U$5:$U$35,0)),"") -> 90-180 EUR/MWh | L34: =IFERROR(INDEX('99_Exec_Helper'!$Y$5:$Y$35,MATCH($A34,'99_Exec_Helper'!$U$5:$U$35,0)),"") -> SELEZIONARE / PILOTARE
A35: 9 | B35: =IFERROR(INDEX('99_Exec_Helper'!$B$5:$B$35,MATCH($A35,'99_Exec_Helper'!$U$5:$U$35,0)),"") -> Nucleare da fissione | C35: =IFERROR(INDEX('99_Exec_Helper'!$C$5:$C$35,MATCH($A35,'99_Exec_Helper'!$U$5:$U$35,0)),"") -> Basse emissioni / transitorie | D35: =IFERROR(INDEX('99_Exec_Helper'!$D$5:$D$35,MATCH($A35,'99_Exec_Helper'!$U$5:$U$35,0)),"") -> 0 | E35: =IFERROR(INDEX('99_Exec_Helper'!$T$5:$T$35,MATCH($A35,'99_Exec_Helper'!$U$5:$U$35,0)),"") -> 64.7 | F35: =IFERROR(INDEX('99_Exec_Helper'!$Z$5:$Z$35,MATCH($A35,'99_Exec_Helper'!$U$5:$U$35,0)),"") -> Selettiva | G35: =IFERROR(INDEX('99_Exec_Helper'!$V$5:$V$35,MATCH($A35,'99_Exec_Helper'!$U$5:$U$35,0)),"") -> GIALLO | H35: =IFERROR(INDEX('99_Exec_Helper'!$X$5:$X$35,MATCH($A35,'99_Exec_Helper'!$U$5:$U$35,0)),"") -> GIALLO | I35: =IFERROR(INDEX('99_Exec_Helper'!$W$5:$W$35,MATCH($A35,'99_Exec_Helper'!$U$5:$U$35,0)),"") -> VERDE | J35: =IFERROR(INDEX('99_Exec_Helper'!$F$5:$F$35,MATCH($A35,'99_Exec_Helper'!$U$5:$U$35,0)),"") -> 8 | K35: =IFERROR(INDEX('99_Exec_Helper'!$H$5:$H$35,MATCH($A35,'99_Exec_Helper'!$U$5:$U$35,0)),"") -> 90-180 EUR/MWh | L35: =IFERROR(INDEX('99_Exec_Helper'!$Y$5:$Y$35,MATCH($A35,'99_Exec_Helper'!$U$5:$U$35,0)),"") -> SELEZIONARE / PILOTARE
A36: 10 | B36: =IFERROR(INDEX('99_Exec_Helper'!$B$5:$B$35,MATCH($A36,'99_Exec_Helper'!$U$5:$U$35,0)),"") -> Carbone | C36: =IFERROR(INDEX('99_Exec_Helper'!$C$5:$C$35,MATCH($A36,'99_Exec_Helper'!$U$5:$U$35,0)),"") -> Fossili | D36: =IFERROR(INDEX('99_Exec_Helper'!$D$5:$D$35,MATCH($A36,'99_Exec_Helper'!$U$5:$U$35,0)),"") -> 0 | E36: =IFERROR(INDEX('99_Exec_Helper'!$T$5:$T$35,MATCH($A36,'99_Exec_Helper'!$U$5:$U$35,0)),"") -> 52.8 | F36: =IFERROR(INDEX('99_Exec_Helper'!$Z$5:$Z$35,MATCH($A36,'99_Exec_Helper'!$U$5:$U$35,0)),"") -> Presidio | G36: =IFERROR(INDEX('99_Exec_Helper'!$V$5:$V$35,MATCH($A36,'99_Exec_Helper'!$U$5:$U$35,0)),"") -> ROSSO | H36: =IFERROR(INDEX('99_Exec_Helper'!$X$5:$X$35,MATCH($A36,'99_Exec_Helper'!$U$5:$U$35,0)),"") -> ROSSO | I36: =IFERROR(INDEX('99_Exec_Helper'!$W$5:$W$35,MATCH($A36,'99_Exec_Helper'!$U$5:$U$35,0)),"") -> VERDE | J36: =IFERROR(INDEX('99_Exec_Helper'!$F$5:$F$35,MATCH($A36,'99_Exec_Helper'!$U$5:$U$35,0)),"") -> 9 | K36: =IFERROR(INDEX('99_Exec_Helper'!$H$5:$H$35,MATCH($A36,'99_Exec_Helper'!$U$5:$U$35,0)),"") -> 90-160 EUR/MWh | L36: =IFERROR(INDEX('99_Exec_Helper'!$Y$5:$Y$35,MATCH($A36,'99_Exec_Helper'!$U$5:$U$35,0)),"") -> PRESIDIARE / PHASE-OUT
A37: 11 | B37: =IFERROR(INDEX('99_Exec_Helper'!$B$5:$B$35,MATCH($A37,'99_Exec_Helper'!$U$5:$U$35,0)),"") -> Olio | C37: =IFERROR(INDEX('99_Exec_Helper'!$C$5:$C$35,MATCH($A37,'99_Exec_Helper'!$U$5:$U$35,0)),"") -> Fossili | D37: =IFERROR(INDEX('99_Exec_Helper'!$D$5:$D$35,MATCH($A37,'99_Exec_Helper'!$U$5:$U$35,0)),"") -> 0 | E37: =IFERROR(INDEX('99_Exec_Helper'!$T$5:$T$35,MATCH($A37,'99_Exec_Helper'!$U$5:$U$35,0)),"") -> 46.1 | F37: =IFERROR(INDEX('99_Exec_Helper'!$Z$5:$Z$35,MATCH($A37,'99_Exec_Helper'!$U$5:$U$35,0)),"") -> Presidio | G37: =IFERROR(INDEX('99_Exec_Helper'!$V$5:$V$35,MATCH($A37,'99_Exec_Helper'!$U$5:$U$35,0)),"") -> ROSSO | H37: =IFERROR(INDEX('99_Exec_Helper'!$X$5:$X$35,MATCH($A37,'99_Exec_Helper'!$U$5:$U$35,0)),"") -> ROSSO | I37: =IFERROR(INDEX('99_Exec_Helper'!$W$5:$W$35,MATCH($A37,'99_Exec_Helper'!$U$5:$U$35,0)),"") -> VERDE | J37: =IFERROR(INDEX('99_Exec_Helper'!$F$5:$F$35,MATCH($A37,'99_Exec_Helper'!$U$5:$U$35,0)),"") -> 9 | K37: =IFERROR(INDEX('99_Exec_Helper'!$H$5:$H$35,MATCH($A37,'99_Exec_Helper'!$U$5:$U$35,0)),"") -> 130-220 EUR/MWh | L37: =IFERROR(INDEX('99_Exec_Helper'!$Y$5:$Y$35,MATCH($A37,'99_Exec_Helper'!$U$5:$U$35,0)),"") -> PRESIDIARE / PHASE-OUT

Sheet 00_Dashboard
A1: ERMES | Dashboard manageriale e KPI sintetici
A2: Cruscotto executive per seguire il popolamento dell'Osservatorio. Le metriche leggono in automatico le anagrafiche e i fogli analitici; si aggiornano man mano che compili il database.
B4: Fonti censite | F4: Tecnologie monitorate | J4: Perimetro mercati | N4: Record analitici
B5: =COUNTA('02_Fonti'!$A$4:$A$1000) -> 121 | F5: =COUNTA('03_Tecnologie'!$A$4:$A$1000) -> 12 | J5: =COUNTA('04_Componenti'!$A$4:$A$1000) -> 69 | N5: =SUM('00_Scorecard'!$T$4:$T$1000) -> 694
B7: Repertorio fonti | F7: Tecnologie attive in anagrafica | J7: Classificazione mercati di riferimento | N7: Somma di tutte le aree
B9: Copertura media aree | F9: TRL/TLR medio | J9: Mercati perimetro | N9: Copertura avanzata
B10: =IFERROR(AVERAGEIF('00_Scorecard'!$R$4:$R$1000,">0"),0) -> 0.91666667 | F10: =IFERROR(AVERAGEIF('00_Scorecard'!$S$4:$S$1000,">0"),0) -> 8.2121212 | J10: =COUNTIF('03_Tecnologie'!$H$4:$H$1000,"<>") -> 0 | N10: =COUNTIF('00_Scorecard'!$U$4:$U$1000,"Copertura avanzata") -> 11
B12: Quota media aree coperte | F12: Solo tecnologie con dati TRL | J12: Tecnologie senza perimetro mercato | N12: Tecnologie oltre il 70%
J13: =COUNTIFS('03_Tecnologie'!$A$4:$A$1000,"<>",'03_Tecnologie'!$H$4:$H$1000,"") -> 12
A14: Sintesi per tecnologia (vista rapida)
A15: La tabella sotto riprende la scorecard manageriale. Se una tecnologia ha copertura bassa o presidio informativo limitato, il database va rafforzato prima.
A17: Tecnologia | B17: Stato monitoraggio | C17: Copertura | D17: Stato manageriale | E17: Priorita di popolamento
A18: =IF('00_Scorecard'!B4="","",'00_Scorecard'!B4) -> Carbone | B18: =IF($A18="","",'00_Scorecard'!D4) -> Monitoraggio attivo | C18: =IF($A18="","",'00_Scorecard'!R4) -> 0.91666667 | D18: =IF($A18="","",'00_Scorecard'!U4) -> Copertura avanzata | E18: =IF($A18="","",'00_Scorecard'!V4) -> Presidio adeguato
A19: =IF('00_Scorecard'!B5="","",'00_Scorecard'!B5) -> Olio | B19: =IF($A19="","",'00_Scorecard'!D5) -> Archiviata | C19: =IF($A19="","",'00_Scorecard'!R5) -> 0.91666667 | D19: =IF($A19="","",'00_Scorecard'!U5) -> Copertura avanzata | E19: =IF($A19="","",'00_Scorecard'!V5) -> Presidio adeguato
A20: =IF('00_Scorecard'!B6="","",'00_Scorecard'!B6) -> Gas Naturale | B20: =IF($A20="","",'00_Scorecard'!D6) -> Monitoraggio attivo | C20: =IF($A20="","",'00_Scorecard'!R6) -> 0.91666667 | D20: =IF($A20="","",'00_Scorecard'!U6) -> Copertura avanzata | E20: =IF($A20="","",'00_Scorecard'!V6) -> Presidio adeguato
A21: =IF('00_Scorecard'!B7="","",'00_Scorecard'!B7) -> Fotovoltaico | B21: =IF($A21="","",'00_Scorecard'!D7) -> Monitoraggio attivo | C21: =IF($A21="","",'00_Scorecard'!R7) -> 0.91666667 | D21: =IF($A21="","",'00_Scorecard'!U7) -> Copertura avanzata | E21: =IF($A21="","",'00_Scorecard'!V7) -> Presidio adeguato
A22: =IF('00_Scorecard'!B8="","",'00_Scorecard'!B8) -> Solare Termico | B22: =IF($A22="","",'00_Scorecard'!D8) -> Monitoraggio attivo | C22: =IF($A22="","",'00_Scorecard'!R8) -> 0.91666667 | D22: =IF($A22="","",'00_Scorecard'!U8) -> Copertura avanzata | E22: =IF($A22="","",'00_Scorecard'!V8) -> Presidio adeguato
A23: =IF('00_Scorecard'!B9="","",'00_Scorecard'!B9) -> Eolico | B23: =IF($A23="","",'00_Scorecard'!D9) -> Monitoraggio attivo | C23: =IF($A23="","",'00_Scorecard'!R9) -> 0.91666667 | D23: =IF($A23="","",'00_Scorecard'!U9) -> Copertura avanzata | E23: =IF($A23="","",'00_Scorecard'!V9) -> Presidio adeguato
A24: =IF('00_Scorecard'!B10="","",'00_Scorecard'!B10) -> Idroelettrico | B24: =IF($A24="","",'00_Scorecard'!D10) -> Monitoraggio attivo | C24: =IF($A24="","",'00_Scorecard'!R10) -> 0.91666667 | D24: =IF($A24="","",'00_Scorecard'!U10) -> Copertura avanzata | E24: =IF($A24="","",'00_Scorecard'!V10) -> Presidio adeguato
A25: =IF('00_Scorecard'!B11="","",'00_Scorecard'!B11) -> Biomasse | B25: =IF($A25="","",'00_Scorecard'!D11) -> Monitoraggio attivo | C25: =IF($A25="","",'00_Scorecard'!R11) -> 0.91666667 | D25: =IF($A25="","",'00_Scorecard'!U11) -> Copertura avanzata | E25: =IF($A25="","",'00_Scorecard'!V11) -> Presidio adeguato
A26: =IF('00_Scorecard'!B12="","",'00_Scorecard'!B12) -> Geotermico | B26: =IF($A26="","",'00_Scorecard'!D12) -> Monitoraggio attivo | C26: =IF($A26="","",'00_Scorecard'!R12) -> 0.91666667 | D26: =IF($A26="","",'00_Scorecard'!U12) -> Copertura avanzata | E26: =IF($A26="","",'00_Scorecard'!V12) -> Presidio adeguato
A27: =IF('00_Scorecard'!B13="","",'00_Scorecard'!B13) -> Nucleare da fissione | B27: =IF($A27="","",'00_Scorecard'!D13) -> Monitoraggio attivo | C27: =IF($A27="","",'00_Scorecard'!R13) -> 0.91666667 | D27: =IF($A27="","",'00_Scorecard'!U13) -> Copertura avanzata | E27: =IF($A27="","",'00_Scorecard'!V13) -> Presidio adeguato
A28: =IF('00_Scorecard'!B14="","",'00_Scorecard'!B14) -> Idrogeno verde | B28: =IF($A28="","",'00_Scorecard'!D14) -> Prioritaria | C28: =IF($A28="","",'00_Scorecard'!R14) -> 0.91666667 | D28: =IF($A28="","",'00_Scorecard'!U14) -> Copertura avanzata | E28: =IF($A28="","",'00_Scorecard'!V14) -> Presidio adeguato
A29: =IF('00_Scorecard'!B15="","",'00_Scorecard'!B15) -> 0 | B29: =IF($A29="","",'00_Scorecard'!D15) -> 0 | C29: =IF($A29="","",'00_Scorecard'!R15) -> 0 | D29: =IF($A29="","",'00_Scorecard'!U15) -> Da avviare | E29: =IF($A29="","",'00_Scorecard'!V15) -> Da avviare
... A32: =IF('00_Scorecard'!B18="","",'00_Scorecard'!B18) | B32: =IF($A32="","",'00_Scorecard'!D18) | C32: =IF($A32="","",'00_Scorecard'!R18) | D32: =IF($A32="","",'00_Scorecard'!U18) | E32: =IF($A32="","",'00_Scorecard'!V18)

Sheet 00_Scorecard
A1: ERMES | Scorecard manageriale per tecnologia
A2: Foglio di sintesi automatico: misura la completezza del database ERMES per ciascuna tecnologia. Non valuta il merito tecnologico, ma il livello di copertura informativa dei dati raccolti.
A3: Tech_ID | B3: Tecnologia | C3: Macro-categoria | D3: Stato monitoraggio | E3: # Componenti | F3: # Descrizione | G3: # Avanzamento | H3: # TRL/TLR | I3: # Costi | J3: # Settori | K3: # Mercati | L3: # Sostenibilita | M3: # Best practice | N3: # Policy | O3: # Barriere/Opp. | P3: # Attori | Q3: # Prestazioni | R3: Copertura aree | S3: TRL medio | T3: Record totali | U3: Stato manageriale | V3: Priorita di popolamento
A4: =IF('03_Tecnologie'!A4="","",'03_Tecnologie'!A4) -> T001 | B4: =IF($A4="","",'03_Tecnologie'!D4) -> Carbone | C4: =IF($A4="","",'03_Tecnologie'!B4) -> Fossili | D4: =IF($A4="","",'03_Tecnologie'!F4) -> Monitoraggio attivo | E4: =IF($A4="","",COUNTIF('04_Componenti'!$B$4:$B$1000,$A4)) -> 6 | F4: =IF($A4="","",COUNTIF('05_Descrizione'!$B$4:$B$1000,$A4)) -> 6 | G4: =IF($A4="","",COUNTIF('06_Avanzamento'!$B$4:$B$1000,$A4)) -> 6 | H4: =IF($A4="","",COUNTIF('07_TRL_TLR'!$B$4:$B$1000,$A4)) -> 6 | I4: =IF($A4="","",COUNTIF('08_Costi_Compet'!$B$4:$B$1000,$A4)) -> 6 | J4: =IF($A4="","",COUNTIF('09_Settori_Impatto'!$B$4:$B$1000,$A4)) -> 6 | K4: =IF($A4="","",COUNTIF('16_Mercati_Riferimento'!$B$4:$B$1000,$A4)) -> 0 | L4: =IF($A4="","",COUNTIF('10_Sostenibilita'!$B$4:$B$1000,$A4)) -> 3 | M4: =IF($A4="","",COUNTIF('11_Best_Practice'!$B$4:$B$1000,$A4)) -> 4 | N4: =IF($A4="","",COUNTIF('12_Policy_Regolazione'!$B$4:$B$1000,$A4)) -> 5 | O4: =IF($A4="","",COUNTIF('13_Barriere_Opp'!$B$4:$B$1000,$A4)) -> 6 | P4: =IF($A4="","",COUNTIF('14_Attori_Imprese'!$B$4:$B$1000,$A4)) -> 7 | Q4: =IF($A4="","",COUNTIF('15_Prestazioni'!$B$4:$B$1000,$A4)) -> 8 | R4: =IF($A4="","",COUNTIF(F4:Q4,">0")/12) -> 0.91666667 | S4: =IF($A4="","",IFERROR(AVERAGEIF('07_TRL_TLR'!$B$4:$B$1000,$A4,'07_TRL_TLR'!$F$4:$F$1000),"")) -> 8.1666667 | T4: =IF($A4="","",SUM(F4:Q4)) -> 63 | U4: =IF($A4="","",IF(T4=0,"Da avviare",IF(R4<0.3,"Copertura base",IF(R4<0.7,"Copertura intermedia","Copertura avanzata")))) -> Copertura avanzata | V4: =IF($A4="","",IF(AND(D4="Prioritaria",R4<0.5),"Alta priorita",IF(AND(D4="Monitoraggio attivo",R4<0.3),"Media priorita",IF(T4=0,"Da avviare","Presidio adeguato")))) -> Presidio adeguato
A5: =IF('03_Tecnologie'!A5="","",'03_Tecnologie'!A5) -> T002 | B5: =IF($A5="","",'03_Tecnologie'!D5) -> Olio | C5: =IF($A5="","",'03_Tecnologie'!B5) -> Fossili | D5: =IF($A5="","",'03_Tecnologie'!F5) -> Archiviata | E5: =IF($A5="","",COUNTIF('04_Componenti'!$B$4:$B$1000,$A5)) -> 6 | F5: =IF($A5="","",COUNTIF('05_Descrizione'!$B$4:$B$1000,$A5)) -> 6 | G5: =IF($A5="","",COUNTIF('06_Avanzamento'!$B$4:$B$1000,$A5)) -> 6 | H5: =IF($A5="","",COUNTIF('07_TRL_TLR'!$B$4:$B$1000,$A5)) -> 6 | I5: =IF($A5="","",COUNTIF('08_Costi_Compet'!$B$4:$B$1000,$A5)) -> 6 | J5: =IF($A5="","",COUNTIF('09_Settori_Impatto'!$B$4:$B$1000,$A5)) -> 6 | K5: =IF($A5="","",COUNTIF('16_Mercati_Riferimento'!$B$4:$B$1000,$A5)) -> 0 | L5: =IF($A5="","",COUNTIF('10_Sostenibilita'!$B$4:$B$1000,$A5)) -> 3 | M5: =IF($A5="","",COUNTIF('11_Best_Practice'!$B$4:$B$1000,$A5)) -> 4 | N5: =IF($A5="","",COUNTIF('12_Policy_Regolazione'!$B$4:$B$1000,$A5)) -> 5 | O5: =IF($A5="","",COUNTIF('13_Barriere_Opp'!$B$4:$B$1000,$A5)) -> 6 | P5: =IF($A5="","",COUNTIF('14_Attori_Imprese'!$B$4:$B$1000,$A5)) -> 7 | Q5: =IF($A5="","",COUNTIF('15_Prestazioni'!$B$4:$B$1000,$A5)) -> 8 | R5: =IF($A5="","",COUNTIF(F5:Q5,">0")/12) -> 0.91666667 | S5: =IF($A5="","",IFERROR(AVERAGEIF('07_TRL_TLR'!$B$4:$B$1000,$A5,'07_TRL_TLR'!$F$4:$F$1000),"")) -> 8.8333333 | T5: =IF($A5="","",SUM(F5:Q5)) -> 63 | U5: =IF($A5="","",IF(T5=0,"Da avviare",IF(R5<0.3,"Copertura base",IF(R5<0.7,"Copertura intermedia","Copertura avanzata")))) -> Copertura avanzata | V5: =IF($A5="","",IF(AND(D5="Prioritaria",R5<0.5),"Alta priorita",IF(AND(D5="Monitoraggio attivo",R5<0.3),"Media priorita",IF(T5=0,"Da avviare","Presidio adeguato")))) -> Presidio adeguato
A6: =IF('03_Tecnologie'!A6="","",'03_Tecnologie'!A6) -> T003 | B6: =IF($A6="","",'03_Tecnologie'!D6) -> Gas Naturale | C6: =IF($A6="","",'03_Tecnologie'!B6) -> Fossili | D6: =IF($A6="","",'03_Tecnologie'!F6) -> Monitoraggio attivo | E6: =IF($A6="","",COUNTIF('04_Componenti'!$B$4:$B$1000,$A6)) -> 6 | F6: =IF($A6="","",COUNTIF('05_Descrizione'!$B$4:$B$1000,$A6)) -> 6 | G6: =IF($A6="","",COUNTIF('06_Avanzamento'!$B$4:$B$1000,$A6)) -> 6 | H6: =IF($A6="","",COUNTIF('07_TRL_TLR'!$B$4:$B$1000,$A6)) -> 6 | I6: =IF($A6="","",COUNTIF('08_Costi_Compet'!$B$4:$B$1000,$A6)) -> 6 | J6: =IF($A6="","",COUNTIF('09_Settori_Impatto'!$B$4:$B$1000,$A6)) -> 6 | K6: =IF($A6="","",COUNTIF('16_Mercati_Riferimento'!$B$4:$B$1000,$A6)) -> 0 | L6: =IF($A6="","",COUNTIF('10_Sostenibilita'!$B$4:$B$1000,$A6)) -> 3 | M6: =IF($A6="","",COUNTIF('11_Best_Practice'!$B$4:$B$1000,$A6)) -> 4 | N6: =IF($A6="","",COUNTIF('12_Policy_Regolazione'!$B$4:$B$1000,$A6)) -> 5 | O6: =IF($A6="","",COUNTIF('13_Barriere_Opp'!$B$4:$B$1000,$A6)) -> 6 | P6: =IF($A6="","",COUNTIF('14_Attori_Imprese'!$B$4:$B$1000,$A6)) -> 7 | Q6: =IF($A6="","",COUNTIF('15_Prestazioni'!$B$4:$B$1000,$A6)) -> 8 | R6: =IF($A6="","",COUNTIF(F6:Q6,">0")/12) -> 0.91666667 | S6: =IF($A6="","",IFERROR(AVERAGEIF('07_TRL_TLR'!$B$4:$B$1000,$A6,'07_TRL_TLR'!$F$4:$F$1000),"")) -> 8.5 | T6: =IF($A6="","",SUM(F6:Q6)) -> 63 | U6: =IF($A6="","",IF(T6=0,"Da avviare",IF(R6<0.3,"Copertura base",IF(R6<0.7,"Copertura intermedia","Copertura avanzata")))) -> Copertura avanzata | V6: =IF($A6="","",IF(AND(D6="Prioritaria",R6<0.5),"Alta priorita",IF(AND(D6="Monitoraggio attivo",R6<0.3),"Media priorita",IF(T6=0,"Da avviare","Presidio adeguato")))) -> Presidio adeguato
A7: =IF('03_Tecnologie'!A7="","",'03_Tecnologie'!A7) -> T004 | B7: =IF($A7="","",'03_Tecnologie'!D7) -> Fotovoltaico | C7: =IF($A7="","",'03_Tecnologie'!B7) -> Rinnovabili | D7: =IF($A7="","",'03_Tecnologie'!F7) -> Monitoraggio attivo | E7: =IF($A7="","",COUNTIF('04_Componenti'!$B$4:$B$1000,$A7)) -> 7 | F7: =IF($A7="","",COUNTIF('05_Descrizione'!$B$4:$B$1000,$A7)) -> 7 | G7: =IF($A7="","",COUNTIF('06_Avanzamento'!$B$4:$B$1000,$A7)) -> 6 | H7: =IF($A7="","",COUNTIF('07_TRL_TLR'!$B$4:$B$1000,$A7)) -> 6 | I7: =IF($A7="","",COUNTIF('08_Costi_Compet'!$B$4:$B$1000,$A7)) -> 6 | J7: =IF($A7="","",COUNTIF('09_Settori_Impatto'!$B$4:$B$1000,$A7)) -> 6 | K7: =IF($A7="","",COUNTIF('16_Mercati_Riferimento'!$B$4:$B$1000,$A7)) -> 0 | L7: =IF($A7="","",COUNTIF('10_Sostenibilita'!$B$4:$B$1000,$A7)) -> 3 | M7: =IF($A7="","",COUNTIF('11_Best_Practice'!$B$4:$B$1000,$A7)) -> 4 | N7: =IF($A7="","",COUNTIF('12_Policy_Regolazione'!$B$4:$B$1000,$A7)) -> 5 | O7: =IF($A7="","",COUNTIF('13_Barriere_Opp'!$B$4:$B$1000,$A7)) -> 6 | P7: =IF($A7="","",COUNTIF('14_Attori_Imprese'!$B$4:$B$1000,$A7)) -> 7 | Q7: =IF($A7="","",COUNTIF('15_Prestazioni'!$B$4:$B$1000,$A7)) -> 8 | R7: =IF($A7="","",COUNTIF(F7:Q7,">0")/12) -> 0.91666667 | S7: =IF($A7="","",IFERROR(AVERAGEIF('07_TRL_TLR'!$B$4:$B$1000,$A7,'07_TRL_TLR'!$F$4:$F$1000),"")) -> 8 | T7: =IF($A7="","",SUM(F7:Q7)) -> 64 | U7: =IF($A7="","",IF(T7=0,"Da avviare",IF(R7<0.3,"Copertura base",IF(R7<0.7,"Copertura intermedia","Copertura avanzata")))) -> Copertura avanzata | V7: =IF($A7="","",IF(AND(D7="Prioritaria",R7<0.5),"Alta priorita",IF(AND(D7="Monitoraggio attivo",R7<0.3),"Media priorita",IF(T7=0,"Da avviare","Presidio adeguato")))) -> Presidio adeguato
A8: =IF('03_Tecnologie'!A8="","",'03_Tecnologie'!A8) -> T005 | B8: =IF($A8="","",'03_Tecnologie'!D8) -> Solare Termico | C8: =IF($A8="","",'03_Tecnologie'!B8) -> Rinnovabili | D8: =IF($A8="","",'03_Tecnologie'!F8) -> Monitoraggio attivo | E8: =IF($A8="","",COUNTIF('04_Componenti'!$B$4:$B$1000,$A8)) -> 6 | F8: =IF($A8="","",COUNTIF('05_Descrizione'!$B$4:$B$1000,$A8)) -> 6 | G8: =IF($A8="","",COUNTIF('06_Avanzamento'!$B$4:$B$1000,$A8)) -> 6 | H8: =IF($A8="","",COUNTIF('07_TRL_TLR'!$B$4:$B$1000,$A8)) -> 6 | I8: =IF($A8="","",COUNTIF('08_Costi_Compet'!$B$4:$B$1000,$A8)) -> 6 | J8: =IF($A8="","",COUNTIF('09_Settori_Impatto'!$B$4:$B$1000,$A8)) -> 6 | K8: =IF($A8="","",COUNTIF('16_Mercati_Riferimento'!$B$4:$B$1000,$A8)) -> 0 | L8: =IF($A8="","",COUNTIF('10_Sostenibilita'!$B$4:$B$1000,$A8)) -> 3 | M8: =IF($A8="","",COUNTIF('11_Best_Practice'!$B$4:$B$1000,$A8)) -> 4 | N8: =IF($A8="","",COUNTIF('12_Policy_Regolazione'!$B$4:$B$1000,$A8)) -> 5 | O8: =IF($A8="","",COUNTIF('13_Barriere_Opp'!$B$4:$B$1000,$A8)) -> 6 | P8: =IF($A8="","",COUNTIF('14_Attori_Imprese'!$B$4:$B$1000,$A8)) -> 7 | Q8: =IF($A8="","",COUNTIF('15_Prestazioni'!$B$4:$B$1000,$A8)) -> 8 | R8: =IF($A8="","",COUNTIF(F8:Q8,">0")/12) -> 0.91666667 | S8: =IF($A8="","",IFERROR(AVERAGEIF('07_TRL_TLR'!$B$4:$B$1000,$A8,'07_TRL_TLR'!$F$4:$F$1000),"")) -> 8.1666667 | T8: =IF($A8="","",SUM(F8:Q8)) -> 63 | U8: =IF($A8="","",IF(T8=0,"Da avviare",IF(R8<0.3,"Copertura base",IF(R8<0.7,"Copertura intermedia","Copertura avanzata")))) -> Copertura avanzata | V8: =IF($A8="","",IF(AND(D8="Prioritaria",R8<0.5),"Alta priorita",IF(AND(D8="Monitoraggio attivo",R8<0.3),"Media priorita",IF(T8=0,"Da avviare","Presidio adeguato")))) -> Presidio adeguato
A9: =IF('03_Tecnologie'!A9="","",'03_Tecnologie'!A9) -> T006 | B9: =IF($A9="","",'03_Tecnologie'!D9) -> Eolico | C9: =IF($A9="","",'03_Tecnologie'!B9) -> Rinnovabili | D9: =IF($A9="","",'03_Tecnologie'!F9) -> Monitoraggio attivo | E9: =IF($A9="","",COUNTIF('04_Componenti'!$B$4:$B$1000,$A9)) -> 7 | F9: =IF($A9="","",COUNTIF('05_Descrizione'!$B$4:$B$1000,$A9)) -> 6 | G9: =IF($A9="","",COUNTIF('06_Avanzamento'!$B$4:$B$1000,$A9)) -> 6 | H9: =IF($A9="","",COUNTIF('07_TRL_TLR'!$B$4:$B$1000,$A9)) -> 6 | I9: =IF($A9="","",COUNTIF('08_Costi_Compet'!$B$4:$B$1000,$A9)) -> 6 | J9: =IF($A9="","",COUNTIF('09_Settori_Impatto'!$B$4:$B$1000,$A9)) -> 6 | K9: =IF($A9="","",COUNTIF('16_Mercati_Riferimento'!$B$4:$B$1000,$A9)) -> 0 | L9: =IF($A9="","",COUNTIF('10_Sostenibilita'!$B$4:$B$1000,$A9)) -> 3 | M9: =IF($A9="","",COUNTIF('11_Best_Practice'!$B$4:$B$1000,$A9)) -> 4 | N9: =IF($A9="","",COUNTIF('12_Policy_Regolazione'!$B$4:$B$1000,$A9)) -> 5 | O9: =IF($A9="","",COUNTIF('13_Barriere_Opp'!$B$4:$B$1000,$A9)) -> 6 | P9: =IF($A9="","",COUNTIF('14_Attori_Imprese'!$B$4:$B$1000,$A9)) -> 7 | Q9: =IF($A9="","",COUNTIF('15_Prestazioni'!$B$4:$B$1000,$A9)) -> 8 | R9: =IF($A9="","",COUNTIF(F9:Q9,">0")/12) -> 0.91666667 | S9: =IF($A9="","",IFERROR(AVERAGEIF('07_TRL_TLR'!$B$4:$B$1000,$A9,'07_TRL_TLR'!$F$4:$F$1000),"")) -> 8.6666667 | T9: =IF($A9="","",SUM(F9:Q9)) -> 63 | U9: =IF($A9="","",IF(T9=0,"Da avviare",IF(R9<0.3,"Copertura base",IF(R9<0.7,"Copertura intermedia","Copertura avanzata")))) -> Copertura avanzata | V9: =IF($A9="","",IF(AND(D9="Prioritaria",R9<0.5),"Alta priorita",IF(AND(D9="Monitoraggio attivo",R9<0.3),"Media priorita",IF(T9=0,"Da avviare","Presidio adeguato")))) -> Presidio adeguato
A10: =IF('03_Tecnologie'!A10="","",'03_Tecnologie'!A10) -> T007 | B10: =IF($A10="","",'03_Tecnologie'!D10) -> Idroelettrico | C10: =IF($A10="","",'03_Tecnologie'!B10) -> Rinnovabili | D10: =IF($A10="","",'03_Tecnologie'!F10) -> Monitoraggio attivo | E10: =IF($A10="","",COUNTIF('04_Componenti'!$B$4:$B$1000,$A10)) -> 6 | F10: =IF($A10="","",COUNTIF('05_Descrizione'!$B$4:$B$1000,$A10)) -> 6 | G10: =IF($A10="","",COUNTIF('06_Avanzamento'!$B$4:$B$1000,$A10)) -> 6 | H10: =IF($A10="","",COUNTIF('07_TRL_TLR'!$B$4:$B$1000,$A10)) -> 6 | I10: =IF($A10="","",COUNTIF('08_Costi_Compet'!$B$4:$B$1000,$A10)) -> 6 | J10: =IF($A10="","",COUNTIF('09_Settori_Impatto'!$B$4:$B$1000,$A10)) -> 6 | K10: =IF($A10="","",COUNTIF('16_Mercati_Riferimento'!$B$4:$B$1000,$A10)) -> 0 | L10: =IF($A10="","",COUNTIF('10_Sostenibilita'!$B$4:$B$1000,$A10)) -> 3 | M10: =IF($A10="","",COUNTIF('11_Best_Practice'!$B$4:$B$1000,$A10)) -> 4 | N10: =IF($A10="","",COUNTIF('12_Policy_Regolazione'!$B$4:$B$1000,$A10)) -> 5 | O10: =IF($A10="","",COUNTIF('13_Barriere_Opp'!$B$4:$B$1000,$A10)) -> 6 | P10: =IF($A10="","",COUNTIF('14_Attori_Imprese'!$B$4:$B$1000,$A10)) -> 7 | Q10: =IF($A10="","",COUNTIF('15_Prestazioni'!$B$4:$B$1000,$A10)) -> 8 | R10: =IF($A10="","",COUNTIF(F10:Q10,">0")/12) -> 0.91666667 | S10: =IF($A10="","",IFERROR(AVERAGEIF('07_TRL_TLR'!$B$4:$B$1000,$A10,'07_TRL_TLR'!$F$4:$F$1000),"")) -> 8.8333333 | T10: =IF($A10="","",SUM(F10:Q10)) -> 63 | U10: =IF($A10="","",IF(T10=0,"Da avviare",IF(R10<0.3,"Copertura base",IF(R10<0.7,"Copertura intermedia","Copertura avanzata")))) -> Copertura avanzata | V10: =IF($A10="","",IF(AND(D10="Prioritaria",R10<0.5),"Alta priorita",IF(AND(D10="Monitoraggio attivo",R10<0.3),"Media priorita",IF(T10=0,"Da avviare","Presidio adeguato")))) -> Presidio adeguato
A11: =IF('03_Tecnologie'!A11="","",'03_Tecnologie'!A11) -> T008 | B11: =IF($A11="","",'03_Tecnologie'!D11) -> Biomasse | C11: =IF($A11="","",'03_Tecnologie'!B11) -> Rinnovabili | D11: =IF($A11="","",'03_Tecnologie'!F11) -> Monitoraggio attivo | E11: =IF($A11="","",COUNTIF('04_Componenti'!$B$4:$B$1000,$A11)) -> 6 | F11: =IF($A11="","",COUNTIF('05_Descrizione'!$B$4:$B$1000,$A11)) -> 6 | G11: =IF($A11="","",COUNTIF('06_Avanzamento'!$B$4:$B$1000,$A11)) -> 6 | H11: =IF($A11="","",COUNTIF('07_TRL_TLR'!$B$4:$B$1000,$A11)) -> 6 | I11: =IF($A11="","",COUNTIF('08_Costi_Compet'!$B$4:$B$1000,$A11)) -> 6 | J11: =IF($A11="","",COUNTIF('09_Settori_Impatto'!$B$4:$B$1000,$A11)) -> 6 | K11: =IF($A11="","",COUNTIF('16_Mercati_Riferimento'!$B$4:$B$1000,$A11)) -> 0 | L11: =IF($A11="","",COUNTIF('10_Sostenibilita'!$B$4:$B$1000,$A11)) -> 3 | M11: =IF($A11="","",COUNTIF('11_Best_Practice'!$B$4:$B$1000,$A11)) -> 4 | N11: =IF($A11="","",COUNTIF('12_Policy_Regolazione'!$B$4:$B$1000,$A11)) -> 5 | O11: =IF($A11="","",COUNTIF('13_Barriere_Opp'!$B$4:$B$1000,$A11)) -> 6 | P11: =IF($A11="","",COUNTIF('14_Attori_Imprese'!$B$4:$B$1000,$A11)) -> 7 | Q11: =IF($A11="","",COUNTIF('15_Prestazioni'!$B$4:$B$1000,$A11)) -> 8 | R11: =IF($A11="","",COUNTIF(F11:Q11,">0")/12) -> 0.91666667 | S11: =IF($A11="","",IFERROR(AVERAGEIF('07_TRL_TLR'!$B$4:$B$1000,$A11,'07_TRL_TLR'!$F$4:$F$1000),"")) -> 8.1666667 | T11: =IF($A11="","",SUM(F11:Q11)) -> 63 | U11: =IF($A11="","",IF(T11=0,"Da avviare",IF(R11<0.3,"Copertura base",IF(R11<0.7,"Copertura intermedia","Copertura avanzata")))) -> Copertura avanzata | V11: =IF($A11="","",IF(AND(D11="Prioritaria",R11<0.5),"Alta priorita",IF(AND(D11="Monitoraggio attivo",R11<0.3),"Media priorita",IF(T11=0,"Da avviare","Presidio adeguato")))) -> Presidio adeguato
A12: =IF('03_Tecnologie'!A12="","",'03_Tecnologie'!A12) -> T009 | B12: =IF($A12="","",'03_Tecnologie'!D12) -> Geotermico | C12: =IF($A12="","",'03_Tecnologie'!B12) -> Rinnovabili | D12: =IF($A12="","",'03_Tecnologie'!F12) -> Monitoraggio attivo | E12: =IF($A12="","",COUNTIF('04_Componenti'!$B$4:$B$1000,$A12)) -> 6 | F12: =IF($A12="","",COUNTIF('05_Descrizione'!$B$4:$B$1000,$A12)) -> 6 | G12: =IF($A12="","",COUNTIF('06_Avanzamento'!$B$4:$B$1000,$A12)) -> 6 | H12: =IF($A12="","",COUNTIF('07_TRL_TLR'!$B$4:$B$1000,$A12)) -> 6 | I12: =IF($A12="","",COUNTIF('08_Costi_Compet'!$B$4:$B$1000,$A12)) -> 6 | J12: =IF($A12="","",COUNTIF('09_Settori_Impatto'!$B$4:$B$1000,$A12)) -> 6 | K12: =IF($A12="","",COUNTIF('16_Mercati_Riferimento'!$B$4:$B$1000,$A12)) -> 0 | L12: =IF($A12="","",COUNTIF('10_Sostenibilita'!$B$4:$B$1000,$A12)) -> 3 | M12: =IF($A12="","",COUNTIF('11_Best_Practice'!$B$4:$B$1000,$A12)) -> 4 | N12: =IF($A12="","",COUNTIF('12_Policy_Regolazione'!$B$4:$B$1000,$A12)) -> 5 | O12: =IF($A12="","",COUNTIF('13_Barriere_Opp'!$B$4:$B$1000,$A12)) -> 6 | P12: =IF($A12="","",COUNTIF('14_Attori_Imprese'!$B$4:$B$1000,$A12)) -> 7 | Q12: =IF($A12="","",COUNTIF('15_Prestazioni'!$B$4:$B$1000,$A12)) -> 8 | R12: =IF($A12="","",COUNTIF(F12:Q12,">0")/12) -> 0.91666667 | S12: =IF($A12="","",IFERROR(AVERAGEIF('07_TRL_TLR'!$B$4:$B$1000,$A12,'07_TRL_TLR'!$F$4:$F$1000),"")) -> 7.3333333 | T12: =IF($A12="","",SUM(F12:Q12)) -> 63 | U12: =IF($A12="","",IF(T12=0,"Da avviare",IF(R12<0.3,"Copertura base",IF(R12<0.7,"Copertura intermedia","Copertura avanzata")))) -> Copertura avanzata | V12: =IF($A12="","",IF(AND(D12="Prioritaria",R12<0.5),"Alta priorita",IF(AND(D12="Monitoraggio attivo",R12<0.3),"Media priorita",IF(T12=0,"Da avviare","Presidio adeguato")))) -> Presidio adeguato
A13: =IF('03_Tecnologie'!A13="","",'03_Tecnologie'!A13) -> T010 | B13: =IF($A13="","",'03_Tecnologie'!D13) -> Nucleare da fissione | C13: =IF($A13="","",'03_Tecnologie'!B13) -> Basse emissioni / transitorie | D13: =IF($A13="","",'03_Tecnologie'!F13) -> Monitoraggio attivo | E13: =IF($A13="","",COUNTIF('04_Componenti'!$B$4:$B$1000,$A13)) -> 6 | F13: =IF($A13="","",COUNTIF('05_Descrizione'!$B$4:$B$1000,$A13)) -> 6 | G13: =IF($A13="","",COUNTIF('06_Avanzamento'!$B$4:$B$1000,$A13)) -> 6 | H13: =IF($A13="","",COUNTIF('07_TRL_TLR'!$B$4:$B$1000,$A13)) -> 6 | I13: =IF($A13="","",COUNTIF('08_Costi_Compet'!$B$4:$B$1000,$A13)) -> 6 | J13: =IF($A13="","",COUNTIF('09_Settori_Impatto'!$B$4:$B$1000,$A13)) -> 6 | K13: =IF($A13="","",COUNTIF('16_Mercati_Riferimento'!$B$4:$B$1000,$A13)) -> 0 | L13: =IF($A13="","",COUNTIF('10_Sostenibilita'!$B$4:$B$1000,$A13)) -> 3 | M13: =IF($A13="","",COUNTIF('11_Best_Practice'!$B$4:$B$1000,$A13)) -> 4 | N13: =IF($A13="","",COUNTIF('12_Policy_Regolazione'!$B$4:$B$1000,$A13)) -> 5 | O13: =IF($A13="","",COUNTIF('13_Barriere_Opp'!$B$4:$B$1000,$A13)) -> 6 | P13: =IF($A13="","",COUNTIF('14_Attori_Imprese'!$B$4:$B$1000,$A13)) -> 7 | Q13: =IF($A13="","",COUNTIF('15_Prestazioni'!$B$4:$B$1000,$A13)) -> 8 | R13: =IF($A13="","",COUNTIF(F13:Q13,">0")/12) -> 0.91666667 | S13: =IF($A13="","",IFERROR(AVERAGEIF('07_TRL_TLR'!$B$4:$B$1000,$A13,'07_TRL_TLR'!$F$4:$F$1000),"")) -> 8 | T13: =IF($A13="","",SUM(F13:Q13)) -> 63 | U13: =IF($A13="","",IF(T13=0,"Da avviare",IF(R13<0.3,"Copertura base",IF(R13<0.7,"Copertura intermedia","Copertura avanzata")))) -> Copertura avanzata | V13: =IF($A13="","",IF(AND(D13="Prioritaria",R13<0.5),"Alta priorita",IF(AND(D13="Monitoraggio attivo",R13<0.3),"Media priorita",IF(T13=0,"Da avviare","Presidio adeguato")))) -> Presidio adeguato
A14: =IF('03_Tecnologie'!A14="","",'03_Tecnologie'!A14) -> T011 | B14: =IF($A14="","",'03_Tecnologie'!D14) -> Idrogeno verde | C14: =IF($A14="","",'03_Tecnologie'!B14) -> Vettori innovativi | D14: =IF($A14="","",'03_Tecnologie'!F14) -> Prioritaria | E14: =IF($A14="","",COUNTIF('04_Componenti'!$B$4:$B$1000,$A14)) -> 7 | F14: =IF($A14="","",COUNTIF('05_Descrizione'!$B$4:$B$1000,$A14)) -> 6 | G14: =IF($A14="","",COUNTIF('06_Avanzamento'!$B$4:$B$1000,$A14)) -> 6 | H14: =IF($A14="","",COUNTIF('07_TRL_TLR'!$B$4:$B$1000,$A14)) -> 6 | I14: =IF($A14="","",COUNTIF('08_Costi_Compet'!$B$4:$B$1000,$A14)) -> 6 | J14: =IF($A14="","",COUNTIF('09_Settori_Impatto'!$B$4:$B$1000,$A14)) -> 6 | K14: =IF($A14="","",COUNTIF('16_Mercati_Riferimento'!$B$4:$B$1000,$A14)) -> 0 | L14: =IF($A14="","",COUNTIF('10_Sostenibilita'!$B$4:$B$1000,$A14)) -> 3 | M14: =IF($A14="","",COUNTIF('11_Best_Practice'!$B$4:$B$1000,$A14)) -> 4 | N14: =IF($A14="","",COUNTIF('12_Policy_Regolazione'!$B$4:$B$1000,$A14)) -> 5 | O14: =IF($A14="","",COUNTIF('13_Barriere_Opp'!$B$4:$B$1000,$A14)) -> 6 | P14: =IF($A14="","",COUNTIF('14_Attori_Imprese'!$B$4:$B$1000,$A14)) -> 7 | Q14: =IF($A14="","",COUNTIF('15_Prestazioni'!$B$4:$B$1000,$A14)) -> 8 | R14: =IF($A14="","",COUNTIF(F14:Q14,">0")/12) -> 0.91666667 | S14: =IF($A14="","",IFERROR(AVERAGEIF('07_TRL_TLR'!$B$4:$B$1000,$A14,'07_TRL_TLR'!$F$4:$F$1000),"")) -> 7.6666667 | T14: =IF($A14="","",SUM(F14:Q14)) -> 63 | U14: =IF($A14="","",IF(T14=0,"Da avviare",IF(R14<0.3,"Copertura base",IF(R14<0.7,"Copertura intermedia","Copertura avanzata")))) -> Copertura avanzata | V14: =IF($A14="","",IF(AND(D14="Prioritaria",R14<0.5),"Alta priorita",IF(AND(D14="Monitoraggio attivo",R14<0.3),"Media priorita",IF(T14=0,"Da avviare","Presidio adeguato")))) -> Presidio adeguato
A15: =IF('03_Tecnologie'!A15="","",'03_Tecnologie'!A15) -> T012 | B15: =IF($A15="","",'03_Tecnologie'!D15) -> 0 | C15: =IF($A15="","",'03_Tecnologie'!B15) -> Rinnovabili | D15: =IF($A15="","",'03_Tecnologie'!F15) -> 0 | E15: =IF($A15="","",COUNTIF('04_Componenti'!$B$4:$B$1000,$A15)) -> 0 | F15: =IF($A15="","",COUNTIF('05_Descrizione'!$B$4:$B$1000,$A15)) -> 0 | G15: =IF($A15="","",COUNTIF('06_Avanzamento'!$B$4:$B$1000,$A15)) -> 0 | H15: =IF($A15="","",COUNTIF('07_TRL_TLR'!$B$4:$B$1000,$A15)) -> 0 | I15: =IF($A15="","",COUNTIF('08_Costi_Compet'!$B$4:$B$1000,$A15)) -> 0 | J15: =IF($A15="","",COUNTIF('09_Settori_Impatto'!$B$4:$B$1000,$A15)) -> 0 | K15: =IF($A15="","",COUNTIF('16_Mercati_Riferimento'!$B$4:$B$1000,$A15)) -> 0 | L15: =IF($A15="","",COUNTIF('10_Sostenibilita'!$B$4:$B$1000,$A15)) -> 0 | M15: =IF($A15="","",COUNTIF('11_Best_Practice'!$B$4:$B$1000,$A15)) -> 0 | N15: =IF($A15="","",COUNTIF('12_Policy_Regolazione'!$B$4:$B$1000,$A15)) -> 0 | O15: =IF($A15="","",COUNTIF('13_Barriere_Opp'!$B$4:$B$1000,$A15)) -> 0 | P15: =IF($A15="","",COUNTIF('14_Attori_Imprese'!$B$4:$B$1000,$A15)) -> 0 | Q15: =IF($A15="","",COUNTIF('15_Prestazioni'!$B$4:$B$1000,$A15)) -> 0 | R15: =IF($A15="","",COUNTIF(F15:Q15,">0")/12) -> 0 | S15: =IF($A15="","",IFERROR(AVERAGEIF('07_TRL_TLR'!$B$4:$B$1000,$A15,'07_TRL_TLR'!$F$4:$F$1000),"")) | T15: =IF($A15="","",SUM(F15:Q15)) -> 0 | U15: =IF($A15="","",IF(T15=0,"Da avviare",IF(R15<0.3,"Copertura base",IF(R15<0.7,"Copertura intermedia","Copertura avanzata")))) -> Da avviare | V15: =IF($A15="","",IF(AND(D15="Prioritaria",R15<0.5),"Alta priorita",IF(AND(D15="Monitoraggio attivo",R15<0.3),"Media priorita",IF(T15=0,"Da avviare","Presidio adeguato")))) -> Da avviare
... A250: =IF('03_Tecnologie'!A250="","",'03_Tecnologie'!A250) | B250: =IF($A250="","",'03_Tecnologie'!D250) | C250: =IF($A250="","",'03_Tecnologie'!B250) | D250: =IF($A250="","",'03_Tecnologie'!F250) | E250: =IF($A250="","",COUNTIF('04_Componenti'!$B$4:$B$1000,$A250)) | F250: =IF($A250="","",COUNTIF('05_Descrizione'!$B$4:$B$1000,$A250)) | G250: =IF($A250="","",COUNTIF('06_Avanzamento'!$B$4:$B$1000,$A250)) | H250: =IF($A250="","",COUNTIF('07_TRL_TLR'!$B$4:$B$1000,$A250)) | I250: =IF($A250="","",COUNTIF('08_Costi_Compet'!$B$4:$B$1000,$A250)) | J250: =IF($A250="","",COUNTIF('09_Settori_Impatto'!$B$4:$B$1000,$A250)) | K250: =IF($A250="","",COUNTIF('16_Mercati_Riferimento'!$B$4:$B$1000,$A250)) | L250: =IF($A250="","",COUNTIF('10_Sostenibilita'!$B$4:$B$1000,$A250)) | M250: =IF($A250="","",COUNTIF('11_Best_Practice'!$B$4:$B$1000,$A250)) | N250: =IF($A250="","",COUNTIF('12_Policy_Regolazione'!$B$4:$B$1000,$A250)) | O250: =IF($A250="","",COUNTIF('13_Barriere_Opp'!$B$4:$B$1000,$A250)) | P250: =IF($A250="","",COUNTIF('14_Attori_Imprese'!$B$4:$B$1000,$A250)) | Q250: =IF($A250="","",COUNTIF('15_Prestazioni'!$B$4:$B$1000,$A250)) | R250: =IF($A250="","",COUNTIF(F250:Q250,">0")/12) | S250: =IF($A250="","",IFERROR(AVERAGEIF('07_TRL_TLR'!$B$4:$B$1000,$A250,'07_TRL_TLR'!$F$4:$F$1000),"")) | T250: =IF($A250="","",SUM(F250:Q250)) | U250: =IF($A250="","",IF(T250=0,"Da avviare",IF(R250<0.3,"Copertura base",IF(R250<0.7,"Copertura intermedia","Copertura avanzata")))) | V250: =IF($A250="","",IF(AND(D250="Prioritaria",R250<0.5),"Alta priorita",IF(AND(D250="Monitoraggio attivo",R250<0.3),"Media priorita",IF(T250=0,"Da avviare","Presidio adeguato"))))

Sheet 00_Portafoglio_Tecnologie
A1: ERMES | Portafoglio tecnologie integrato
A2: Vista sintetica per tecnologia: maturita, competitivita, sostenibilita e copertura informativa.
A4: Tech_ID | B4: Tecnologia | C4: Macro-categoria | D4: Mercato di riferimento | E4: Stato monitoraggio | F4: TRL indicativo | G4: TLR indicativo | H4: LCOE / costo indicativo | I4: GHG lifecycle | J4: Allineamento tassonomia UE | K4: Fonte primaria | L4: Scorecard row
A5: T001 | B5: Carbone | C5: Fossili | D5: Media | E5: Monitoraggio attivo | F5: 9 | G5: Medio in calo | H5: 90-160 EUR/MWh | I5: 1000 gCO2e/kWh | J5: Non allineata | K5: S077 | L5: vedi 00_Scorecard
A6: T002 | B6: Olio | C6: Fossili | D6: Media | E6: Monitoraggio attivo | F6: 9 | G6: Alto ma in calo nei segmenti power | H6: 130-220 EUR/MWh | I6: 780 gCO2e/kWh | J6: Non allineata | K6: S076 | L6: vedi 00_Scorecard
A7: T003 | B7: Gas Naturale | C7: Fossili | D7: Alta | E7: Prioritaria | F7: 9 | G7: Alto ma condizionato da policy climatiche | H7: 70-120 EUR/MWh | I7: 450 gCO2e/kWh | J7: Parzialmente allineata / transitoria | K7: S074 | L7: vedi 00_Scorecard
A8: T004 | B8: Fotovoltaico | C8: Rinnovabili | D8: Alta | E8: Prioritaria | F8: 9 | G8: Alta | H8: Molto competitivo | I8: 23 gCO2e/kWh | J8: Allineata | K8: S012 | L8: vedi 00_Scorecard
A9: T005 | B9: Solare Termico | C9: Rinnovabili | D9: Media | E9: Monitoraggio attivo | F9: 8 | G9: Medio | H9: 110-220 EUR/MWh | I9: 30 gCO2e/kWh | J9: Allineata | K9: S063 | L9: vedi 00_Scorecard
A10: T006 | B10: Eolico | C10: Rinnovabili | D10: Alta | E10: Prioritaria | F10: 9 | G10: Alta | H10: Competitivo | I10: ~10-15 gCO2e/kWh | J10: Allineata | K10: S033 | L10: vedi 00_Scorecard
A11: T007 | B11: Idroelettrico | C11: Rinnovabili | D11: Media | E11: Monitoraggio attivo | F11: 9 | G11: Alto | H11: 40-120 EUR/MWh | I11: 15 gCO2e/kWh | J11: Allineata con DNSH | K11: S068 | L11: vedi 00_Scorecard
A12: T008 | B12: Biomasse | C12: Rinnovabili | D12: Media | E12: Monitoraggio attivo | F12: 8 | G12: Medio-alto | H12: 90-180 EUR/MWh | I12: 70 gCO2e/kWh | J12: Condizionata | K12: S065 | L12: vedi 00_Scorecard
A13: T009 | B13: Geotermico | C13: Rinnovabili | D13: Media | E13: Monitoraggio attivo | F13: 8 | G13: Medio-alto | H13: 45-120 EUR/MWh | I13: 25 gCO2e/kWh | J13: Allineata | K13: S079 | L13: vedi 00_Scorecard
A14: T010 | B14: Nucleare da fissione | C14: Basse emissioni / transitorie | D14: Media | E14: In approfondimento | F14: 8 | G14: Medio-alto | H14: 90-180 EUR/MWh | I14: 12 gCO2e/kWh | J14: Condizionata | K14: S070 | L14: vedi 00_Scorecard
A15: T011 | B15: Idrogeno verde | C15: Vettori innovativi | D15: Alta | E15: Prioritaria | F15: 7-8 | G15: In crescita | H15: Fuel cost-driven | I15: molto dipende da power input | J15: Allineabile | K15: S048 | L15: vedi 00_Scorecard

Sheet 00_Guida
A1: ERMES | Template database informativo per l'Osservatorio Tecnologie Energetiche Emergenti
A2: Workbook strutturato per raccogliere dati su tecnologie, componenti, costi, sostenibilita, policy, attori e prestazioni. In questa versione manageriale apri prima 00_Executive, poi 00_Dashboard e 00_Scorecard.
A3: Navigazione consigliata: 00_Dashboard -> 00_Scorecard -> fogli tematici (05-15) -> 16_Log_Aggiornamenti
A4: 1. Logica del database | E4: 3. Filtro analitico ERMES
A5: • Ogni riga rappresenta una singola evidenza / osservazione. | E5: • Technology Watch
A6: • Le anagrafiche base sono: 02_Fonti, 03_Tecnologie, 04_Componenti. | E6: • Horizon Scanning
A7: • I fogli 05-15 raccolgono i dati tematici richiesti da ERMES. | E7: • P-TEA (assessment preliminare)
A8: • Usa sempre Tech_ID e, quando serve, Comp_ID per collegare i record. | E8: • Disseminazione / reporting
A11: 2. Regole di compilazione | E11: 4. Fogli del workbook
A12: • Compila i campi in blu (input manuale). I campi in nero sono formule di supporto. | E12: • 02_Fonti: repertorio delle fonti informative.
A13: • Una tecnologia va descritta in modo sintetico; i dettagli analitici vanno nei fogli tematici. | E13: • 03_Tecnologie: elenco delle tecnologie osservate.
A14: • Cita sempre una Fonte_ID presente nel foglio 02_Fonti e, se utile, aggiungi URL o note. | E14: • 04_Componenti: macrocomponenti / sottosistemi.
A15: • Formato data consigliato: YYYY-MM-DD. | E15: • 05-15: raccolta strutturata delle 11 aree informative richieste.
A16: • TRL/TLR: nel workbook è usata la scala standard 1-9. | E16: • 16_Log_Aggiornamenti: storico operativo degli aggiornamenti.
A18: 5. Convenzione minima consigliata per gli ID | E18: 6. Legenda colori
A19: Tech_ID | B19: T004 | C19: Fotovoltaico | E19: Input manuale | F19: esempio
A20: Comp_ID | B20: C-FV-001 | C20: Modulo FV | E20: Formula / supporto | F20: esempio
A21: Record_ID | B21: R-COST-0001 | C21: Prima osservazione costi | E21: Valori statici / anagrafiche | F21: esempio
E22: Istruzioni / attenzione | F22: esempio
A24: Fonti informative di base già precaricate nel foglio 02_Fonti: IEA, MIT Technology Review, Gartner, WEF, Cleantechnica, SETIS, JRC, BloombergNEF, Energy Innovation, NREL.
A25: Aggiornamento struttura: eliminata la colonna "Priorità ERMES"; aggiunto il foglio "09bis_Mercati_Riferimento" per valutare applicabilità in Paesi sviluppati, Paesi in via di sviluppo o entrambi.

Sheet 01_Liste
A1: MacroCategorie | B1: StatoMonitoraggio | C1: LivelloAnalisi | D1: FaseSviluppo | E1: MetricheCosto | F1: SettoriEconomici | G1: TipiPolicy | H1: CategorieBarriere | I1: TipiAttore | J1: KPI_Tecnici | K1: Geografie | L1: Mercato di riferimento | M1: TipiFonte | N1: Affidabilita | O1: TassonomiaUE | P1: FrequenzeAgg | Q1: AccessoFonte | R1: AzioniLog | S1: TRL | T1: Booleane | U1: Valute | V1: Trend | W1: IntensitaImpatto | X1: Orizzonti | Y1: StatiPolicy | Z1: BarrieraOOpportunita | AA1: EsitoVerifica
A2: Fossili | B2: Monitoraggio attivo | C2: Tecnologia | D2: Ricerca di base | E2: CAPEX | F2: Agricoltura | G2: Strategia | H2: Tecnologica | I2: Azienda | J2: Efficienza energetica | K2: Italia | L2: PS (Paesi Sviluppati) | M2: Report istituzionale | N2: 1 | O2: Allineata | P2: Continuativa | Q2: Pubblica | R2: Nuovo record | S2: 1 | T2: Sì | U2: EUR | V2: In calo | W2: Alta | X2: Breve termine | Y2: In vigore | Z2: Barriera | AA2: Da verificare
A3: Rinnovabili | B3: Archiviata | C3: Componente | D3: Proof of concept | E3: OPEX | F3: Industria | G3: Legge | H3: Economica | I3: OEM | J3: Scalabilità | K3: UE | L3: PVS Paesi in Via di Sviluppo) | M3: Paper scientifico | N3: 2 | O3: Parzialmente allineata | P3: Mensile | Q3: Abbonamento | R3: Aggiornamento | S3: 2 | T3: No | U3: USD | V3: Stabile | W3: Media | X3: Medio termine | Y3: In consultazione | Z3: Opportunità | AA3: Verificato
A4: Nucleare | C4: Sottosistema | D4: Prototipo laboratorio | E4: LCOE | F4: Trasporti | G4: Decreto | H4: Regolatoria | I4: Utility | J4: Disponibilità | K4: USA | M4: Database | N4: 3 | O4: Non allineata | P4: Trimestrale | Q4: Interna | R4: Validazione | S4: 3 | T4: Parziale | U4: GBP | V4: In aumento | W4: Bassa | X4: Lungo termine | Y4: In revisione | AA4: Parzialmente verificato
A5: Idrogeno | D5: Pilota / dimostratore | E5: LCOS | F5: Edilizia | G5: Regolazione | H5: Infrastrutturale | I5: Startup | J5: Durata utile | K5: Cina | M5: News / media specializzato | N5: 4 | O5: Da verificare | P5: Semestrale | Q5: Mista | R5: Correzione | S5: 4 | U5: Altro | V5: Volatile | Y5: Scaduta
A6: Altro | D6: FOAK (First of a kind) | E6: TCO | F6: Pubblica Amministrazione | G6: Incentivo | H6: Supply chain | I6: Centro di ricerca | J6: Emissioni dirette | K6: Asia-Pacifico | M6: Documento normativo | N6: 5 | P6: Annuale | R6: Archiviazione | S6: 5
D7: Commerciale iniziale | E7: Trend costo | F7: Utility | G7: Standard tecnico | H7: Sociale | I7: Università | J7: Fattore di capacità | K7: Globale | M7: Sito corporate | P7: Ad hoc | S7: 6
D8: Commerciale diffusa | E8: Incentivi | F8: Residenziale | G8: Tassonomia | H8: Competenze | I8: Ente pubblico | J8: Densità energetica | K8: Altro | M8: Intervista esperto | S8: 7
E9: Altro | F9: Altro | G9: Altro | H9: Opportunità | I9: Investitore | J9: Altro | M9: Altro | S9: 8
I10: Associazione | J10: Ramp rate | S10: 9
I11: Altro | J11: Round-trip efficiency
J12: Heat rate
J13: Capture rate CO2
J14: Ore di accumulo termico
J15: Vita utile tecnica

Sheet 02_Fonti
A1: 02_Fonti | Repertorio fonti informative
A2: Precaricate le principali fonti esplicitate nel brief. Aggiungere qui eventuali fonti FEEM / interne / di progetto prima di usarle nei fogli analitici.
A3: Source_ID | B3: Nome fonte | C3: Categoria fonte | D3: Organizzazione | E3: URL | F3: Copertura / ambito | G3: Frequenza agg. | H3: Accesso | I3: Affidabilità (1-5) | J3: Note operative
A4: S001 | B4: IEA - Tracking Clean Energy Progress | C4: Report istituzionale | D4: IEA | E4: https://www.iea.org/topics/tracking-clean-energy-progress | F4: monitoraggio progresso clean energy | G4: Continuativa | H4: Pubblica | I4: 5 | J4: Fonte istituzionale di monitoraggio
A5: S002 | B5: IEA - Technology Innovation | C5: Report istituzionale | D5: IEA | E5: https://www.iea.org/topics/technology-innovation | F5: rapporti e analisi su innovazione energetica | G5: Continuativa | H5: Pubblica | I5: 5
A6: S003 | B6: MIT Technology Review | C6: News / media specializzato | D6: MIT Technology Review | E6: https://www.technologyreview.com/ | F6: trend e segnali deboli tecnologici | G6: Continuativa | H6: Pubblica | I6: 3 | J6: utile per horizon scanning
A7: S004 | B7: Gartner - Hype Cycle | C7: Report istituzionale | D7: Gartner | E7: https://www.gartner.com/en/research/methodologies/gartner-hype-cycle | F7: maturità e hype di tecnologie | G7: Annuale | H7: Abbonamento | I7: 4
A8: S005 | B8: World Economic Forum - Strategic Intelligence | C8: Database | D8: World Economic Forum | E8: https://intelligence.weforum.org/ | F8: trend, temi strategici e correlazioni | G8: Continuativa | H8: Pubblica | I8: 3
A9: S006 | B9: Cleantechnica | C9: News / media specializzato | D9: Cleantechnica | E9: https://cleantechnica.com/ | F9: notizie e casi applicativi clean tech | G9: Continuativa | H9: Pubblica | I9: 2 | J9: da validare sempre con fonti primarie
A10: S007 | B10: SETIS - Strategic Energy Technology Information System | C10: Database | D10: Commissione Europea | E10: https://setis.ec.europa.eu/ | F10: informazioni su tecnologie SET europee | G10: Continuativa | H10: Pubblica | I10: 5
A11: S008 | B11: JRC - Technology Innovation Watch | C11: Report istituzionale | D11: Joint Research Centre | E11: https://ec.europa.eu/jrc/en/research-topic/energy-technologies-and-innovation | F11: sorveglianza innovazione tecnologica | G11: Continuativa | H11: Pubblica | I11: 5
A12: S009 | B12: BloombergNEF | C12: Database | D12: BloombergNEF | E12: https://about.bnef.com/ | F12: mercati, costi, investimenti, benchmark | G12: Continuativa | H12: Abbonamento | I12: 5
A13: S010 | B13: Energy Innovation - Technology Policy Insights | C13: Report istituzionale | D13: Energy Innovation | E13: https://energyinnovation.org/our-work/energy-policy-solutions/ | F13: policy insight e technology policy | G13: Continuativa | H13: Pubblica | I13: 4
A14: S011 | B14: NREL Research | C14: Report istituzionale | D14: NREL | E14: https://www.nrel.gov/research/ | F14: ricerca applicata e benchmark tecnologici | G14: Continuativa | H14: Pubblica | I14: 5
A15: S012 | B15: IEA - Solar PV | C15: Report istituzionale | D15: IEA | E15: https://www.iea.org/energy-system/renewables/solar-pv | F15: quadro globale PV: mercato, generazione, outlook | G15: Continuativa | H15: Pubblica | I15: 5 | J15: fonte primaria per scenario e ruolo della tecnologia
A16: S013 | B16: NREL - Spring 2025 Solar Industry Update | C16: Report istituzionale | D16: NREL | E16: https://docs.nrel.gov/docs/fy25osti/95135.pdf | F16: mercato globale PV, trend industriali e roadmap | G16: Periodica | H16: Pubblica | I16: 5 | J16: fonte utile per horizon scanning e trend 2024-2025
A17: S014 | B17: NREL - Fall 2024 Solar Industry Update | C17: Report istituzionale | D17: NREL | E17: https://docs.nrel.gov/docs/fy25osti/92257.pdf | F17: benchmark costi PV, ibridazione con storage, tracker | G17: Periodica | H17: Pubblica | I17: 5 | J17: fonte di benchmark costi e configurazioni di impianto
A18: S015 | B18: NREL - Updated Life Cycle Assessment and Techno-Economic Analysis of Utility-Scale PV | C18: Report istituzionale | D18: NREL | E18: https://docs.nrel.gov/docs/fy24osti/87372.pdf | F18: LCA, emissioni lifecycle, energy payback, costi benchmark | G18: Periodica | H18: Pubblica | I18: 5 | J18: fonte primaria per sostenibilita ambientale
A19: S016 | B19: Fraunhofer ISE - Photovoltaics Report | C19: Report istituzionale | D19: Fraunhofer ISE | E19: https://www.ise.fraunhofer.de/content/dam/ise/de/documents/publications/studies/Photovoltaics-Report.pdf | F19: prestazioni, efficienze, andamento mercato PV | G19: Periodica | H19: Pubblica | I19: 5 | J19: riferimento tecnico europeo sulle performance
A20: S017 | B20: VDMA - International Technology Roadmap for Photovoltaic (ITRPV) | C20: Roadmap industriale | D20: VDMA | E20: https://www.vdma.org/international-technology-roadmap-photovoltaic | F20: roadmap tecnologica moduli, celle, costi, supply chain | G20: Annuale | H20: Pubblica | I20: 5 | J20: fonte chiave su maturita e transizione PERC/TOPCon/tandem
A21: S018 | B21: European Commission - Renewable Energy Directive (RED III) | C21: Normativa UE | D21: Commissione Europea | E21: https://energy.ec.europa.eu/topics/renewable-energy/renewable-energy-directive-targets-and-rules/renewable-energy-directive_en | F21: quadro normativo UE per rinnovabili, permitting, target 2030 | G21: Continuativa | H21: Pubblica | I21: 5 | J21: policy di cornice per diffusione FV
A22: S019 | B22: European Commission - Net-Zero Industry Act | C22: Normativa UE | D22: Commissione Europea | E22: https://single-market-economy.ec.europa.eu/industry/sustainability/net-zero-industry-act_en | F22: manifattura cleantech UE, permitting, resilience e aste | G22: Continuativa | H22: Pubblica | I22: 5 | J22: rilevante per filiera FV e componenti
A23: S020 | B23: GSE - Configurazioni per autoconsumo diffuso e CER | C23: Normativa/Incentivi | D23: GSE | E23: https://www.gse.it/servizi-per-te/autoconsumo/gruppi-di-autoconsumatori-e-comunita-di-energia-rinnovabile | F23: regole operative autoconsumo, CER, tariffa incentivante e PNRR | G23: Continuativa | H23: Pubblica | I23: 5 | J23: riferimento operativo per mercato italiano distribuito
A24: S021 | B24: JRC - Deep Dive on Critical Raw Materials for Solar Photovoltaics in the EU | C24: Report istituzionale | D24: Joint Research Centre | E24: https://publications.jrc.ec.europa.eu/repository/handle/JRC141760 | F24: materie prime critiche, supply chain e resilienza filiera FV | G24: Periodica | H24: Pubblica | I24: 5 | J24: riferimento per rischio materiali e circolarita
A25: S022 | B25: European Commission - EU Taxonomy for sustainable activities | C25: Normativa UE | D25: Commissione Europea | E25: https://finance.ec.europa.eu/sustainable-finance/tools-and-standards/eu-taxonomy-sustainable-activities_en | F25: criteri di sostenibilita e accesso alla finanza sostenibile | G25: Continuativa | H25: Pubblica | I25: 5 | J25: utile per compatibilita tassonomia UE
A26: S023 | B26: Al Dhafra Solar PV Project | C26: Caso applicativo | D26: ADPV2 / EWEC / EDF Renewables / Jinko Power | E26: https://www.adpv2.ae/solar-project | F26: mega-impianto utility-scale con tariffa record | G26: Continuativa | H26: Pubblica | I26: 4 | J26: best practice utility-scale in area MENA
... A124: S121 | B124: Yuhuan power plant | C124: Caso applicativo | D124: China Energy | E124: https://www.ceic.com/ | F124: impianto ultrasupercritico di grande taglia | G124: Continuativa | H124: Pubblica | I124: 3 | J124: best practice coal efficiency

Sheet 03_Tecnologie
A1: 03_Tecnologie | Anagrafica tecnologie osservate
A2: Precaricato l’elenco base delle tecnologie emerse nel brief. Integrare con nuove tecnologie mantenendo un Tech_ID univoco e stabile.
A3: Tech_ID | B3: Macro-categoria | C3: Cluster | D3: Tecnologia | E3: Descrizione sintetica | F3: Stato monitoraggio | G3: Geografia focus | H3: Mercato di riferimento | I3: Link approfondimento | J3: Fonte_ID primaria | K3: Ultimo aggiornamento | L3: Responsabile
A4: T001 | B4: Fossili | C4: Fonti fossili | D4: Carbone | E4: Tecnologia fossile matura usata soprattutto per generazione elettrica e processi industriali ad alta intensita energetica; in molti mercati e in declino regolatorio ma ancora rilevante per sicurezza e baseload. | F4: Monitoraggio attivo | G4: Globale | I4: https://www.iea.org/energy-system/fossil-fuels/coal | J4: S077
A5: T002 | B5: Fossili | C5: Fonti fossili | D5: Olio | E5: Tecnologia fossile consolidata che alimenta soprattutto mobilita, calore e parte della generazione di backup; strategicamente rilevante ma esposta a forte pressione climatica e di efficienza. | F5: Archiviata | G5: Globale | I5: https://www.iea.org/energy-system/fossil-fuels/oil | J5: S076
A6: T003 | B6: Fossili | C6: Fonti fossili / transitoria | D6: Gas Naturale | E6: Tecnologia fossile flessibile e programmabile, centrale per bilanciamento del sistema elettrico, calore industriale e sicurezza energetica; in UE e considerata fonte transitoria sotto condizioni stringenti. | F6: Monitoraggio attivo | G6: Italia / UE | I6: https://www.iea.org/energy-system/fossil-fuels/natural-gas | J6: S074
A7: T004 | B7: Rinnovabili | C7: Solare | D7: Fotovoltaico | E7: Tecnologia di generazione elettrica che converte la radiazione solare in elettricità tramite celle semiconduttrici. Applicabile su scala utility, C&I, residenziale, floating e agrivoltaica. | F7: Monitoraggio attivo | G7: Globale | I7: https://www.iea.org/energy-system/renewables/solar-pv | J7: S012 | K7: 2026-03-28
A8: T005 | B8: Rinnovabili | C8: Solare | D8: Solare Termico | E8: Tecnologia che converte l irraggiamento solare in calore utile o in elettricita tramite concentrazione; include collettori per acqua calda/process heat e CSP con accumulo termico per generazione programmabile. | F8: Monitoraggio attivo | G8: MENA / UE | I8: https://atb.nrel.gov/electricity/2024/concentrating_solar_power | J8: S063
A9: T006 | B9: Rinnovabili | C9: Elettricità rinnovabile | D9: Eolico | E9: Tecnologia di generazione elettrica che converte l energia cinetica del vento in elettricita tramite aerogeneratori onshore e offshore, inclusi sistemi floating in acque profonde. | F9: Monitoraggio attivo | G9: Globale | I9: https://www.iea.org/energy-system/renewables/wind | J9: S033 | K9: 2026-03-28
A10: T007 | B10: Rinnovabili | C10: Elettricita rinnovabile | D10: Idroelettrico | E10: Tecnologia rinnovabile matura e programmabile che sfrutta salti idraulici, invasi o impianti ad acqua fluente; chiave per flessibilita, riserva e servizi di rete, inclusi sistemi di pompaggio. | F10: Monitoraggio attivo | G10: Globale | I10: https://www.iea.org/energy-system/renewables/hydroelectricity | J10: S068
A11: T008 | B11: Rinnovabili | C11: Bioenergia | D11: Biomasse | E11: Famiglia di tecnologie che valorizza biomasse solide, biogas, biometano e residui organici per produrre elettricita, calore, gas rinnovabili e combustibili avanzati, con forte dipendenza dalla sostenibilita della filiera. | F11: Monitoraggio attivo | G11: UE / Italia | I11: https://www.iea.org/energy-system/renewables/bioenergy | J11: S065
A12: T009 | B12: Rinnovabili | C12: Calore / elettricita rinnovabile | D12: Geotermico | E12: Tecnologia che sfrutta il calore del sottosuolo per generare elettricita e calore; oggi basata su risorse idrotermali ma in forte attenzione per EGS e closed-loop di nuova generazione. | F12: Monitoraggio attivo | G12: UE / Globale | I12: https://www.iea.org/reports/the-future-of-geothermal-energy | J12: S079
A13: T010 | B13: Basse emissioni / transitorie | C13: Nucleare | D13: Nucleare da fissione | E13: Tecnologia a basse emissioni lifecycle per generazione elettrica e potenzialmente calore industriale; elevata intensita di capitale, forte rilevanza per sicurezza energetica, con nuova attenzione verso Gen III+ e SMR. | F13: Monitoraggio attivo | G13: UE / Globale | I13: https://www.iea.org/energy-system/electricity/nuclear-power | J13: S070
A14: T011 | B14: Vettori innovativi | C14: Idrogeno | D14: Idrogeno verde | E14: Vettore energetico prodotto per elettrolisi dell acqua alimentata da elettricita rinnovabile; rilevante per industria hard-to-abate, chimica, fertilizzanti e alcuni trasporti pesanti. | F14: Prioritaria | G14: UE / Globale | I14: https://www.iea.org/energy-system/low-emission-fuels/hydrogen | J14: S048 | K14: 2026-03-28
A15: T012 | B15: Rinnovabili

Sheet 04_Componenti
A1: 04_Componenti | Anagrafica componenti e sottosistemi
A2: Starter list con alcuni componenti esemplificativi. Puoi estendere l’anagrafica aggiungendo righe mantenendo Comp_ID stabili e univoci.
A3: Comp_ID | B3: Tech_ID | C3: Tecnologia | D3: Macrocomponente | E3: Componente / Sottosistema | F3: Descrizione sintetica | G3: Funzione | H3: Stato componente | I3: Fonte_ID | J3: Ultimo aggiornamento | K3: Note
A4: C-FV-001 | B4: T004 | C4: Fotovoltaico | D4: Generazione | E4: Modulo FV | F4: Elemento attivo composto da celle, vetro, encapsulante e frame; oggi dominano soluzioni bifacciali e n-type. | G4: Conversione della radiazione in corrente continua | H4: Commerciale diffusa | I4: S016 | J4: 2026-03-28 | K4: mainstream c-Si; transizione rapida verso TOPCon
A5: C-FV-002 | B5: T004 | C5: Fotovoltaico | D5: Elettronica di potenza | E5: Inverter | F5: Converte la corrente continua in alternata e abilita controllo, protezione e servizi di rete. | G5: Conversione DC/AC, controllo e grid support | H5: Commerciale diffusa | I5: S027 | J5: 2026-03-28 | K5: piattaforme 1500 V e funzioni smart inverter
A6: C-FV-003 | B6: T004 | C6: Fotovoltaico | D6: Accumulo / backup | E6: Sistema di backup / accumulo | F6: Batterie e PCS integrati con il FV per continuità, peak shaving e riduzione curtailment. | G6: Flessibilità, backup e ottimizzazione energetica | H6: Commerciale iniziale | I6: S014 | J6: 2026-03-28 | K6: crescita rapida nei sistemi ibridi PV+BESS
A7: C-ST-001 | B7: T005 | C7: Solare Termico | D7: Captazione solare | E7: Campo collettori / eliostati | F7: Superficie ottica che concentra o raccoglie la radiazione solare. | G7: Raccolta energia solare | H7: Commerciale diffusa | I7: S063 | J7: 2026-03-29 | K7: starter
A8: C-ST-002 | B8: T005 | C8: Solare Termico | D8: Accumulo termico | E8: Serbatoio / TES termico | F8: Accumulo caldo/freddo o molten salt per spostare produzione nel tempo. | G8: Dispatchability e spostamento energetico | H8: Commerciale diffusa | I8: S063 | J8: 2026-03-29 | K8: starter
A9: C-FV-004 | B9: T004 | C9: Fotovoltaico | D9: Inseguimento / BOS | E9: Tracker monoassiale | F9: Struttura mobile che aumenta la produzione seguendo il sole, molto diffusa negli impianti utility-scale. | G9: Incremento resa energetica | H9: Commerciale diffusa | I9: S014 | J9: 2026-03-28 | K9: standard di mercato in molti impianti a terra
A10: C-FV-005 | B10: T004 | C10: Fotovoltaico | D10: BOS / connessione | E10: Strutture e BOS | F10: Cabling, quadri, trasformatori, protezioni e opere elettromeccaniche di impianto. | G10: Installazione, connessione e sicurezza | H10: Commerciale diffusa | I10: S014 | J10: 2026-03-28 | K10: determinante per costi e tempi di connessione
A11: C-FV-006 | B11: T004 | C11: Fotovoltaico | D11: Modulo avanzato | E11: Modulo tandem perovskite-silicio | F11: Nuova generazione di moduli ad altissima efficienza, oggi in fase di scale-up industriale iniziale. | G11: Aumento efficienza e riduzione impronta materiale per kWh | H11: FOAK / pre-commerciale | I11: S017 | J11: 2026-03-28 | K11: alto potenziale ma sfide su stabilità e durabilità
A12: C-FV-007 | B12: T004 | C12: Fotovoltaico | D12: Applicazione integrata | E12: Sistema agrivoltaico | F12: Configurazione integrata FV + attività agricola con progettazione per dual land use. | G12: Co-produzione di energia e valore agricolo | H12: Pilota / dimostratore | I12: S026 | J12: 2026-03-28 | K12: in sviluppo regolatorio e tecnico
A13: C-GEO-001 | B13: T009 | C13: Geotermico | D13: Reservoir | E13: Esplorazione e modellazione serbatoio | F13: Geofisica, geologia e reservoir simulation. | G13: Riduzione rischio geologico | H13: Commerciale iniziale | I13: S079 | J13: 2026-03-29 | K13: starter
A14: C-NUC-001 | B14: T010 | C14: Nucleare da fissione | D14: Nuclear island | E14: Reattore e vessel | F14: Core, vessel e sistema nucleare principale. | G14: Fissione controllata e produzione calore | H14: Commerciale diffusa | I14: S070 | J14: 2026-03-29 | K14: starter
... A24: C-WI-007 | B24: T006 | C24: Eolico | D24: Grid connection | E24: Sottostazione e connessione di rete | F24: Trasformatori, sottostazioni offshore/onshore e cavi HVAC/HVDC necessari per evacuare la produzione. | G24: Connessione alla rete e integrazione di sistema | H24: Commerciale diffusa | I24: S038 | J24: 2026-03-28 | K24: driver critico per time-to-market offshore
A25: C-CO-001 | B25: T001 | C25: Carbone | D25: Supply | E25: Estrazione e preparazione | F25: Mining, washing e handling del carbone con controllo qualita combustibile. | G25: Fornitura combustibile e riduzione impurita | H25: Commerciale diffusa | I25: S077 | J25: 2026-03-29
A26: C-CO-002 | B26: T001 | C26: Carbone | D26: Combustione | E26: Caldaia PC / USC | F26: Boiler a polverino, supercritical o ultrasupercritical per migliorare efficienza. | G26: Generazione vapore ad alta temperatura e pressione | H26: Commerciale diffusa | I26: S075 | J26: 2026-03-29
A27: C-CO-003 | B27: T001 | C27: Carbone | D27: Turbina | E27: Turbina a vapore e generatore | F27: Isola convenzionale di conversione termoelettrica. | G27: Conversione meccanica ed elettrica | H27: Commerciale diffusa | I27: S075 | J27: 2026-03-29
A28: C-H2-004 | B28: T011 | C28: Idrogeno verde | D28: Balance of Plant | E28: Rettificatori, acqua e ausiliari di processo | F28: Include conversione elettrica, deionizzazione, raffreddamento, separazione gas e sicurezza. | G28: Supporto al funzionamento dello stack | H28: Commerciale diffusa | I28: S055 | J28: 2026-03-28 | K28: spesso quota rilevante del CAPEX totale
A29: C-H2-005 | B29: T011 | C29: Idrogeno verde | D29: Midstream | E29: Compressione e stoccaggio H2 | F29: Compressori, serbatoi e sistemi di accumulo per buffer operativo, distribuzione e flessibilita. | G29: Condizionamento e disponibilita del vettore | H29: Commerciale iniziale | I29: S049 | J29: 2026-03-28 | K29: cruciale per utilizzi continui e logistica
A30: C-H2-006 | B30: T011 | C30: Idrogeno verde | D30: Logistica | E30: Trasporto e distribuzione | F30: Tube trailer, pipeline, liquefazione o conversione in vettori come ammoniaca per movimentazione a distanza. | G30: Consegna del vettore ai siti di uso finale | H30: Commerciale iniziale | I30: S049 | J30: 2026-03-28 | K30: maturita variabile per soluzione e distanza
A31: C-H2-007 | B31: T011 | C31: Idrogeno verde | D31: Controllo sistema | E31: Energy management e integrazione con rinnovabili | F31: EMS e logiche di dispatch che coordinano elettrolizzatore, rinnovabili, rete e stoccaggi. | G31: Ottimizzazione LCOH e flessibilita di esercizio | H31: Commerciale iniziale | I31: S049 | J31: 2026-03-28 | K31: determinante per profilo di utilizzo e business case
A32: C-CO-004 | B32: T001 | C32: Carbone | D32: Controllo emissioni | E32: FGD / SCR / ESP | F32: Sistemi di abbattimento SOx, NOx, polveri e mercurio. | G32: Conformita ambientale | H32: Commerciale diffusa | I32: S075 | J32: 2026-03-29
A33: C-CO-005 | B33: T001 | C33: Carbone | D33: Decarbonizzazione | E33: CCS retrofit | F33: Cattura post-combustione e compressione CO2 su impianti esistenti o nuovi. | G33: Riduzione emissioni lifecycle e direct stack | H33: FOAK / pre-commerciale | I33: S118 | J33: 2026-03-29
A34: C-CO-006 | B34: T001 | C34: Carbone | D34: Materiali avanzati | E34: AUSC materials | F34: Materiali e componenti per temperature piu elevate e maggiore efficienza. | G34: Aumento efficienza e affidabilita | H34: Pilota / dimostratore | I34: S075 | J34: 2026-03-29
A35: C-OI-001 | B35: T002 | C35: Olio | D35: Upstream | E35: Produzione ed estrazione | F35: Pozzi, gathering e separazione primaria del greggio. | G35: Fornitura feedstock liquidi | H35: Commerciale diffusa | I35: S076 | J35: 2026-03-29
A36: C-OI-002 | B36: T002 | C36: Olio | D36: Midstream | E36: Stoccaggio e logistica | F36: Tank farm, terminali, shipping e pipeline per greggio e prodotti. | G36: Movimentazione e sicurezza di approvvigionamento | H36: Commerciale diffusa | I36: S076 | J36: 2026-03-29
A37: C-OI-003 | B37: T002 | C37: Olio | D37: Downstream | E37: Raffinazione | F37: Distillazione, cracking, hydrotreating e upgrading prodotti. | G37: Produzione carburanti e feedstock | H37: Commerciale diffusa | I37: S114 | J37: 2026-03-29
A38: C-OI-004 | B38: T002 | C38: Olio | D38: Uso finale | E38: Motori / turbine oil-fired | F38: Tecnologie di combustione per trasporti, backup e alcuni mercati insulari. | G38: Conversione energetica finale | H38: Commerciale diffusa | I38: S076 | J38: 2026-03-29
A39: C-OI-005 | B39: T002 | C39: Olio | D39: Efficienza | E39: Cogen e heat integration | F39: Recuperi termici, cogenerazione e digital energy management in raffineria. | G39: Riduzione consumi ed emissioni | H39: Commerciale diffusa | I39: S115 | J39: 2026-03-29
A40: C-OI-006 | B40: T002 | C40: Olio | D40: Abatement | E40: Flare and methane monitoring | F40: Tecnologie LDAR, riduzione flaring e monitoraggio perdite. | G40: Riduzione emissioni fuggitive | H40: Commerciale iniziale | I40: S116 | J40: 2026-03-29
A41: C-GA-001 | B41: T003 | C41: Gas Naturale | D41: Produzione e supply | E41: Upstream / LNG / import | F41: Filiera di produzione, liquefazione, rigassificazione e importazione gas. | G41: Sicurezza di approvvigionamento | H41: Commerciale diffusa | I41: S087 | J41: 2026-03-29
A42: C-GA-002 | B42: T003 | C42: Gas Naturale | D42: Generazione | E42: Turbina a gas simple cycle | F42: Macchine flessibili per picco e servizi ancillari. | G42: Peak load e fast ramping | H42: Commerciale diffusa | I42: S075 | J42: 2026-03-29
A43: C-GA-003 | B43: T003 | C43: Gas Naturale | D43: Generazione | E43: CCGT H/F class | F43: Cicli combinati ad alta efficienza per mid-merit e baseload flessibile. | G43: Generazione efficiente e modulabile | H43: Commerciale diffusa | I43: S075 | J43: 2026-03-29
... A72: C-NUC-006 | B72: T010 | C72: Nucleare da fissione | D72: Advanced nuclear | E72: SMR / modular factory | F72: Componenti modularizzati e architetture di piccola taglia. | G72: Riduzione tempi e scala di deployment | H72: FOAK / pre-commerciale | I72: S085 | J72: 2026-03-29

Sheet 05_Descrizione
A1: 05_Descrizione | Profilo sintetico tecnologia / componente
A2: Area 1 del brief: descrizione sintetica della tecnologia o del componente con rimando a eventuali approfondimenti.
A3: Record_ID | B3: Tech_ID | C3: Tecnologia | D3: Comp_ID (opz.) | E3: Livello analisi | F3: Tecnologia / elemento osservato | G3: Descrizione sintetica | H3: Ambito applicativo | I3: Link approfondimento | J3: Fonte_ID | K3: Data rilevazione | L3: Analista | M3: Note
A4: DESC-FV-001 | B4: T004 | C4: Fotovoltaico | E4: Tecnologia | F4: Fotovoltaico | G4: Tecnologia elettrica rinnovabile modulare, scalabile e oggi fra le opzioni piu competitive per nuova capacità di generazione. | H4: Utility-scale, C&I, residenziale, floating, agrivoltaico | I4: https://www.iea.org/energy-system/renewables/solar-pv | J4: S012 | K4: 2026-03-28 | M4: caso pilota ERMES
A5: DESC-FV-002 | B5: T004 | C5: Fotovoltaico | D5: C-FV-001 | E5: Componente | F5: Modulo FV | G5: Componente che converte la radiazione in corrente continua; il mercato si sposta verso moduli bifacciali e celle n-type. | H5: Nuovi impianti e repowering | I5: https://www.ise.fraunhofer.de/content/dam/ise/de/documents/publications/studies/Photovoltaics-Report.pdf | J5: S016 | K5: 2026-03-28 | M5: focus su efficienza e affidabilita
A6: DESC-FV-003 | B6: T004 | C6: Fotovoltaico | D6: C-FV-002 | E6: Componente | F6: Inverter | G6: Nodo elettronico che governa conversione DC/AC, sicurezza, monitoraggio e servizi di rete. | H6: Impianti distribuiti e utility-scale | I6: https://en.sungrowpower.com/productDetail/4102/1-x-modular-inverter-sg1100ud-20 | J6: S027 | K6: 2026-03-28 | M6: abilitatore di grid support e ibridazione
A7: DESC-FV-004 | B7: T004 | C7: Fotovoltaico | D7: C-FV-003 | E7: Componente | F7: Sistema di backup / accumulo | G7: Sistema di accumulo elettrochimico integrato al FV per aumentare autoconsumo, resilienza e valore di sistema. | H7: Residenziale, C&I, utility-scale ibrido | I7: https://docs.nrel.gov/docs/fy25osti/92257.pdf | J7: S014 | K7: 2026-03-28 | M7: componente chiave contro curtailment e picchi
A8: DESC-FV-005 | B8: T004 | C8: Fotovoltaico | D8: C-FV-004 | E8: Componente | F8: Tracker monoassiale | G8: Sistema meccanico di inseguimento che aumenta il fattore di capacità negli impianti a terra. | H8: Utility-scale a terra | I8: https://docs.nrel.gov/docs/fy25osti/92257.pdf | J8: S014 | K8: 2026-03-28 | M8: molto diffuso nei mercati maturi
A9: DESC-FV-006 | B9: T004 | C9: Fotovoltaico | D9: C-FV-006 | E9: Componente | F9: Modulo tandem perovskite-silicio | G9: Architettura avanzata che mira a superare le efficienze del silicio convenzionale. | H9: Roadmap industriale e linee pilota | I9: https://www.vdma.org/international-technology-roadmap-photovoltaic | J9: S017 | K9: 2026-03-28 | M9: tema da monitorare in horizon scanning
A10: DESC-FV-007 | B10: T004 | C10: Fotovoltaico | D10: C-FV-007 | E10: Sottosistema | F10: Sistema agrivoltaico | G10: Schema progettuale che integra produzione agricola e generazione FV con regole dedicate. | H10: Agricoltura, irrigazione, serre e colture specializzate | I10: https://www.ise.fraunhofer.de/en/publications/studies/agrivoltaics-opportunities-for-agriculture-and-the-energy-transition.html | J10: S026 | K10: 2026-03-28 | M10: forte rilevanza per Italia ed Europa
A11: DESC-WI-001 | B11: T006 | C11: Eolico | E11: Tecnologia | F11: Eolico | G11: Tecnologia rinnovabile matura e competitiva che converte l energia del vento in elettricita, con traiettorie distinte tra onshore, offshore fisso e floating. | H11: Onshore utility-scale, repowering, offshore fisso e floating | I11: https://www.iea.org/energy-system/renewables/wind | J11: S033 | K11: 2026-03-28 | M11: caso pilota ERMES
A12: DESC-WI-002 | B12: T006 | C12: Eolico | D12: C-WI-001 | E12: Componente | F12: Rotore e pale | G12: Componente aerodinamico chiave che determina gran parte della resa e del capacity factor. | H12: Onshore e offshore | I12: https://www.vestas.com/en/energy-solutions/onshore-wind-turbines | J12: S047 | K12: 2026-03-28 | M12: focus su lunghezza pale e materiali
A13: DESC-WI-003 | B13: T006 | C13: Eolico | D13: C-WI-002 | E13: Componente | F13: Nacelle e drivetrain | G13: Cuore elettromeccanico della turbina, con trade-off tra gearbox e direct-drive, affidabilita e costi. | H13: Onshore e offshore | I13: https://www.gevernova.com/wind-power/wind-turbines/offshore-wind-turbines | J13: S046 | K13: 2026-03-28 | M13: abilitatore prestazioni e disponibilita
A14: DESC-WI-004 | B14: T006 | C14: Eolico | D14: C-WI-004 | E14: Componente | F14: Fondazione fissa offshore | G14: Sottosistema che abilita l offshore in acque basse o medie, con forte impatto su costi e installazione. | H14: Offshore fixed-bottom | I14: https://docs.nrel.gov/docs/fy24osti/90897.pdf | J14: S037 | K14: 2026-03-28 | M14: rilevante per monopile e jacket
A15: DESC-WI-005 | B15: T006 | C15: Eolico | D15: C-WI-005 | E15: Componente | F15: Piattaforma floating | G15: Architettura che estende l eolico offshore in acque profonde e aumenta il potenziale tecnico accessibile. | H15: Offshore floating | I15: https://www.equinor.com/energy/hywind-tampen | J15: S044 | K15: 2026-03-28 | M15: tema chiave di horizon scanning
A16: DESC-WI-006 | B16: T006 | C16: Eolico | D16: C-WI-006 | E16: Componente | F16: Sistemi di controllo e condition monitoring | G16: Layer digitale che incrementa disponibilita, resa e manutenzione predittiva. | H16: Onshore e offshore | I16: https://www.energy.gov/eere/wind/land-based-wind-market-report-2024-edition | J16: S036 | K16: 2026-03-28 | M16: abilita O&M avanzata
A17: DESC-H2-001 | B17: T011 | C17: Idrogeno verde | E17: Tecnologia | F17: Idrogeno verde | G17: Vettore energetico e feedstock industriale prodotto da elettrolisi con elettricita rinnovabile; rilevante per usi hard-to-abate e flessibilita di sistema. | H17: Industria, chimica, fertilizzanti, steel, trasporti pesanti, storage | I17: https://www.iea.org/energy-system/low-emission-fuels/hydrogen | J17: S048 | K17: 2026-03-28 | M17: caso pilota ERMES
A18: DESC-H2-002 | B18: T011 | C18: Idrogeno verde | D18: C-H2-001 | E18: Componente | F18: Elettrolizzatore alcalino | G18: Tecnologia consolidata per grandi impianti con costi relativamente competitivi e buona scalabilita. | H18: Impianti centralizzati e industriali | I18: https://publications.jrc.ec.europa.eu/repository/handle/JRC144106 | J18: S055 | K18: 2026-03-28 | M18: forte presenza nelle pipeline di progetto
A19: DESC-H2-003 | B19: T011 | C19: Idrogeno verde | D19: C-H2-002 | E19: Componente | F19: Elettrolizzatore PEM | G19: Soluzione ad alta flessibilita, adatta a profili dinamici e integrazione con rinnovabili variabili. | H19: Industria, stazioni rifornimento, impianti flessibili | I19: https://docs.nrel.gov/docs/fy24osti/87625.pdf | J19: S050 | K19: 2026-03-28 | M19: focus su materiali nobili
A20: DESC-H2-004 | B20: T011 | C20: Idrogeno verde | D20: C-H2-003 | E20: Componente | F20: Elettrolizzatore SOEC | G20: Tecnologia avanzata ad alta temperatura con potenziale vantaggio di efficienza in presenza di calore di processo. | H20: Raffinerie, chimica, acciaio, e-fuels | I20: https://publications.jrc.ec.europa.eu/repository/handle/JRC144106 | J20: S055 | K20: 2026-03-28 | M20: frontiera con rischio tecnologico piu alto
A21: DESC-H2-005 | B21: T011 | C21: Idrogeno verde | D21: C-H2-005 | E21: Componente | F21: Compressione e stoccaggio H2 | G21: Nodo essenziale per assicurare buffer, continuita di fornitura e integrazione con usi non sincroni alla produzione. | H21: Industria, logistica, mobilita | I21: https://www.iea.org/reports/global-hydrogen-review-2025 | J21: S049 | K21: 2026-03-28 | M21: abilita continuita e valore di sistema
A22: DESC-H2-006 | B22: T011 | C22: Idrogeno verde | D22: C-H2-007 | E22: Componente | F22: Energy management e integrazione con rinnovabili | G22: Sistema di controllo che ottimizza fattore di utilizzo, costo dell elettricita e profilo di produzione dell H2. | H22: Impianti collegati a rete o dietro al contatore | I22: https://www.iea.org/reports/global-hydrogen-review-2025 | J22: S049 | K22: 2026-03-28 | M22: chiave per LCOH e bancabilita
A23: DESC-CO-001 | B23: T001 | C23: Carbone | E23: Tecnologia | F23: Carbone | G23: Tecnologia fossile matura usata soprattutto per generazione elettrica e processi industriali ad alta intensita energetica; in molti mercati e in declino regolatorio ma ancora rilevante per sicurezza e baseload. | H23: Applicazioni rilevanti nel mix energetico e nelle filiere industriali | I23: https://www.iea.org/energy-system/fossil-fuels/coal | J23: S077
A24: DESC-CO-002 | B24: T001 | C24: Carbone | D24: C-CO-001 | E24: Componente | F24: Estrazione e preparazione | G24: Mining, washing e handling del carbone con controllo qualita combustibile. | H24: Fornitura combustibile e riduzione impurita | I24: https://www.iea.org/energy-system/fossil-fuels/coal | J24: S077
A25: DESC-CO-003 | B25: T001 | C25: Carbone | D25: C-CO-002 | E25: Componente | F25: Caldaia PC / USC | G25: Boiler a polverino, supercritical o ultrasupercritical per migliorare efficienza. | H25: Generazione vapore ad alta temperatura e pressione | I25: https://www.iea.org/energy-system/fossil-fuels/coal | J25: S075
A26: DESC-CO-004 | B26: T001 | C26: Carbone | D26: C-CO-003 | E26: Componente | F26: Turbina a vapore e generatore | G26: Isola convenzionale di conversione termoelettrica. | H26: Conversione meccanica ed elettrica | I26: https://www.iea.org/energy-system/fossil-fuels/coal | J26: S075
A27: DESC-CO-005 | B27: T001 | C27: Carbone | D27: C-CO-004 | E27: Componente | F27: FGD / SCR / ESP | G27: Sistemi di abbattimento SOx, NOx, polveri e mercurio. | H27: Conformita ambientale | I27: https://www.iea.org/energy-system/fossil-fuels/coal | J27: S075
A28: DESC-CO-006 | B28: T001 | C28: Carbone | D28: C-CO-005 | E28: Componente | F28: CCS retrofit | G28: Cattura post-combustione e compressione CO2 su impianti esistenti o nuovi. | H28: Riduzione emissioni lifecycle e direct stack | I28: https://www.iea.org/energy-system/fossil-fuels/coal | J28: S118
A29: DESC-OI-001 | B29: T002 | C29: Olio | E29: Tecnologia | F29: Olio | G29: Tecnologia fossile consolidata che alimenta soprattutto mobilita, calore e parte della generazione di backup; strategicamente rilevante ma esposta a forte pressione climatica e di efficienza. | H29: Applicazioni rilevanti nel mix energetico e nelle filiere industriali | I29: https://www.iea.org/energy-system/fossil-fuels/oil | J29: S076
A30: DESC-OI-002 | B30: T002 | C30: Olio | D30: C-OI-001 | E30: Componente | F30: Produzione ed estrazione | G30: Pozzi, gathering e separazione primaria del greggio. | H30: Fornitura feedstock liquidi | I30: https://www.iea.org/energy-system/fossil-fuels/oil | J30: S076
A31: DESC-OI-003 | B31: T002 | C31: Olio | D31: C-OI-002 | E31: Componente | F31: Stoccaggio e logistica | G31: Tank farm, terminali, shipping e pipeline per greggio e prodotti. | H31: Movimentazione e sicurezza di approvvigionamento | I31: https://www.iea.org/energy-system/fossil-fuels/oil | J31: S076
A32: DESC-OI-004 | B32: T002 | C32: Olio | D32: C-OI-003 | E32: Componente | F32: Raffinazione | G32: Distillazione, cracking, hydrotreating e upgrading prodotti. | H32: Produzione carburanti e feedstock | I32: https://www.iea.org/energy-system/fossil-fuels/oil | J32: S114
A33: DESC-OI-005 | B33: T002 | C33: Olio | D33: C-OI-004 | E33: Componente | F33: Motori / turbine oil-fired | G33: Tecnologie di combustione per trasporti, backup e alcuni mercati insulari. | H33: Conversione energetica finale | I33: https://www.iea.org/energy-system/fossil-fuels/oil | J33: S076
A34: DESC-OI-006 | B34: T002 | C34: Olio | D34: C-OI-005 | E34: Componente | F34: Cogen e heat integration | G34: Recuperi termici, cogenerazione e digital energy management in raffineria. | H34: Riduzione consumi ed emissioni | I34: https://www.iea.org/energy-system/fossil-fuels/oil | J34: S115
A35: DESC-GA-001 | B35: T003 | C35: Gas Naturale | E35: Tecnologia | F35: Gas Naturale | G35: Tecnologia fossile flessibile e programmabile, centrale per bilanciamento del sistema elettrico, calore industriale e sicurezza energetica; in UE e considerata fonte transitoria sotto condizioni stringenti. | H35: Applicazioni rilevanti nel mix energetico e nelle filiere industriali | I35: https://www.iea.org/energy-system/fossil-fuels/natural-gas | J35: S074
A36: DESC-GA-002 | B36: T003 | C36: Gas Naturale | D36: C-GA-001 | E36: Componente | F36: Upstream / LNG / import | G36: Filiera di produzione, liquefazione, rigassificazione e importazione gas. | H36: Sicurezza di approvvigionamento | I36: https://www.iea.org/energy-system/fossil-fuels/natural-gas | J36: S087
A37: DESC-GA-003 | B37: T003 | C37: Gas Naturale | D37: C-GA-002 | E37: Componente | F37: Turbina a gas simple cycle | G37: Macchine flessibili per picco e servizi ancillari. | H37: Peak load e fast ramping | I37: https://www.iea.org/energy-system/fossil-fuels/natural-gas | J37: S075
A38: DESC-GA-004 | B38: T003 | C38: Gas Naturale | D38: C-GA-003 | E38: Componente | F38: CCGT H/F class | G38: Cicli combinati ad alta efficienza per mid-merit e baseload flessibile. | H38: Generazione efficiente e modulabile | I38: https://www.iea.org/energy-system/fossil-fuels/natural-gas | J38: S075
A39: DESC-GA-005 | B39: T003 | C39: Gas Naturale | D39: C-GA-004 | E39: Componente | F39: Storage, pipeline e terminali | G39: Reti, stoccaggi e terminali LNG a supporto di sicurezza e flessibilita. | H39: Bilanciamento e resilienza di sistema | I39: https://www.iea.org/energy-system/fossil-fuels/natural-gas | J39: S087
A40: DESC-GA-006 | B40: T003 | C40: Gas Naturale | D40: C-GA-005 | E40: Componente | F40: CCS-ready / post-combustion CCS | G40: Configurazioni nuove o retrofit con cattura CO2. | H40: Riduzione emissioni dirette | I40: https://www.iea.org/energy-system/fossil-fuels/natural-gas | J40: S112
A41: DESC-ST-001 | B41: T005 | C41: Solare Termico | E41: Tecnologia | F41: Solare Termico | G41: Tecnologia che converte l irraggiamento solare in calore utile o in elettricita tramite concentrazione; include collettori per acqua calda/process heat e CSP con accumulo termico per generazione programmabile. | H41: Applicazioni rilevanti nel mix energetico e nelle filiere industriali | I41: https://atb.nrel.gov/electricity/2024/concentrating_solar_power | J41: S063
A42: DESC-ST-002 | B42: T005 | C42: Solare Termico | D42: C-ST-001 | E42: Componente | F42: Campo collettori / eliostati | G42: Superficie ottica che concentra o raccoglie la radiazione solare. | H42: Raccolta energia solare | I42: https://atb.nrel.gov/electricity/2024/concentrating_solar_power | J42: S063
A43: DESC-ST-003 | B43: T005 | C43: Solare Termico | D43: C-ST-002 | E43: Componente | F43: Serbatoio / TES termico | G43: Accumulo caldo/freddo o molten salt per spostare produzione nel tempo. | H43: Dispatchability e spostamento energetico | I43: https://atb.nrel.gov/electricity/2024/concentrating_solar_power | J43: S063
A44: DESC-ST-004 | B44: T005 | C44: Solare Termico | D44: C-ST-003 | E44: Componente | F44: Ricevitore e fluido termovettore | G44: Receiver, HTF e piping per trasferire il calore al power block o ai carichi termici. | H44: Trasferimento del calore | I44: https://atb.nrel.gov/electricity/2024/concentrating_solar_power | J44: S063
A45: DESC-ST-005 | B45: T005 | C45: Solare Termico | D45: C-ST-004 | E45: Componente | F45: Steam cycle / ORC / chiller | G45: Blocco di conversione elettrica o termofrigorifera. | H45: Produzione elettricita, calore o freddo | I45: https://atb.nrel.gov/electricity/2024/concentrating_solar_power | J45: S063
A46: DESC-ST-006 | B46: T005 | C46: Solare Termico | D46: C-ST-005 | E46: Componente | F46: Solar process heat | G46: Integrazione in processi industriali a bassa-media temperatura. | H46: Decarbonizzazione del calore | I46: https://atb.nrel.gov/electricity/2024/concentrating_solar_power | J46: S062
A47: DESC-HY-001 | B47: T007 | C47: Idroelettrico | E47: Tecnologia | F47: Idroelettrico | G47: Tecnologia rinnovabile matura e programmabile che sfrutta salti idraulici, invasi o impianti ad acqua fluente; chiave per flessibilita, riserva e servizi di rete, inclusi sistemi di pompaggio. | H47: Applicazioni rilevanti nel mix energetico e nelle filiere industriali | I47: https://www.iea.org/energy-system/renewables/hydroelectricity | J47: S068
A48: DESC-HY-002 | B48: T007 | C48: Idroelettrico | D48: C-HY-001 | E48: Componente | F48: Diga / opera di presa | G48: Opere civili, diga, galleria e condotta forzata. | H48: Gestione risorsa idrica e salto | I48: https://www.iea.org/energy-system/renewables/hydroelectricity | J48: S068
A49: DESC-HY-003 | B49: T007 | C49: Idroelettrico | D49: C-HY-002 | E49: Componente | F49: Turbina e generatore | G49: Francis, Kaplan, Pelton e relativi generatori. | H49: Conversione energia idraulica in elettrica | I49: https://www.iea.org/energy-system/renewables/hydroelectricity | J49: S069
A50: DESC-HY-004 | B50: T007 | C50: Idroelettrico | D50: C-HY-003 | E50: Componente | F50: Controllo, protezione e automazione | G50: Sistemi di controllo impianto e servizi di rete. | H50: Affidabilita, dispatch e ancillary services | I50: https://www.iea.org/energy-system/renewables/hydroelectricity | J50: S069
A51: DESC-HY-005 | B51: T007 | C51: Idroelettrico | D51: C-HY-004 | E51: Componente | F51: Pumped storage | G51: Pompage reversible per accumulo e flessibilita di rete. | H51: Storage di lunga durata | I51: https://www.iea.org/energy-system/renewables/hydroelectricity | J51: S103
A52: DESC-HY-006 | B52: T007 | C52: Idroelettrico | D52: C-HY-005 | E52: Componente | F52: Repowering e upgrading | G52: Revamping, rewinding e sostituzione turbine su impianti esistenti. | H52: Estensione vita utile e incremento output | I52: https://www.iea.org/energy-system/renewables/hydroelectricity | J52: S069
A53: DESC-BM-001 | B53: T008 | C53: Biomasse | E53: Tecnologia | F53: Biomasse | G53: Famiglia di tecnologie che valorizza biomasse solide, biogas, biometano e residui organici per produrre elettricita, calore, gas rinnovabili e combustibili avanzati, con forte dipendenza dalla sostenibilita della filiera. | H53: Applicazioni rilevanti nel mix energetico e nelle filiere industriali | I53: https://www.iea.org/energy-system/renewables/bioenergy | J53: S065
A54: DESC-BM-002 | B54: T008 | C54: Biomasse | D54: C-BM-001 | E54: Componente | F54: Supply e pretrattamento | G54: Raccolta, essiccazione, cippatura, pelletizzazione e controllo feedstock. | H54: Stabilita combustibile e filiera | I54: https://www.iea.org/energy-system/renewables/bioenergy | J54: S065
A55: DESC-BM-003 | B55: T008 | C55: Biomasse | D55: C-BM-002 | E55: Componente | F55: Boiler / combustione | G55: Caldaie a biomassa per elettricita, vapore o calore. | H55: Produzione energia termica ed elettrica | I55: https://www.iea.org/energy-system/renewables/bioenergy | J55: S066
A56: DESC-BM-004 | B56: T008 | C56: Biomasse | D56: C-BM-003 | E56: Componente | F56: Gasificazione | G56: Produzione syngas per power, fuels o chemicals. | H56: Maggiore flessibilita di valorizzazione | I56: https://www.iea.org/energy-system/renewables/bioenergy | J56: S066
A57: DESC-BM-005 | B57: T008 | C57: Biomasse | D57: C-BM-004 | E57: Componente | F57: Digestione anaerobica | G57: Produzione di biogas da FORSU, reflui e sottoprodotti. | H57: Generazione rinnovabile e gestione rifiuti | I57: https://www.iea.org/energy-system/renewables/bioenergy | J57: S082
A58: DESC-BM-006 | B58: T008 | C58: Biomasse | D58: C-BM-005 | E58: Componente | F58: Biometano / bioLNG | G58: Rimozione CO2 e upgrading per immissione in rete o uso trasporti. | H58: Gas rinnovabile e flessibilita di uso finale | I58: https://www.iea.org/energy-system/renewables/bioenergy | J58: S082
A59: DESC-GEO-001 | B59: T009 | C59: Geotermico | E59: Tecnologia | F59: Geotermico | G59: Tecnologia che sfrutta il calore del sottosuolo per generare elettricita e calore; oggi basata su risorse idrotermali ma in forte attenzione per EGS e closed-loop di nuova generazione. | H59: Applicazioni rilevanti nel mix energetico e nelle filiere industriali | I59: https://www.iea.org/reports/the-future-of-geothermal-energy | J59: S079
A60: DESC-GEO-002 | B60: T009 | C60: Geotermico | D60: C-GEO-001 | E60: Componente | F60: Esplorazione e modellazione serbatoio | G60: Geofisica, geologia e reservoir simulation. | H60: Riduzione rischio geologico | I60: https://www.iea.org/reports/the-future-of-geothermal-energy | J60: S079
A61: DESC-GEO-003 | B61: T009 | C61: Geotermico | D61: C-GEO-002 | E61: Componente | F61: Drilling e completamento pozzi | G61: Pozzi di produzione e reiniezione con casing e completamento. | H61: Accesso alla risorsa | I61: https://www.iea.org/reports/the-future-of-geothermal-energy | J61: S080
A62: DESC-GEO-004 | B62: T009 | C62: Geotermico | D62: C-GEO-003 | E62: Componente | F62: Flash / dry steam / ORC | G62: Blocco di conversione adatto alla temperatura della risorsa. | H62: Generazione elettrica | I62: https://www.iea.org/reports/the-future-of-geothermal-energy | J62: S080
A63: DESC-GEO-005 | B63: T009 | C63: Geotermico | D63: C-GEO-004 | E63: Componente | F63: Scambiatori e teleriscaldamento | G63: Utilizzo diretto del calore e reti termiche. | H63: Decarbonizzazione del calore | I63: https://www.iea.org/reports/the-future-of-geothermal-energy | J63: S079
A64: DESC-GEO-006 | B64: T009 | C64: Geotermico | D64: C-GEO-005 | E64: Componente | F64: EGS | G64: Stimolazione o sviluppo di reservoir artificiali per estendere il potenziale geografico. | H64: Scalabilita globale della geotermia | I64: https://www.iea.org/reports/the-future-of-geothermal-energy | J64: S100
A65: DESC-NU-001 | B65: T010 | C65: Nucleare da fissione | E65: Tecnologia | F65: Nucleare da fissione | G65: Tecnologia a basse emissioni lifecycle per generazione elettrica e potenzialmente calore industriale; elevata intensita di capitale, forte rilevanza per sicurezza energetica, con nuova attenzione verso Gen III+ e SMR. | H65: Applicazioni rilevanti nel mix energetico e nelle filiere industriali | I65: https://www.iea.org/energy-system/electricity/nuclear-power | J65: S070
A66: DESC-NU-002 | B66: T010 | C66: Nucleare da fissione | D66: C-NUC-001 | E66: Componente | F66: Reattore e vessel | G66: Core, vessel e sistema nucleare principale. | H66: Fissione controllata e produzione calore | I66: https://www.iea.org/energy-system/electricity/nuclear-power | J66: S070
A67: DESC-NU-003 | B67: T010 | C67: Nucleare da fissione | D67: C-NUC-002 | E67: Componente | F67: Steam generator e circuiti primari | G67: Scambiatori, pompe e circuiti del primario. | H67: Trasferimento calore e sicurezza | I67: https://www.iea.org/energy-system/electricity/nuclear-power | J67: S073
A68: DESC-NU-004 | B68: T010 | C68: Nucleare da fissione | D68: C-NUC-003 | E68: Componente | F68: Turbina, condensatore e BOP | G68: Isola convenzionale di conversione termoelettrica. | H68: Generazione elettrica | I68: https://www.iea.org/energy-system/electricity/nuclear-power | J68: S071
A69: DESC-NU-005 | B69: T010 | C69: Nucleare da fissione | D69: C-NUC-004 | E69: Componente | F69: Sistemi di sicurezza passivi | G69: Sistemi di shutdown, rimozione calore residuo e contenimento. | H69: Safety e resilience | I69: https://www.iea.org/energy-system/electricity/nuclear-power | J69: S073
A70: DESC-NU-006 | B70: T010 | C70: Nucleare da fissione | D70: C-NUC-005 | E70: Componente | F70: Combustibile, waste e decommissioning | G70: Produzione combustibile, gestione esaurito e rifiuti radioattivi. | H70: Continuita operativa e chiusura del ciclo | I70: https://www.iea.org/energy-system/electricity/nuclear-power | J70: S073

Sheet 06_Avanzamento
A1: 06_Avanzamento | Stato di avanzamento di componenti e sottosistemi
A2: Area 2 del brief: avanzamento tecnologico di componenti o sottosistemi della tecnologia osservata.
A3: Record_ID | B3: Tech_ID | C3: Tecnologia | D3: Comp_ID | E3: Componente / sottosistema | F3: Fase di sviluppo | G3: Stato di avanzamento | H3: Evidenza / milestone | I3: Benchmark / peer comparison | J3: Geografia | K3: Fonte_ID | L3: Data rilevazione | M3: Note
A4: ADV-FV-001 | B4: T004 | C4: Fotovoltaico | D4: C-FV-001 | E4: Modulo FV | F4: Commerciale diffusa | G4: Mercato mainstream su silicio cristallino, con rapida transizione da PERC a TOPCon e crescita del bifacciale. | H4: Le roadmap industriali indicano TOPCon come tecnologia dominante nel breve periodo. | I4: Benchmark globale molto elevato, con forte pressione competitiva su costi/efficienza. | J4: Globale | K4: S016; S017 | L4: 2026-03-28 | M4: osservare tempi di standardizzazione e bancabilita
A5: ADV-FV-002 | B5: T004 | C5: Fotovoltaico | D5: C-FV-006 | E5: Modulo tandem perovskite-silicio | F5: FOAK / pre-commerciale | G5: Scale-up iniziale: prestazioni promettenti ma ancora da consolidare su stabilita e durabilita. | H5: La roadmap ITRPV prospetta efficienze fino a ~30,5% nel 2035. | I5: Livello superiore ai moduli Si convenzionali ma con rischio tecnologico ancora rilevante. | J5: Globale | K5: S017 | L5: 2026-03-28 | M5: candidato forte per horizon scanning
A6: ADV-FV-003 | B6: T004 | C6: Fotovoltaico | D6: C-FV-002 | E6: Inverter | F6: Commerciale diffusa | G6: Piattaforme mature con architetture modulari, 1500 Vdc e funzioni di grid support avanzate. | H6: Max efficiency ~99%, controllo potenza attiva/reactive e funzioni LV/HVRT. | I6: Mercato competitivo e consolidato, con innovazione incrementale continua. | J6: Globale | K6: S027 | L6: 2026-03-28 | M6: tema chiave per integrazione di rete
A7: ADV-FV-004 | B7: T004 | C7: Fotovoltaico | D7: C-FV-004 | E7: Tracker monoassiale | F7: Commerciale diffusa | G7: Tecnologia standard in molti impianti utility-scale a terra. | H7: Nel 2023 il tracking monoassiale e presente nella maggioranza degli impianti utility-scale a terra negli USA. | I7: Benchmark alto nei mercati maturi con elevata radiazione. | J7: USA / Globale | K7: S014 | L7: 2026-03-28 | M7: rilevante per resa e LCOE
A8: ADV-FV-005 | B8: T004 | C8: Fotovoltaico | D8: C-FV-003 | E8: Sistema di backup / accumulo | F8: Commerciale iniziale | G8: Crescita rapida delle configurazioni ibride FV+BESS per ottimizzare profili di immissione e resilienza. | H8: Aumento della quota di sistemi utility-scale ibridi con storage. | I8: Vantaggio crescente in mercati con congestione, curtailment o prezzi orari volatili. | J8: USA / UE / Globale | K8: S014 | L8: 2026-03-28 | M8: abilitatore di competitivita di sistema
A9: ADV-FV-006 | B9: T004 | C9: Fotovoltaico | D9: C-FV-007 | E9: Sistema agrivoltaico | F9: Pilota / dimostratore | G9: Segmento in accelerazione con linee guida tecniche e supporto regolatorio dedicato. | H9: Casi pilota europei mostrano effetti positivi su uso del suolo e resilienza agricola. | I9: Benchmark ancora eterogeneo per layout, colture e business model. | J9: UE / Italia | K9: S026; S028 | L9: 2026-03-28 | M9: richiede metriche integrate energia-agricoltura
A10: ADV-WI-001 | B10: T006 | C10: Eolico | D10: C-WI-001 | E10: Rotore e pale | F10: Commerciale diffusa | G10: Mercato maturo con crescita dimensionale continua, soprattutto offshore. | H10: Le turbine di ultima generazione aumentano diametro rotore e area spazzata per ridurre LCOE. | I10: Benchmark elevato; vantaggio competitivo di chi controlla materiali, aerodinamica e logistica. | J10: Globale | K10: S046; S047 | L10: 2026-03-28 | M10: osservare materiali compositi e riciclo pale
A11: ADV-WI-002 | B11: T006 | C11: Eolico | D11: C-WI-004 | E11: Fondazione fissa offshore | F11: Commerciale diffusa | G11: Tecnologia consolidata nei mercati offshore maturi. | H11: Ampia pipeline globale e standardizzazione industriale su monopile e jacket. | I11: Molto avanzata nei mari del Nord; vantaggi di scala importanti. | J11: UE / Globale | K11: S037; S038 | L11: 2026-03-28 | M11: maturita alta ma pressione su supply chain
A12: ADV-WI-003 | B12: T006 | C12: Eolico | D12: C-WI-005 | E12: Piattaforma floating | F12: FOAK / pre-commerciale | G12: Numerosi dimostratori e primi progetti commerciali, ma industrializzazione ancora iniziale. | H12: Hywind Tampen mostra il passaggio da demo a progetti di taglia maggiore. | I12: Potenziale elevato in acque profonde ma CAPEX ancora superiore al fixed-bottom. | J12: Globale | K12: S044; S037 | L12: 2026-03-28 | M12: candidato forte per horizon scanning
A13: ADV-WI-004 | B13: T006 | C13: Eolico | D13: C-WI-006 | E13: Sistemi di controllo e condition monitoring | F13: Commerciale diffusa | G13: Digitalizzazione e manutenzione predittiva in rapida diffusione. | H13: SCADA avanzati, analytics e digital twin migliorano disponibilita e resa. | I13: Benchmark crescente sulla qualita dei dati e degli algoritmi. | J13: Globale | K13: S036 | L13: 2026-03-28 | M13: driver importante di OPEX
A14: ADV-WI-005 | B14: T006 | C14: Eolico | D14: C-WI-007 | E14: Sottostazione e connessione di rete | F14: Commerciale diffusa | G14: Tecnologia matura ma spesso collo di bottiglia di permitting e supply chain. | H14: Per l offshore aumentano i fabbisogni di HVDC e infrastrutture portuali. | I14: Forte dipendenza da pianificazione di sistema e catena dei fornitori. | J14: UE / Globale | K14: S038; S037 | L14: 2026-03-28 | M14: tema critico per time-to-market
... A21: ADV-WI-006 | B21: T006 | C21: Eolico | D21: C-WI-003 | E21: Torre e struttura di supporto | F21: Commerciale diffusa | G21: Innovazione incrementale continua su altezze mozzo e logistica modulare. | H21: Torri piu alte e soluzioni modulari migliorano accesso a risorsa e trasportabilita onshore. | I21: Benchmark rilevante nei siti a vento medio-basso e nei programmi di repowering. | J21: Globale | K21: S034; S047 | L21: 2026-03-28 | M21: tema importante per competitivita onshore
A22: AV-CO-001 | B22: T001 | C22: Carbone | E22: Tecnologia | F22: Commerciale diffusa ma in contrazione in molti mercati OECD; frontiera concentrata su flessibilita, efficienza HELE e CCS. | G22: Technology watch / benchmark internazionale | H22: Medio termine | I22: Sviluppo disomogeneo per mercati e filiere | J22: S077
A23: AV-CO-002 | B23: T001 | C23: Carbone | D23: C-CO-002 | E23: Caldaia PC / USC | F23: Domina il parco moderno; frontier su USC/AUSC per migliorare rendimento. | G23: Breve-medio termine | H23: S075 | I23: 9 | J23: Caldaia PC | K23: S075
A24: AV-CO-003 | B24: T001 | C24: Carbone | D24: C-CO-004 | E24: FGD / SCR / ESP | F24: Tecnologie mature indispensabili per conformita emissiva. | G24: Breve termine | H24: S075 | I24: 9 | J24: FGD | K24: S075
A25: AV-CO-004 | B25: T001 | C25: Carbone | D25: C-CO-005 | E25: CCS retrofit | F25: Retrofit possibili ma costosi; casi operativi limitati. | G25: Medio-lungo termine | H25: S118 | I25: 7 | J25: CCS retrofit | K25: S118
A26: AV-CO-005 | B26: T001 | C26: Carbone | D26: C-CO-006 | E26: AUSC materials | F26: Materiali avanzati e componentistica spingono la frontiera di efficienza. | G26: Lungo termine | H26: S075 | I26: 6 | J26: AUSC materials | K26: S075
A27: AV-CO-006 | B27: T001 | C27: Carbone | E27: Mercato | F27: Commerciale diffusa ma in contrazione in molti mercati OECD; frontiera concentrata su flessibilita, efficienza HELE e CCS. | G27: Horizon scanning | H27: Lungo termine | I27: Evoluzione guidata da policy, costi e supply chain | J27: S077
A28: AV-OI-001 | B28: T002 | C28: Olio | E28: Tecnologia | F28: Tecnologia e filiera estremamente mature; innovazione concentrata su efficienza, monitoraggio emissioni, raffinazione avanzata e riduzione intensita carbonica. | G28: Technology watch / benchmark internazionale | H28: Medio termine | I28: Sviluppo disomogeneo per mercati e filiere | J28: S076
A29: AV-OI-002 | B29: T002 | C29: Olio | D29: C-OI-003 | E29: Raffinazione | F29: Innovazione su residue upgrading, desolforazione, efficienza e feedstock flessibili. | G29: Breve-medio termine | H29: S114 | I29: 9 | J29: Raffinazione | K29: S114
A30: AV-OI-003 | B30: T002 | C30: Olio | D30: C-OI-005 | E30: Cogen e heat integration | F30: Digital twin e pinch analysis riducono consumi e intensita carbonica dei siti refinery. | G30: Breve termine | H30: S115 | I30: 9 | J30: Cogen e heat integration | K30: S115
A31: AV-OI-004 | B31: T002 | C31: Olio | D31: C-OI-006 | E31: Flare and methane monitoring | F31: Satelliti, sensoristica e LDAR spingono riduzione flaring e perdite. | G31: Breve termine | H31: S116 | I31: 8 | J31: Flare and methane monitoring | K31: S116
A32: AV-OI-005 | B32: T002 | C32: Olio | D32: C-OI-004 | E32: Motori / turbine oil-fired | F32: Segmento ormai residuale in molti mercati power ma ancora rilevante per backup e isole. | G32: Breve termine | H32: S076 | I32: 9 | J32: Motori | K32: S076
A33: AV-OI-006 | B33: T002 | C33: Olio | E33: Mercato | F33: Tecnologia e filiera estremamente mature; innovazione concentrata su efficienza, monitoraggio emissioni, raffinazione avanzata e riduzione intensita carbonica. | G33: Horizon scanning | H33: Lungo termine | I33: Evoluzione guidata da policy, costi e supply chain | J33: S076
A34: AV-GA-001 | B34: T003 | C34: Gas Naturale | E34: Tecnologia | F34: Tecnologia matura e centrale per flessibilita elettrica e calore; innovazione su efficienza, methane abatement, CCS e hydrogen-ready. | G34: Technology watch / benchmark internazionale | H34: Medio termine | I34: Sviluppo disomogeneo per mercati e filiere | J34: S074
A35: AV-GA-002 | B35: T003 | C35: Gas Naturale | D35: C-GA-003 | E35: CCGT H/F class | F35: Turbine e cicli combinati spingono efficienza verso il 60%+. | G35: Breve termine | H35: S075 | I35: 9 | J35: CCGT H/F class | K35: S075
A36: AV-GA-003 | B36: T003 | C36: Gas Naturale | D36: C-GA-002 | E36: Turbina a gas simple cycle | F36: Rilevante per servizi di rete e picchi, con fast-start. | G36: Breve termine | H36: S075 | I36: 9 | J36: Turbina a gas simple cycle | K36: S075
A37: AV-GA-004 | B37: T003 | C37: Gas Naturale | D37: C-GA-005 | E37: CCS-ready / post-combustion CCS | F37: CCGT con cattura diventa opzione di decarbonizzazione dispatchable. | G37: Medio-lungo termine | H37: S112 | I37: 7 | J37: CCS-ready | K37: S112
A38: AV-GA-005 | B38: T003 | C38: Gas Naturale | D38: C-GA-006 | E38: Hydrogen-ready combustion | F38: Turbine predisposte a blend H2 crescente. | G38: Medio termine | H38: S111 | I38: 8 | J38: Hydrogen-ready combustion | K38: S111
A39: AV-GA-006 | B39: T003 | C39: Gas Naturale | E39: Mercato | F39: Tecnologia matura e centrale per flessibilita elettrica e calore; innovazione su efficienza, methane abatement, CCS e hydrogen-ready. | G39: Horizon scanning | H39: Lungo termine | I39: Evoluzione guidata da policy, costi e supply chain | J39: S074
A40: AV-ST-001 | B40: T005 | C40: Solare Termico | E40: Tecnologia | F40: Tecnologia commerciale ma meno diffusa del FV; il valore distintivo e la programmabilita tramite accumulo termico e la decarbonizzazione del calore industriale. | G40: Technology watch / benchmark internazionale | H40: Medio termine | I40: Sviluppo disomogeneo per mercati e filiere | J40: S063
A41: AV-ST-002 | B41: T005 | C41: Solare Termico | D41: C-ST-001 | E41: Campo collettori / eliostati | F41: Tecnologie mature per campo solare, con miglioramenti continui su precisione e costi. | G41: Breve termine | H41: S063 | I41: 8 | J41: Campo collettori | K41: S063
A42: AV-ST-003 | B42: T005 | C42: Solare Termico | D42: C-ST-002 | E42: Serbatoio / TES termico | F42: Accumuli termici sono il driver chiave di dispatchability. | G42: Breve termine | H42: S063 | I42: 9 | J42: Serbatoio | K42: S063
A43: AV-ST-004 | B43: T005 | C43: Solare Termico | D43: C-ST-003 | E43: Ricevitore e fluido termovettore | F43: Receiver e HTF determinano temperatura e rendimento. | G43: Breve-medio termine | H43: S063 | I43: 8 | J43: Ricevitore e fluido termovettore | K43: S063
A44: AV-ST-005 | B44: T005 | C44: Solare Termico | D44: C-ST-004 | E44: Steam cycle / ORC / chiller | F44: Ottimizzazione del power block e integrazione con process heat/cooling. | G44: Breve-medio termine | H44: S063 | I44: 8 | J44: Steam cycle | K44: S063
A45: AV-ST-006 | B45: T005 | C45: Solare Termico | E45: Mercato | F45: Tecnologia commerciale ma meno diffusa del FV; il valore distintivo e la programmabilita tramite accumulo termico e la decarbonizzazione del calore industriale. | G45: Horizon scanning | H45: Lungo termine | I45: Evoluzione guidata da policy, costi e supply chain | J45: S063
A46: AV-HY-001 | B46: T007 | C46: Idroelettrico | E46: Tecnologia | F46: Tecnologia pienamente matura e cruciale per energia rinnovabile programmabile, flessibilita e servizi di sistema; innovazione soprattutto su pumped storage, repowering e mitigazione ambientale. | G46: Technology watch / benchmark internazionale | H46: Medio termine | I46: Sviluppo disomogeneo per mercati e filiere | J46: S068
A47: AV-HY-002 | B47: T007 | C47: Idroelettrico | D47: C-HY-002 | E47: Turbina e generatore | F47: Core technology matura con miglioramenti su efficienza e digital O&M. | G47: Breve termine | H47: S069 | I47: 9 | J47: Turbina e generatore | K47: S069
A48: AV-HY-003 | B48: T007 | C48: Idroelettrico | D48: C-HY-004 | E48: Pumped storage | F48: PSH resta la principale tecnologia di storage a lunga durata su larga scala. | G48: Breve-medio termine | H48: S103 | I48: 9 | J48: Pumped storage | K48: S103
A49: AV-HY-004 | B49: T007 | C49: Idroelettrico | D49: C-HY-005 | E49: Repowering e upgrading | F49: Molto spazio di incremento output su parco esistente. | G49: Breve termine | H49: S069 | I49: 9 | J49: Repowering e upgrading | K49: S069
A50: AV-HY-005 | B50: T007 | C50: Idroelettrico | D50: C-HY-006 | E50: Fish passage e monitoraggio | F50: Cresce il focus su mitigazione biodiversita e sedimenti. | G50: Breve-medio termine | H50: S068 | I50: 8 | J50: Fish passage e monitoraggio | K50: S068
A51: AV-HY-006 | B51: T007 | C51: Idroelettrico | E51: Mercato | F51: Tecnologia pienamente matura e cruciale per energia rinnovabile programmabile, flessibilita e servizi di sistema; innovazione soprattutto su pumped storage, repowering e mitigazione ambientale. | G51: Horizon scanning | H51: Lungo termine | I51: Evoluzione guidata da policy, costi e supply chain | J51: S068
A52: AV-BM-001 | B52: T008 | C52: Biomasse | E52: Tecnologia | F52: Tecnologie mature per combustione e digestione anaerobica; frontiera su gasificazione, biomethane, bioLNG e BECCS, con sostenibilita della filiera come discriminante chiave. | G52: Technology watch / benchmark internazionale | H52: Medio termine | I52: Sviluppo disomogeneo per mercati e filiere | J52: S065
A53: AV-BM-002 | B53: T008 | C53: Biomasse | D53: C-BM-002 | E53: Boiler / combustione | F53: Matura per CHP e power da biomassa solida. | G53: Breve termine | H53: S066 | I53: 9 | J53: Boiler | K53: S066
A54: AV-BM-003 | B54: T008 | C54: Biomasse | D54: C-BM-004 | E54: Digestione anaerobica | F54: Ampia maturita per reflui, FORSU e sottoprodotti agricoli. | G54: Breve termine | H54: S082 | I54: 9 | J54: Digestione anaerobica | K54: S082
A55: AV-BM-004 | B55: T008 | C55: Biomasse | D55: C-BM-005 | E55: Biometano / bioLNG | F55: Upgrading ormai maturo per immissione in rete e trasporti. | G55: Breve termine | H55: S082 | I55: 8 | J55: Biometano | K55: S082
A56: AV-BM-005 | B56: T008 | C56: Biomasse | D56: C-BM-003 | E56: Gasificazione | F56: Tecnologia promettente ma ancora selettiva su economics e affidabilita. | G56: Medio termine | H56: S066 | I56: 7 | J56: Gasificazione | K56: S066
A57: AV-BM-006 | B57: T008 | C57: Biomasse | E57: Mercato | F57: Tecnologie mature per combustione e digestione anaerobica; frontiera su gasificazione, biomethane, bioLNG e BECCS, con sostenibilita della filiera come discriminante chiave. | G57: Horizon scanning | H57: Lungo termine | I57: Evoluzione guidata da policy, costi e supply chain | J57: S065
A58: AV-GEO-001 | B58: T009 | C58: Geotermico | E58: Tecnologia | F58: Tecnologia matura per risorse idrotermali convenzionali, con forte opzione di crescita per EGS e closed-loop che possono globalizzare il potenziale. | G58: Technology watch / benchmark internazionale | H58: Medio termine | I58: Sviluppo disomogeneo per mercati e filiere | J58: S079
A59: AV-GEO-002 | B59: T009 | C59: Geotermico | D59: C-GEO-002 | E59: Drilling e completamento pozzi | F59: Il drilling resta il principale driver di costo e rischio. | G59: Breve termine | H59: S080 | I59: 8 | J59: Drilling e completamento pozzi | K59: S080
A60: AV-GEO-003 | B60: T009 | C60: Geotermico | D60: C-GEO-003 | E60: Flash / dry steam / ORC | F60: Power block maturo, soprattutto ORC per risorse medie. | G60: Breve termine | H60: S080 | I60: 9 | J60: Flash | K60: S080
A61: AV-GEO-004 | B61: T009 | C61: Geotermico | D61: C-GEO-005 | E61: EGS | F61: Nuova frontiera che amplia la geografia del geotermico. | G61: Medio-lungo termine | H61: S100 | I61: 6 | J61: EGS | K61: S100
A62: AV-GEO-005 | B62: T009 | C62: Geotermico | D62: C-GEO-006 | E62: Closed-loop geothermal | F62: Architetture chiuse per ridurre alcuni rischi di reservoir e water handling. | G62: Medio-lungo termine | H62: S101 | I62: 5 | J62: Closed-loop geothermal | K62: S101
A63: AV-GEO-006 | B63: T009 | C63: Geotermico | E63: Mercato | F63: Tecnologia matura per risorse idrotermali convenzionali, con forte opzione di crescita per EGS e closed-loop che possono globalizzare il potenziale. | G63: Horizon scanning | H63: Lungo termine | I63: Evoluzione guidata da policy, costi e supply chain | J63: S079
A64: AV-NU-001 | B64: T010 | C64: Nucleare da fissione | E64: Tecnologia | F64: Tecnologia commerciale consolidata su grandi reattori Gen II/III; nuova spinta su Gen III+, modularizzazione e SMR, con economics ancora sfidanti ma forte valore di firm low-carbon power. | G64: Technology watch / benchmark internazionale | H64: Medio termine | I64: Sviluppo disomogeneo per mercati e filiere | J64: S070
A65: AV-NU-002 | B65: T010 | C65: Nucleare da fissione | D65: C-NUC-001 | E65: Reattore e vessel | F65: Tecnologia matura su Gen III+ con forte focus execution. | G65: Breve termine | H65: S070 | I65: 8 | J65: Reattore e vessel | K65: S070
A66: AV-NU-003 | B66: T010 | C66: Nucleare da fissione | D66: C-NUC-004 | E66: Sistemi di sicurezza passivi | F66: Elemento distintivo dei design Gen III+. | G66: Breve termine | H66: S073 | I66: 9 | J66: Sistemi di sicurezza passivi | K66: S073
A67: AV-NU-004 | B67: T010 | C67: Nucleare da fissione | D67: C-NUC-005 | E67: Fuel cycle, waste e decommissioning | F67: Parte essenziale del costo totale e della governance sociale. | G67: Breve-medio termine | H67: S073 | I67: 9 | J67: Fuel cycle, waste e decommissioning | K67: S073
A68: AV-NU-005 | B68: T010 | C68: Nucleare da fissione | D68: C-NUC-006 | E68: SMR / modular factory | F68: Promessa di riduzione tempi/rischi tramite modularizzazione. | G68: Medio-lungo termine | H68: S086 | I68: 6 | J68: SMR | K68: S086
A69: AV-NU-006 | B69: T010 | C69: Nucleare da fissione | E69: Mercato | F69: Tecnologia commerciale consolidata su grandi reattori Gen II/III; nuova spinta su Gen III+, modularizzazione e SMR, con economics ancora sfidanti ma forte valore di firm low-carbon power. | G69: Horizon scanning | H69: Lungo termine | I69: Evoluzione guidata da policy, costi e supply chain | J69: S070

Sheet 07_TRL_TLR
A1: 07_TRL_TLR | Maturità tecnologica di componenti e sottosistemi
A2: Area 3 del brief: scala TRL/TLR per componenti o sottosistemi, con evidenze e contesto di applicazione.
A3: Record_ID | B3: Tech_ID | C3: Tecnologia | D3: Comp_ID | E3: Componente / sottosistema | F3: TRL/TLR (1-9) | G3: Contesto (lab/pilota/mercato) | H3: Evidenza a supporto | I3: Anno riferimento | J3: Geografia | K3: Fonte_ID | L3: Note
A4: TRL-FV-001 | B4: T004 | C4: Fotovoltaico | D4: C-FV-001 | E4: Modulo FV | F4: 9 | G4: Mercato | H4: Tecnologia consolidata e bancabile su vasta scala in tutti i principali mercati. | I4: 2025 | J4: Globale | K4: S012; S016 | L4: mainstream c-Si
A5: TRL-FV-002 | B5: T004 | C5: Fotovoltaico | D5: C-FV-002 | E5: Inverter | F5: 9 | G5: Mercato | H5: Soluzione industriale consolidata con prestazioni elevate e vasta base installata. | I5: 2025 | J5: Globale | K5: S027 | L5: maturita molto alta
A6: TRL-FV-003 | B6: T004 | C6: Fotovoltaico | D6: C-FV-004 | E6: Tracker monoassiale | F6: 9 | G6: Mercato | H6: Componente standard in molti impianti utility-scale a terra. | I6: 2024 | J6: USA / Globale | K6: S014 | L6: adozione consolidata
A7: TRL-FV-004 | B7: T004 | C7: Fotovoltaico | D7: C-FV-003 | E7: Sistema di backup / accumulo | F7: 8 | G7: Pilota / mercato | H7: Soluzioni ormai commerciali ma con architetture e business model ancora in forte evoluzione. | I7: 2024 | J7: USA / UE / Globale | K7: S014 | L7: maturita alta ma non uniforme
A8: TRL-FV-005 | B8: T004 | C8: Fotovoltaico | D8: C-FV-007 | E8: Sistema agrivoltaico | F8: 7 | G8: Pilota / dimostratore | H8: Sistemi operativi e finanziabili in alcuni contesti, ma non ancora standardizzati universalmente. | I8: 2025 | J8: UE / Italia | K8: S026; S028 | L8: dipende da regole e layout agronomico
A9: TRL-FV-006 | B9: T004 | C9: Fotovoltaico | D9: C-FV-006 | E9: Modulo tandem perovskite-silicio | F9: 6 | G9: Lab / pilota | H9: Prestazioni elevate in laboratorio e prime linee pilota, con rischio tecnologico ancora significativo. | I9: 2025 | J9: Globale | K9: S017 | L9: tema da presidiare
A10: TRL-WI-001 | B10: T006 | C10: Eolico | D10: C-WI-001 | E10: Rotore e pale | F10: 9 | G10: Mercato | H10: Tecnologia consolidata su larga scala con continua evoluzione dimensionale. | I10: 2025 | J10: Globale | K10: S047 | L10: maturita molto alta
A11: TRL-WI-002 | B11: T006 | C11: Eolico | D11: C-WI-002 | E11: Nacelle e drivetrain | F11: 9 | G11: Mercato | H11: Soluzioni industriali mature sia geared sia direct-drive. | I11: 2025 | J11: Globale | K11: S046; S047 | L11: benchmark elevato
A12: TRL-WI-003 | B12: T006 | C12: Eolico | D12: C-WI-004 | E12: Fondazione fissa offshore | F12: 9 | G12: Mercato | H12: Standard industriale nei mercati offshore maturi. | I12: 2024 | J12: UE / Globale | K12: S037 | L12: adozione consolidata
A13: TRL-WI-004 | B13: T006 | C13: Eolico | D13: C-WI-005 | E13: Piattaforma floating | F13: 7 | G13: Pilota / dimostratore | H13: Primi progetti operativi e pipeline commerciale, ma non ancora pienamente standardizzata. | I13: 2025 | J13: Globale | K13: S044; S037 | L13: maturita intermedia-alta
A14: TRL-WI-005 | B14: T006 | C14: Eolico | D14: C-WI-006 | E14: Sistemi di controllo e condition monitoring | F14: 9 | G14: Mercato | H14: Tecnologia consolidata, con ulteriore spazio di miglioramento via analytics. | I14: 2024 | J14: Globale | K14: S036 | L14: digitale mainstream
A15: TRL-WI-006 | B15: T006 | C15: Eolico | D15: C-WI-007 | E15: Sottostazione e connessione di rete | F15: 9 | G15: Mercato | H15: Tecnologie mature, ma con complessita crescente su grande offshore e HVDC. | I15: 2024 | J15: UE / Globale | K15: S038; S037 | L15: maturita alta lato tecnologia
... A21: TRL-H2-006 | B21: T011 | C21: Idrogeno verde | D21: C-H2-007 | E21: Energy management e integrazione con rinnovabili | F21: 8 | G21: Pilota / mercato | H21: Architetture gia applicate in progetti reali, ma ottimizzazione ancora in rapida evoluzione. | I21: 2025 | J21: Globale | K21: S049; S061 | L21: abilitatore chiave
A22: TRL-CO-001 | B22: T001 | C22: Carbone | E22: Carbone | F22: 9 | G22: Medio in calo | H22: Valutazione sintetica portafoglio tecnologia | I22: Osservatorio ERMES - benchmark indicativo | J22: S077
A23: TRL-CO-002 | B23: T001 | C23: Carbone | D23: C-CO-002 | E23: Caldaia PC / USC | F23: 9 | G23: Medio in calo | H23: Commerciale ma con nuovo mercato limitato | I23: 400-900 | J23: S075
A24: TRL-CO-003 | B24: T001 | C24: Carbone | D24: C-CO-004 | E24: FGD / SCR / ESP | F24: 9 | G24: Maturo | H24: Ampiamente diffuse | I24: 150-300 | J24: S075
A25: TRL-CO-004 | B25: T001 | C25: Carbone | D25: C-CO-005 | E25: CCS retrofit | F25: 7 | G25: Basso | H25: Mercato dipendente da carbon price e infrastrutture CO2 | I25: 900-1800 | J25: S118
A26: TRL-CO-005 | B26: T001 | C26: Carbone | D26: C-CO-006 | E26: AUSC materials | F26: 6 | G26: Basso | H26: Necessita dimostrazione su larga scala | I26: n.d. | J26: S075
A27: TRL-CO-006 | B27: T001 | C27: Carbone | E27: Mercato | F27: 9 | G27: Medio in calo | H27: Benchmark integrato techno-market | I27: Valori indicativi | J27: S077
A28: TRL-OI-001 | B28: T002 | C28: Olio | E28: Olio | F28: 9 | G28: Alto ma in calo nei segmenti power | H28: Valutazione sintetica portafoglio tecnologia | I28: Osservatorio ERMES - benchmark indicativo | J28: S076
A29: TRL-OI-002 | B29: T002 | C29: Olio | D29: C-OI-003 | E29: Raffinazione | F29: 9 | G29: Stabile | H29: Mercato legato a competitivita industriale e fuel specs | I29: 1000-2500 | J29: S114
A30: TRL-OI-003 | B30: T002 | C30: Olio | D30: C-OI-005 | E30: Cogen e heat integration | F30: 9 | G30: Stabile | H30: Ampiamente adottabile su siti esistenti | I30: 50-200 | J30: S115
A31: TRL-OI-004 | B31: T002 | C31: Olio | D31: C-OI-006 | E31: Flare and methane monitoring | F31: 8 | G31: In crescita | H31: Spinto da regolazione methane abatement | I31: 5-50 | J31: S116
A32: TRL-OI-005 | B32: T002 | C32: Olio | D32: C-OI-004 | E32: Motori / turbine oil-fired | F32: 9 | G32: In calo | H32: Mercato residuale e replacement oriented | I32: 600-1200 | J32: S076
A33: TRL-OI-006 | B33: T002 | C33: Olio | E33: Mercato | F33: 9 | G33: Alto ma in calo nei segmenti power | H33: Benchmark integrato techno-market | I33: Valori indicativi | J33: S076
A34: TRL-GA-001 | B34: T003 | C34: Gas Naturale | E34: Gas Naturale | F34: 9 | G34: Alto ma condizionato da policy climatiche | H34: Valutazione sintetica portafoglio tecnologia | I34: Osservatorio ERMES - benchmark indicativo | J34: S074
A35: TRL-GA-002 | B35: T003 | C35: Gas Naturale | D35: C-GA-003 | E35: CCGT H/F class | F35: 9 | G35: Stabile | H35: Mercato ancora forte come flessibilita e backup rinnovabili | I35: 700-1200 | J35: S075
A36: TRL-GA-003 | B36: T003 | C36: Gas Naturale | D36: C-GA-002 | E36: Turbina a gas simple cycle | F36: 9 | G36: Stabile | H36: Mercato di capacita e reserve | I36: 450-850 | J36: S075
A37: TRL-GA-004 | B37: T003 | C37: Gas Naturale | D37: C-GA-005 | E37: CCS-ready / post-combustion CCS | F37: 7 | G37: Medio | H37: Serve carbon price e transport/storage CO2 | I37: 800-1500 | J37: S112
A38: TRL-GA-005 | B38: T003 | C38: Gas Naturale | D38: C-GA-006 | E38: Hydrogen-ready combustion | F38: 8 | G38: In crescita | H38: Segmento in espansione in Europa e Giappone | I38: 50-250 | J38: S111
A39: TRL-GA-006 | B39: T003 | C39: Gas Naturale | E39: Mercato | F39: 9 | G39: Alto ma condizionato da policy climatiche | H39: Benchmark integrato techno-market | I39: Valori indicativi | J39: S074
A40: TRL-ST-001 | B40: T005 | C40: Solare Termico | E40: Solare Termico | F40: 8 | G40: Medio in nicchie favorevoli | H40: Valutazione sintetica portafoglio tecnologia | I40: Osservatorio ERMES - benchmark indicativo | J40: S063
A41: TRL-ST-002 | B41: T005 | C41: Solare Termico | D41: C-ST-001 | E41: Campo collettori / eliostati | F41: 8 | G41: Medio | H41: Mercati migliori in aree ad alta DNI | I41: 1200-2500 | J41: S063
A42: TRL-ST-003 | B42: T005 | C42: Solare Termico | D42: C-ST-002 | E42: Serbatoio / TES termico | F42: 9 | G42: Medio | H42: Nucleo distintivo rispetto al FV | I42: 500-1200 | J42: S063
A43: TRL-ST-004 | B43: T005 | C43: Solare Termico | D43: C-ST-003 | E43: Ricevitore e fluido termovettore | F43: 8 | G43: Medio | H43: Incrementi graduali di performance | I43: 300-900 | J43: S063
A44: TRL-ST-005 | B44: T005 | C44: Solare Termico | D44: C-ST-004 | E44: Steam cycle / ORC / chiller | F44: 8 | G44: Medio | H44: Spazio per integrazione multi-servizio | I44: 400-1000 | J44: S063
A45: TRL-ST-006 | B45: T005 | C45: Solare Termico | E45: Mercato | F45: 8 | G45: Medio in nicchie favorevoli | H45: Benchmark integrato techno-market | I45: Valori indicativi | J45: S063
A46: TRL-HY-001 | B46: T007 | C46: Idroelettrico | E46: Idroelettrico | F46: 9 | G46: Alto ma con nuovi siti piu selettivi | H46: Valutazione sintetica portafoglio tecnologia | I46: Osservatorio ERMES - benchmark indicativo | J46: S068
A47: TRL-HY-002 | B47: T007 | C47: Idroelettrico | D47: C-HY-002 | E47: Turbina e generatore | F47: 9 | G47: Maturo | H47: Mercato prevalentemente replacement/repowering | I47: 500-1500 | J47: S069
A48: TRL-HY-003 | B48: T007 | C48: Idroelettrico | D48: C-HY-004 | E48: Pumped storage | F48: 9 | G48: In crescita | H48: Domanda spinta da rinnovabili variabili | I48: 1000-3000 | J48: S103
A49: TRL-HY-004 | B49: T007 | C49: Idroelettrico | D49: C-HY-005 | E49: Repowering e upgrading | F49: 9 | G49: Medio | H49: Pipeline ampia su asset esistenti | I49: 300-1200 | J49: S069
A50: TRL-HY-005 | B50: T007 | C50: Idroelettrico | D50: C-HY-006 | E50: Fish passage e monitoraggio | F50: 8 | G50: In crescita | H50: Più rilevante in permitting nuovi siti | I50: n.d. | J50: S068
A51: TRL-HY-006 | B51: T007 | C51: Idroelettrico | E51: Mercato | F51: 9 | G51: Alto ma con nuovi siti piu selettivi | H51: Benchmark integrato techno-market | I51: Valori indicativi | J51: S068
A52: TRL-BM-001 | B52: T008 | C52: Biomasse | E52: Biomasse | F52: 8 | G52: Medio-alto ma molto feedstock-dependent | H52: Valutazione sintetica portafoglio tecnologia | I52: Osservatorio ERMES - benchmark indicativo | J52: S065
A53: TRL-BM-002 | B53: T008 | C53: Biomasse | D53: C-BM-002 | E53: Boiler / combustione | F53: 9 | G53: Stabile | H53: Mercato legato a filiere locali e calore utile | I53: 1500-3000 | J53: S066
A54: TRL-BM-003 | B54: T008 | C54: Biomasse | D54: C-BM-004 | E54: Digestione anaerobica | F54: 9 | G54: In crescita | H54: Spinto da biometano e waste management | I54: 800-2000 | J54: S082
A55: TRL-BM-004 | B55: T008 | C55: Biomasse | D55: C-BM-005 | E55: Biometano / bioLNG | F55: 8 | G55: In crescita | H55: Mercato trainato da policy e rete gas | I55: 0.5-1.5 | J55: S082
A56: TRL-BM-005 | B56: T008 | C56: Biomasse | D56: C-BM-003 | E56: Gasificazione | F56: 7 | G56: Medio | H56: Interesse per fuels e chemicals | I56: 2500-5000 | J56: S066
A57: TRL-BM-006 | B57: T008 | C57: Biomasse | E57: Mercato | F57: 8 | G57: Medio-alto ma molto feedstock-dependent | H57: Benchmark integrato techno-market | I57: Valori indicativi | J57: S065
A58: TRL-GEO-001 | B58: T009 | C58: Geotermico | E58: Geotermico | F58: 8 | G58: Medio-alto, in crescita per next-gen geothermal | H58: Valutazione sintetica portafoglio tecnologia | I58: Osservatorio ERMES - benchmark indicativo | J58: S079
A59: TRL-GEO-002 | B59: T009 | C59: Geotermico | D59: C-GEO-002 | E59: Drilling e completamento pozzi | F59: 8 | G59: In crescita | H59: Riduzioni costo cruciali per scalare il settore | I59: 1500-4000 | J59: S080
A60: TRL-GEO-003 | B60: T009 | C60: Geotermico | D60: C-GEO-003 | E60: Flash / dry steam / ORC | F60: 9 | G60: Stabile | H60: Ampia esperienza commerciale | I60: 800-1800 | J60: S080
A61: TRL-GEO-004 | B61: T009 | C61: Geotermico | D61: C-GEO-005 | E61: EGS | F61: 6 | G61: In crescita | H61: Spinto da learning del settore oil&gas | I61: 5000-12000 | J61: S100
A62: TRL-GEO-005 | B62: T009 | C62: Geotermico | D62: C-GEO-006 | E62: Closed-loop geothermal | F62: 5 | G62: In crescita | H62: Ancora early market | I62: n.d. | J62: S101
A63: TRL-GEO-006 | B63: T009 | C63: Geotermico | E63: Mercato | F63: 8 | G63: Medio-alto, in crescita per next-gen geothermal | H63: Benchmark integrato techno-market | I63: Valori indicativi | J63: S079
A64: TRL-NU-001 | B64: T010 | C64: Nucleare da fissione | E64: Nucleare da fissione | F64: 8 | G64: Medio-alto, con forte dipendenza da execution e supply chain | H64: Valutazione sintetica portafoglio tecnologia | I64: Osservatorio ERMES - benchmark indicativo | J64: S070
A65: TRL-NU-002 | B65: T010 | C65: Nucleare da fissione | D65: C-NUC-001 | E65: Reattore e vessel | F65: 8 | G65: Medio | H65: Mercato trainato da nuove build selettive e life extension | I65: 2000-5000 | J65: S070
A66: TRL-NU-003 | B66: T010 | C66: Nucleare da fissione | D66: C-NUC-004 | E66: Sistemi di sicurezza passivi | F66: 9 | G66: Medio | H66: Standard chiave per accettabilita e licensing | I66: n.d. | J66: S073
A67: TRL-NU-004 | B67: T010 | C67: Nucleare da fissione | D67: C-NUC-005 | E67: Fuel cycle, waste e decommissioning | F67: 9 | G67: Stabile | H67: Necessita forte quadro istituzionale | I67: n.d. | J67: S073
A68: TRL-NU-005 | B68: T010 | C68: Nucleare da fissione | D68: C-NUC-006 | E68: SMR / modular factory | F68: 6 | G68: In crescita | H68: Early projects e strategie industriali in avvio | I68: n.d. | J68: S086
A69: TRL-NU-006 | B69: T010 | C69: Nucleare da fissione | E69: Mercato | F69: 8 | G69: Medio-alto, con forte dipendenza da execution e supply chain | H69: Benchmark integrato techno-market | I69: Valori indicativi | J69: S070

Sheet 08_Costi_Compet
A1: 08_Costi_Compet | Costi e competitività
A2: Area 4 del brief: CAPEX, OPEX, LCOE/LCOS, trend di costo, incentivi e driver competitivi.
A3: Record_ID | B3: Tech_ID | C3: Tecnologia | D3: Comp_ID | E3: Metrica costo / competitività | F3: Valore | G3: Unità | H3: Valuta | I3: Anno | J3: Geografia | K3: Trend | L3: Incentivo / driver | M3: Fonte_ID | N3: Note
A4: COST-FV-001 | B4: T004 | C4: Fotovoltaico | E4: CAPEX utility-scale PV-only | F4: 1.12 | G4: USD/Wdc | H4: USD | I4: 2024 | J4: USA | K4: Strutturalmente in calo nel lungo periodo | L4: LCOE molto competitivo; learning curve elevata | M4: S014 | N4: benchmark NREL Q1 2024, impianto 100 MWdc
A5: COST-FV-002 | B5: T004 | C5: Fotovoltaico | E5: CAPEX residenziale PV-only | F5: 3.15 | G5: USD/Wdc | H5: USD | I5: 2024 | J5: USA | K5: In riduzione, ma meno rapidamente dell utility-scale | L5: Driver: scala, permitting, BOS e soft costs | M5: S014 | N5: benchmark NREL Q1 2024
A6: COST-FV-003 | B6: T004 | C6: Fotovoltaico | D6: C-FV-003 | E6: CAPEX utility-scale PV+BESS (2,4h) | F6: 1.99 | G6: USD/Wdc | H6: USD | I6: 2024 | J6: USA | K6: In progressiva ottimizzazione | L6: Driver: arbitraggio, riduzione curtailment, capacity value | M6: S014 | N6: benchmark NREL Q1 2024
A7: COST-FV-004 | B7: T004 | C7: Fotovoltaico | E7: Tariffa PPA / energia aggiudicata | F7: 1.32 | G7: US cent/kWh | H7: USD | I7: 2020 | J7: EAU | K7: Record competitivo in utility-scale | L7: Sito e scala di progetto, ottimo resource base, filiera efficiente | M7: S023 | N7: tariffa annunciata per Al Dhafra
A8: COST-FV-005 | B8: T004 | C8: Fotovoltaico | D8: C-FV-001 | E8: Trend prezzo moduli c-Si | F8: -33 | G8: percento | H8: n.a. | I8: 2024 | J8: Globale | K8: Riduzione molto forte nel 2024 | L8: Spinta competitiva su utility-scale, rooftop e repowering | M8: S017 | N8: variazione spot price indicata in roadmap
A9: COST-FV-006 | B9: T004 | C9: Fotovoltaico | D9: C-FV-007 | E9: LCOE agrivoltaico | F9: 0.095 | G9: EUR/kWh | H9: EUR | I9: 2024 | J9: Germania / UE | K9: In calo con standardizzazione e scala | L9: Driver: dual land use, valore agricolo, incentivi dedicati | M9: S026 | N9: intervallo indicativo 0,07-0,12 EUR/kWh; valore inserito come punto medio
A10: COST-WI-001 | B10: T006 | C10: Eolico | E10: CAPEX land-based wind | F10: 1.6 | G10: USD/W | H10: USD | I10: 2024 | J10: USA | K10: Competitiva ma influenzata da supply chain e tassi | L10: Driver: taglia turbine, altezza torre, logistica e permitting | M10: S034 | N10: valore indicativo benchmark ATB 2024
A11: COST-WI-002 | B11: T006 | C11: Eolico | E11: CAPEX offshore fixed-bottom | F11: 4.8 | G11: USD/W | H11: USD | I11: 2024 | J11: USA / UE | K11: In calo nel lungo termine ma sotto pressione nel breve | L11: Driver: fondazioni, cavi, porti, navi e tassi | M11: S035; S037 | N11: valore indicativo benchmark offshore
A12: COST-WI-003 | B12: T006 | C12: Eolico | D12: C-WI-005 | E12: CAPEX offshore floating | F12: 6.6 | G12: USD/W | H12: USD | I12: 2024 | J12: Globale | K12: Atteso in riduzione con scala e standardizzazione | L12: Driver: piattaforme, ormeggi, assemblaggio e learning curve | M12: S035; S044 | N12: frontiera con forte potenziale di cost down
A13: COST-WI-004 | B13: T006 | C13: Eolico | E13: OPEX land-based wind | F13: 44 | G13: USD/kW-anno | H13: USD | I13: 2024 | J13: USA | K13: Ottimizzabile con condition monitoring e repowering | L13: Driver: disponibilita, ricambi, accessibilita del sito | M13: S034; S036 | N13: valore indicativo benchmark
A14: COST-WI-005 | B14: T006 | C14: Eolico | E14: Fattore incentivo / subsidy | F14: 0 | G14: EUR/MWh | H14: EUR | I14: 2024 | J14: Paesi Bassi | K14: Segnale di crescente competitivita in mercati maturi | L14: Driver: risorsa, taglia, rischio, pianificazione di rete | M14: S045 | N14: Hollandse Kust Zuid come riferimento subsidy-free
A15: COST-WI-006 | B15: T006 | C15: Eolico | D15: C-WI-001 | E15: Taglia turbina offshore di frontiera | F15: 14.7 | G15: MW | H15: n.a. | I15: 2025 | J15: Globale | K15: Trend di aumento taglia e riduzione BOS per MW | L15: Driver: LCOE, minor numero unita, maggiore resa | M15: S046 | N15: metrica competitiva indiretta
A16: COST-H2-001 | B16: T011 | C16: Idrogeno verde | D16: C-H2-001 | E16: CAPEX electrolyzer alkaline | F16: 700 | G16: USD/kW | H16: USD | I16: 2025 | J16: Globale | K16: In calo con scala e manifattura | L16: Driver: materiali, volumi, learning rate | M16: S049; S055 | N16: valore indicativo di ordine di grandezza
A17: COST-H2-002 | B17: T011 | C17: Idrogeno verde | D17: C-H2-002 | E17: CAPEX electrolyzer PEM | F17: 950 | G17: USD/kW | H17: USD | I17: 2025 | J17: Globale | K17: Atteso in calo ma ancora sopra alkaline | L17: Driver: iridio, produzione stack, BOP e volumi | M17: S050; S049 | N17: valore indicativo di ordine di grandezza
A18: COST-H2-003 | B18: T011 | C18: Idrogeno verde | D18: C-H2-003 | E18: CAPEX electrolyzer SOEC | F18: 1400 | G18: USD/kW | H18: USD | I18: 2025 | J18: Globale | K18: Riduzione attesa se la tecnologia scala | L18: Driver: materiali ceramici, durabilita, integrazione termica | M18: S055 | N18: valore indicativo per tecnologia avanzata
A19: COST-H2-004 | B19: T011 | C19: Idrogeno verde | E19: LCOH green hydrogen | F19: 4.5 | G19: USD/kgH2 | H19: USD | I19: 2025 | J19: Globale | K19: Molto sensibile a costo elettricita e utilization rate | L19: Driver: prezzo energia, CAPEX, load factor, financing | M19: S049 | N19: ordine di grandezza medio attuale
A20: COST-H2-005 | B20: T011 | C20: Idrogeno verde | E20: Target di competitivita clean hydrogen | F20: 1 | G20: USD/kgH2 | H20: USD | I20: 2031 | J20: USA / Globale | K20: Target di lungo termine | L20: Driver: Hydrogen Shot, innovazione, scala e accesso a rinnovabili low-cost | M20: S051 | N20: target 1-1-1 DOE
A21: COST-H2-006 | B21: T011 | C21: Idrogeno verde | E21: Quota costo elettricita nel LCOH | F21: 60 | G21: percento | H21: n.a. | I21: 2025 | J21: Globale | K21: Peso molto elevato sul business case | L21: Driver: PPA, autoconsumo rinnovabile, flessibilita di esercizio | M21: S049 | N21: indicatore sintetico
A22: COST-CO-001 | B22: T001 | C22: Carbone | E22: CAPEX | F22: 2500-4500 | G22: EUR/kW | H22: Stabile / in lieve calo | I22: Ordine di grandezza new build o impianto di riferimento | J22: S077
A23: COST-CO-002 | B23: T001 | C23: Carbone | E23: OPEX | F23: 35-70 | G23: EUR/kW-anno | H23: Stabile | I23: Ordine di grandezza esercizio e manutenzione | J23: S077
A24: COST-CO-003 | B24: T001 | C24: Carbone | E24: LCOE | F24: 90-160 | G24: EUR/MWh | H24: Volatile / site-specific | I24: Range indicativo techno-economic | J24: S077
A25: COST-CO-004 | B25: T001 | C25: Carbone | D25: C-CO-002 | E25: CAPEX | F25: 400-900 | G25: EUR/kW | H25: Dipende da scala e supply chain | I25: miglioramenti su componenti e materiali | J25: S075
A26: COST-CO-005 | B26: T001 | C26: Carbone | D26: C-CO-004 | E26: CAPEX | F26: 150-300 | G26: EUR/kW | H26: Dipende da scala e supply chain | I26: abbattimento inquinanti locali | J26: S075
A27: COST-CO-006 | B27: T001 | C27: Carbone | D27: C-CO-005 | E27: CAPEX | F27: 900-1800 | G27: EUR/kW | H27: Dipende da scala e supply chain | I27: capex add-on per capture train | J27: S118
A28: COST-OI-001 | B28: T002 | C28: Olio | E28: CAPEX | F28: 1200-4000 | G28: EUR/kW | H28: Stabile / in lieve calo | I28: Ordine di grandezza new build o impianto di riferimento | J28: S076
A29: COST-OI-002 | B29: T002 | C29: Olio | E29: OPEX | F29: variabile | G29: EUR/kW-anno | H29: Stabile | I29: Ordine di grandezza esercizio e manutenzione | J29: S076
A30: COST-OI-003 | B30: T002 | C30: Olio | E30: LCOE | F30: 130-220 | G30: EUR/MWh | H30: Volatile / site-specific | I30: Range indicativo techno-economic | J30: S076
A31: COST-OI-004 | B31: T002 | C31: Olio | D31: C-OI-003 | E31: CAPEX | F31: 1000-2500 | G31: EUR/tpd eq | H31: Dipende da scala e supply chain | I31: ordine di grandezza upgrading | J31: S114
A32: COST-OI-005 | B32: T002 | C32: Olio | D32: C-OI-005 | E32: CAPEX | F32: 50-200 | G32: EUR/t throughput | H32: Dipende da scala e supply chain | I32: progetti efficienza | J32: S115
A33: COST-OI-006 | B33: T002 | C33: Olio | D33: C-OI-006 | E33: CAPEX | F33: 5-50 | G33: EUR/boe capacity | H33: Dipende da scala e supply chain | I33: digital and monitoring | J33: S116
A34: COST-GA-001 | B34: T003 | C34: Gas Naturale | E34: CAPEX | F34: 800-1800 | G34: EUR/kW | H34: Stabile / in lieve calo | I34: Ordine di grandezza new build o impianto di riferimento | J34: S074
A35: COST-GA-002 | B35: T003 | C35: Gas Naturale | E35: OPEX | F35: 10-35 | G35: EUR/kW-anno | H35: Stabile | I35: Ordine di grandezza esercizio e manutenzione | J35: S074
A36: COST-GA-003 | B36: T003 | C36: Gas Naturale | E36: LCOE | F36: 70-120 | G36: EUR/MWh | H36: Volatile / site-specific | I36: Range indicativo techno-economic | J36: S074
A37: COST-GA-004 | B37: T003 | C37: Gas Naturale | D37: C-GA-003 | E37: CAPEX | F37: 700-1200 | G37: EUR/kW | H37: Dipende da scala e supply chain | I37: new build CCGT | J37: S075
A38: COST-GA-005 | B38: T003 | C38: Gas Naturale | D38: C-GA-002 | E38: CAPEX | F38: 450-850 | G38: EUR/kW | H38: Dipende da scala e supply chain | I38: peaker CT | J38: S075
A39: COST-GA-006 | B39: T003 | C39: Gas Naturale | D39: C-GA-005 | E39: CAPEX | F39: 800-1500 | G39: EUR/kW add-on | H39: Dipende da scala e supply chain | I39: capture train | J39: S112
A40: COST-ST-001 | B40: T005 | C40: Solare Termico | E40: CAPEX | F40: 4500-9000 | G40: EUR/kW | H40: Stabile / in lieve calo | I40: Ordine di grandezza new build o impianto di riferimento | J40: S063
A41: COST-ST-002 | B41: T005 | C41: Solare Termico | E41: OPEX | F41: 60-120 | G41: EUR/kW-anno | H41: Stabile | I41: Ordine di grandezza esercizio e manutenzione | J41: S063
A42: COST-ST-003 | B42: T005 | C42: Solare Termico | E42: LCOE | F42: 110-220 | G42: EUR/MWh | H42: Volatile / site-specific | I42: Range indicativo techno-economic | J42: S063
A43: COST-ST-004 | B43: T005 | C43: Solare Termico | D43: C-ST-001 | E43: CAPEX | F43: 1200-2500 | G43: EUR/kWth eq | H43: Dipende da scala e supply chain | I43: campo solare | J43: S063
A44: COST-ST-005 | B44: T005 | C44: Solare Termico | D44: C-ST-002 | E44: CAPEX | F44: 500-1200 | G44: EUR/kWhth | H44: Dipende da scala e supply chain | I44: storage termico | J44: S063
A45: COST-ST-006 | B45: T005 | C45: Solare Termico | D45: C-ST-003 | E45: CAPEX | F45: 300-900 | G45: EUR/kW eq | H45: Dipende da scala e supply chain | I45: receiver/HTF | J45: S063
A46: COST-HY-001 | B46: T007 | C46: Idroelettrico | E46: CAPEX | F46: 3000-8000 | G46: EUR/kW | H46: Stabile / in lieve calo | I46: Ordine di grandezza new build o impianto di riferimento | J46: S068
A47: COST-HY-002 | B47: T007 | C47: Idroelettrico | E47: OPEX | F47: 20-60 | G47: EUR/kW-anno | H47: Stabile | I47: Ordine di grandezza esercizio e manutenzione | J47: S068
A48: COST-HY-003 | B48: T007 | C48: Idroelettrico | E48: LCOE | F48: 40-120 | G48: EUR/MWh | H48: Volatile / site-specific | I48: Range indicativo techno-economic | J48: S068
A49: COST-HY-004 | B49: T007 | C49: Idroelettrico | D49: C-HY-002 | E49: CAPEX | F49: 500-1500 | G49: EUR/kW eq | H49: Dipende da scala e supply chain | I49: componenti elettromeccanici | J49: S069
A50: COST-HY-005 | B50: T007 | C50: Idroelettrico | D50: C-HY-004 | E50: CAPEX | F50: 1000-3000 | G50: EUR/kWh eq storage component | H50: Dipende da scala e supply chain | I50: site-specific | J50: S103
A51: COST-HY-006 | B51: T007 | C51: Idroelettrico | D51: C-HY-005 | E51: CAPEX | F51: 300-1200 | G51: EUR/kW | H51: Dipende da scala e supply chain | I51: revamping capex | J51: S069
A52: COST-BM-001 | B52: T008 | C52: Biomasse | E52: CAPEX | F52: 3000-6000 | G52: EUR/kW | H52: Stabile / in lieve calo | I52: Ordine di grandezza new build o impianto di riferimento | J52: S065
A53: COST-BM-002 | B53: T008 | C53: Biomasse | E53: OPEX | F53: 40-120 | G53: EUR/kW-anno | H53: Stabile | I53: Ordine di grandezza esercizio e manutenzione | J53: S065
A54: COST-BM-003 | B54: T008 | C54: Biomasse | E54: LCOE | F54: 90-180 | G54: EUR/MWh | H54: Volatile / site-specific | I54: Range indicativo techno-economic | J54: S065
A55: COST-BM-004 | B55: T008 | C55: Biomasse | D55: C-BM-002 | E55: CAPEX | F55: 1500-3000 | G55: EUR/kW | H55: Dipende da scala e supply chain | I55: combustione biomass power | J55: S066
A56: COST-BM-005 | B56: T008 | C56: Biomasse | D56: C-BM-004 | E56: CAPEX | F56: 800-2000 | G56: EUR/kW eq | H56: Dipende da scala e supply chain | I56: biogas plants | J56: S082
A57: COST-BM-006 | B57: T008 | C57: Biomasse | D57: C-BM-005 | E57: CAPEX | F57: 0.5-1.5 | G57: EUR/Nm3 annual capacity | H57: Dipende da scala e supply chain | I57: indicativo | J57: S082
A58: COST-GEO-001 | B58: T009 | C58: Geotermico | E58: CAPEX | F58: 3500-8500 | G58: EUR/kW | H58: Stabile / in lieve calo | I58: Ordine di grandezza new build o impianto di riferimento | J58: S079
A59: COST-GEO-002 | B59: T009 | C59: Geotermico | E59: OPEX | F59: 20-50 | G59: EUR/kW-anno | H59: Stabile | I59: Ordine di grandezza esercizio e manutenzione | J59: S079
A60: COST-GEO-003 | B60: T009 | C60: Geotermico | E60: LCOE | F60: 45-120 | G60: EUR/MWh | H60: Volatile / site-specific | I60: Range indicativo techno-economic | J60: S079
A61: COST-GEO-004 | B61: T009 | C61: Geotermico | D61: C-GEO-002 | E61: CAPEX | F61: 1500-4000 | G61: EUR/kW eq | H61: Dipende da scala e supply chain | I61: forte dipendenza da profondita | J61: S080
A62: COST-GEO-005 | B62: T009 | C62: Geotermico | D62: C-GEO-003 | E62: CAPEX | F62: 800-1800 | G62: EUR/kW eq | H62: Dipende da scala e supply chain | I62: power block | J62: S080
A63: COST-GEO-006 | B63: T009 | C63: Geotermico | D63: C-GEO-005 | E63: CAPEX | F63: 5000-12000 | G63: EUR/kW | H63: Dipende da scala e supply chain | I63: early projects | J63: S100
A64: COST-NU-001 | B64: T010 | C64: Nucleare da fissione | E64: CAPEX | F64: 6000-12000 | G64: EUR/kW | H64: Stabile / in lieve calo | I64: Ordine di grandezza new build o impianto di riferimento | J64: S070
A65: COST-NU-002 | B65: T010 | C65: Nucleare da fissione | E65: OPEX | F65: 80-160 | G65: EUR/kW-anno | H65: Stabile | I65: Ordine di grandezza esercizio e manutenzione | J65: S070
A66: COST-NU-003 | B66: T010 | C66: Nucleare da fissione | E66: LCOE | F66: 90-180 | G66: EUR/MWh | H66: Volatile / site-specific | I66: Range indicativo techno-economic | J66: S070
A67: COST-NU-004 | B67: T010 | C67: Nucleare da fissione | D67: C-NUC-001 | E67: CAPEX | F67: 2000-5000 | G67: EUR/kW eq | H67: Dipende da scala e supply chain | I67: nuclear island share | J67: S070
A68: COST-NU-005 | B68: T010 | C68: Nucleare da fissione | D68: C-NUC-004 | E68: CAPEX | F68: n.d. | G68: n.d. | H68: Dipende da scala e supply chain | I68: embedded in plant capex | J68: S073
A69: COST-NU-006 | B69: T010 | C69: Nucleare da fissione | D69: C-NUC-005 | E69: CAPEX | F69: n.d. | G69: n.d. | H69: Dipende da scala e supply chain | I69: lifecycle management | J69: S073

Sheet 09_Settori_Impatto
A1: 09_Settori_Impatto | Settori economici di impatto
A2: Area 5 del brief: settori di impatto della tecnologia (agricoltura, industria, trasporti, PA, ecc.).
A3: Record_ID | B3: Tech_ID | C3: Tecnologia | D3: Comp_ID | E3: Settore economico | F3: Caso d'uso / applicazione | G3: Tipo impatto | H3: Intensità impatto | I3: Orizzonte temporale | J3: Geografia | K3: Fonte_ID | L3: Note
A4: SET-FV-001 | B4: T004 | C4: Fotovoltaico | E4: Residenziale | F4: Autoconsumo individuale, autoconsumo collettivo e CER | G4: Riduzione costo energia e decarbonizzazione diffusa | H4: Alta | I4: Breve-medio termine | J4: Italia / UE | K4: S020 | L4: mercato spinto da incentivi e regole autoconsumo
A5: SET-FV-002 | B5: T004 | C5: Fotovoltaico | E5: Industria | F5: Impianti onsite, PPAs e coperture contro volatilita energia | G5: Competitivita industriale, hedging e riduzione Scope 2 | H5: Alta | I5: Breve-medio termine | J5: Globale / UE | K5: S012 | L5: interesse alto nei settori energy-intensive
A6: SET-FV-003 | B6: T004 | C6: Fotovoltaico | D6: C-FV-007 | E6: Agricoltura | F6: Agrivoltaico, pompe irrigue, serre e aziende agricole | G6: Nuove entrate, resilienza idrica e migliore uso del suolo | H6: Medio-alta | I6: Medio termine | J6: UE / Italia | K6: S026; S028 | L6: segmento strategico per territorio e consenso
A7: SET-FV-004 | B7: T004 | C7: Fotovoltaico | E7: Pubblica Amministrazione | F7: Edifici pubblici, scuole, parcheggi e illuminazione | G7: Riduzione spesa pubblica, educazione climatica e CO2 evitata | H7: Media | I7: Breve termine | J7: Italia / UE | K7: S020 | L7: rilevante per programmi di riqualificazione
A8: SET-FV-005 | B8: T004 | C8: Fotovoltaico | D8: C-FV-003 | E8: Utility | F8: Grandi impianti a terra, floating e sistemi ibridi con BESS | G8: Decarbonizzazione del mix elettrico e capacity value | H8: Alta | I8: Breve-medio termine | J8: Globale | K8: S012; S014 | L8: forte leva su nuovi MW installati
A9: SET-FV-006 | B9: T004 | C9: Fotovoltaico | E9: Trasporti | F9: Pensiline FV, hub di ricarica EV e logistica | G9: Integrazione energia-mobilita e riduzione costi operativi | H9: Media | I9: Medio termine | J9: Globale / UE | K9: S018 | L9: utile nei nodi di domanda diurna
A10: SET-WI-001 | B10: T006 | C10: Eolico | E10: Utility | F10: Parchi eolici onshore e offshore per generazione bulk power | G10: Decarbonizzazione del mix elettrico e sicurezza energetica | H10: Alta | I10: Breve-medio termine | J10: Globale / UE | K10: S033 | L10: segmento core della tecnologia
A11: SET-WI-002 | B11: T006 | C11: Eolico | E11: Industria | F11: Corporate PPA e approvvigionamento rinnovabile per siti energy-intensive | G11: Riduzione Scope 2 e hedging prezzo energia | H11: Alta | I11: Breve-medio termine | J11: UE / Globale | K11: S033; S036 | L11: rilevante per competitivita industriale
A12: SET-WI-003 | B12: T006 | C12: Eolico | D12: C-WI-005 | E12: Porti e filiere marine | F12: Sviluppo offshore e floating con impatti su porti, cantieristica e supply chain | G12: Nuova occupazione, investimenti industriali e export | H12: Alta | I12: Medio-lungo termine | J12: UE | K12: S038; S039 | L12: leva industriale rilevante
A13: SET-WI-004 | B13: T006 | C13: Eolico | E13: Agricoltura / aree rurali | F13: Canoni, compatibilita con usi agricoli e redditi aggiuntivi nelle aree interne | G13: Entrate locali e sviluppo territoriale | H13: Media | I13: Breve-medio termine | J13: UE / Italia | K13: S041 | L13: impatti condizionati da accettabilita
A14: SET-WI-005 | B14: T006 | C14: Eolico | E14: Isole e sistemi isolati | F14: Riduzione consumo diesel e maggiore autonomia energetica | G14: Sicurezza energetica e riduzione costi di approvvigionamento | H14: Media-alta | I14: Breve-medio termine | J14: Globale | K14: S033 | L14: utile dove il costo marginale fossile e alto
A15: SET-WI-006 | B15: T006 | C15: Eolico | D15: C-WI-007 | E15: Idrogeno / Power-to-X | F15: Elettricita eolica per elettrolizzatori e produzioni derivative | G15: Abilitazione nuovi vettori e decarbonizzazione hard-to-abate | H15: Media-alta | I15: Medio-lungo termine | J15: UE / Globale | K15: S038; S049 | L15: ponte tra elettrificazione e molecole verdi
A16: SET-H2-001 | B16: T011 | C16: Idrogeno verde | E16: Siderurgia | F16: Riduzione diretta del minerale e processi DRI/EAF | G16: Decarbonizzazione hard-to-abate | H16: Alta | I16: Medio-lungo termine | J16: UE / Globale | K16: S059; S049 | L16: caso d uso strategico
A17: SET-H2-002 | B17: T011 | C17: Idrogeno verde | E17: Raffinazione e chimica | F17: Sostituzione dell H2 fossile in raffinerie, ammoniaca e metanolo | G17: Riduzione emissioni di feedstock e processo | H17: Alta | I17: Breve-medio termine | J17: UE / Globale | K17: S060; S061 | L17: early market piu concreto
A18: SET-H2-003 | B18: T011 | C18: Idrogeno verde | E18: Fertilizzanti | F18: Produzione di ammoniaca a basse emissioni | G18: Decarbonizzazione di filiere essenziali | H18: Alta | I18: Breve-medio termine | J18: UE / Globale | K18: S061 | L18: caso d uso industriale diretto
A19: SET-H2-004 | B19: T011 | C19: Idrogeno verde | E19: Trasporti pesanti | F19: Camion, shipping, e-fuels per aviazione e marittimo | G19: Riduzione emissioni in segmenti difficili da elettrificare | H19: Media | I19: Medio-lungo termine | J19: Globale | K19: S048; S052 | L19: dipende da infrastruttura e costo del vettore
A20: SET-H2-005 | B20: T011 | C20: Idrogeno verde | D20: C-H2-005 | E20: Sistema energetico | F20: Storage stagionale e flessibilita di sistema | G20: Integrazione rinnovabili e resilienza | H20: Media | I20: Lungo termine | J20: UE / Globale | K20: S048; S049 | L20: piu prospettico nel breve
A21: SET-H2-006 | B21: T011 | C21: Idrogeno verde | E21: Pubblica Amministrazione / cluster industriali | F21: Hydrogen valleys, hub portuali e distretti territoriali | G21: Sviluppo ecosistemi industriali e infrastrutturali | H21: Media-alta | I21: Breve-medio termine | J21: Italia / UE | K21: S057; S054 | L21: utile per early market formation
A22: SECT-CO-001 | B22: T001 | C22: Carbone | D22: Industria | E22: Uso in siderurgia, cemento e vapore industriale in mercati con forte dipendenza dal carbone. | F22: Alta | G22: Breve termine | H22: S077
A23: SECT-CO-002 | B23: T001 | C23: Carbone | D23: Utility | E23: Baseload e mid-merit in sistemi ancora carbon-intensive. | F23: Alta | G23: Breve termine | H23: S077
A24: SECT-CO-003 | B24: T001 | C24: Carbone | D24: Pubblica Amministrazione | E24: Impatto su sicurezza energetica e politiche di phase-out/just transition. | F24: Media | G24: Medio termine | H24: S089
A25: SECT-CO-004 | B25: T001 | C25: Carbone | D25: Trasporti | E25: Ruolo indiretto via supply chain mineraria e logistica bulk. | F25: Bassa | G25: Breve termine | H25: S077
A26: SECT-CO-005 | B26: T001 | C26: Carbone | D26: Edilizia | E26: Uso residuale in alcuni sistemi di teleriscaldamento e calore. | F26: Bassa | G26: Breve termine | H26: S077
A27: SECT-CO-006 | B27: T001 | C27: Carbone | D27: Altro | E27: CCUS e conversione di siti coal verso hub energetici e CO2 infrastructure. | F27: Media | G27: Lungo termine | H27: S118
A28: SECT-OI-001 | B28: T002 | C28: Olio | D28: Trasporti | E28: Settore principale di impatto per carburanti liquidi in mobilita terrestre, aerea e marittima. | F28: Alta | G28: Breve-medio termine | H28: S088
A29: SECT-OI-002 | B29: T002 | C29: Olio | D29: Industria | E29: Feedstock petrolchimico, calore di processo e supply chain industriale. | F29: Alta | G29: Breve termine | H29: S076
A30: SECT-OI-003 | B30: T002 | C30: Olio | D30: Utility | E30: Ruolo residuale per generazione di picco, isole e backup. | F30: Media | G30: Breve termine | H30: S076
A31: SECT-OI-004 | B31: T002 | C31: Olio | D31: Pubblica Amministrazione | E31: Impatto su bilancia energetica, sicurezza approvvigionamenti e accise. | F31: Alta | G31: Breve termine | H31: S088
A32: SECT-OI-005 | B32: T002 | C32: Olio | D32: Agricoltura | E32: Uso indiretto via carburanti, fertilizzanti e logistica. | F32: Media | G32: Breve termine | H32: S076
A33: SECT-OI-006 | B33: T002 | C33: Olio | D33: Altro | E33: Transizione verso bioraffinerie e prodotti a minore intensita carbonica. | F33: Media | G33: Medio termine | H33: S115
... A69: SECT-NU-006 | B69: T010 | C69: Nucleare da fissione | D69: Altro | E69: SMR e sistemi cogenerativi per data center, isole industriali e military/base load applications. | F69: Media | G69: Lungo termine | H69: S086

Sheet 10_Sostenibilita
A1: 10_Sostenibilita | Sostenibilità ambientale e compatibilità UE
A2: Area 6 del brief: LCA, emissioni GHG, risorse critiche, tassonomia UE e altri impatti ambientali/sociali.
A3: Record_ID | B3: Tech_ID | C3: Tecnologia | D3: Comp_ID | E3: LCA disponibile | F3: Emissioni GHG lifecycle | G3: Unità GHG | H3: Uso risorse critiche | I3: Compatibilità Tassonomia UE | J3: Altri impatti ambientali / sociali | K3: Fonte_ID | L3: Note
A4: SUS-FV-001 | B4: T004 | C4: Fotovoltaico | E4: Si | F4: 23 | G4: gCO2e/kWh | H4: Silicio, argento, rame e alluminio; in alcune filiere attenzione anche a indio e altri metalli speciali | I4: Compatibile in via generale come attivita di generazione/installazione se rispetta i Technical Screening Criteria e il principio DNSH | J4: Emissioni lifecycle molto inferiori alle fonti fossili; attenzione a uso suolo, end-of-life, riciclo e catena di fornitura | K4: S015; S021; S022 | L4: range di riferimento NREL 10-36 gCO2e/kWh; valore 23 inserito come punto medio per il pilot
A5: SUS-FV-002 | B5: T004 | C5: Fotovoltaico | D5: C-FV-001 | E5: Si | F5: 23 | G5: gCO2e/kWh | H5: Hotspot materiali/manifattura: silicio, vetro, alluminio, argento | I5: Compatibile se la catena di fornitura e i processi rispettano criteri ambientali e sociali applicabili | J5: La circolarita e il riciclo riducono il rischio materiali e l impronta lungo il ciclo di vita | K5: S021; S015 | L5: focus sul modulo come componente dominante del footprint
A6: SUS-FV-003 | B6: T004 | C6: Fotovoltaico | D6: C-FV-007 | E6: Parziale / in sviluppo | F6: 23 | G6: gCO2e/kWh | H6: Strutture, cavi e componenti aggiuntivi, ma con potenziali benefici su uso del suolo e acqua | I6: Compatibile se il layout preserva funzione agricola e requisiti DNSH | J6: I progetti ben disegnati possono ridurre conflitti sull uso del suolo e migliorare resilienza delle colture | K6: S026; S022 | L6: nei casi migliori emerge co-beneficio energia-agricoltura
A7: SUS-WI-001 | B7: T006 | C7: Eolico | E7: Si | F7: 12 | G7: gCO2e/kWh | H7: Acciaio, rame, terre rare in alcune macchine, materiali compositi per pale | I7: Compatibile in via generale come attivita di generazione se rispetta TSC e DNSH | J7: Emissioni lifecycle molto basse; attenzione a uso suolo, biodiversita, rumore e fine vita delle pale | K7: S033; S047; S022 | L7: valore indicativo di ordine di grandezza per il pilot
A8: SUS-WI-002 | B8: T006 | C8: Eolico | D8: C-WI-001 | E8: Parziale / in sviluppo | F8: 12 | G8: gCO2e/kWh | H8: Materiali compositi, resine e fibre per pale; sfida sul riciclo | I8: Compatibile se gestito correttamente il fine vita | J8: Tema crescente su blade circularity e soluzioni di riciclo/riuso | K8: S047 | L8: focus su pale e end-of-life
A9: SUS-WI-003 | B9: T006 | C9: Eolico | D9: C-WI-005 | E9: Si | F9: 14 | G9: gCO2e/kWh | H9: Acciaio, cavi, ancoraggi e componenti offshore aggiuntivi | I9: Compatibile se rispettati criteri ambientali marini e DNSH | J9: Per floating attenzione a impatti marini, porti e catena logistica; alto potenziale di accesso a risorsa profonda | K9: S037; S038 | L9: ordine di grandezza indicativo
A10: SUS-H2-001 | B10: T011 | C10: Idrogeno verde | E10: Si | F10: 1.5 | G10: kgCO2e/kgH2 | H10: Acqua deionizzata, elettricita rinnovabile, acciaio, nickel, iridio/platino a seconda della tecnologia | I10: Compatibile se soddisfa i criteri UE su GHG, addizionalita e DNSH | J10: Le emissioni dipendono in modo decisivo dal mix elettrico; attenzione a uso acqua, leakage e materiali critici | K10: S052; S053; S055 | L10: valore indicativo per produzione da rinnovabili
A11: SUS-H2-002 | B11: T011 | C11: Idrogeno verde | D11: C-H2-002 | E11: Si | F11: 1.5 | G11: kgCO2e/kgH2 | H11: Hotspot materiali: iridio, platino, titanio | I11: Compatibile se la filiera rispetta i criteri ambientali e sociali applicabili | J11: La criticita dei materiali nobili rende rilevanti riciclo, sostituzione e riduzione intensita materiale | K11: S050; S055 | L11: focus specifico su PEM
A12: SUS-H2-003 | B12: T011 | C12: Idrogeno verde | D12: C-H2-006 | E12: Parziale / in sviluppo | F12: 1.5 | G12: kgCO2e/kgH2 | H12: Impatti aggiuntivi legati a compressione, liquefazione o conversione in carrier | I12: Compatibile se l intera catena mantiene le soglie GHG richieste | J12: Trasporto e carrier possono aumentare consumi energetici e impronta complessiva | K12: S049; S052 | L12: il footprint finale dipende molto dalla logistica
A13: SUS-CO-001 | B13: T001 | C13: Carbone | E13: Si, ampia letteratura | F13: 1000 | G13: gCO2e/kWh | H13: Carbone, acqua, reagenti di abbattimento e solventi CCS | I13: Non allineata salvo casi eccezionali di retrofit/transition strettamente condizionati | J13: Impronta climatica e locale elevata; attenzione a particolato, SOx/NOx, ceneri e uso acqua
A14: SUS-CO-002 | B14: T001 | C14: Carbone | E14: Parziale / mirata | F14: 850 | G14: gCO2e/kWh | H14: Materiali ad alta temperatura e reagenti di controllo emissioni | I14: Non allineata per nuovi asset convenzionali | J14: Tecnologie HELE riducono intensita ma non risolvono il tema emissivo
A15: SUS-CO-003 | B15: T001 | C15: Carbone | E15: Parziale / mirata | F15: 200 | G15: gCO2e/kWh | H15: Solventi, energia ausiliaria e infrastruttura CO2 | I15: Valutazione molto condizionata e dipendente da stoccaggio permanente | J15: CCS abbatte le emissioni ma penalizza costi, efficienza e complessita impiantistica
A16: SUS-OI-001 | B16: T002 | C16: Olio | E16: Si, ampia letteratura | F16: 780 | G16: gCO2e/kWh | H16: Greggio, catalizzatori, idrogeno di processo e acqua | I16: Non allineata | J16: Impronta climatica elevata, rischi su qualita aria, perdite e sversamenti
A17: SUS-OI-002 | B17: T002 | C17: Olio | E17: Parziale / mirata | F17: 650 | G17: gCO2e/kWh | H17: Efficienza energetica, elettrificazione e recuperi termici | I17: Non allineata per il core business ma utile per ridurre intensita del sito | J17: Miglioramenti operativi riducono intensita ma non cambiano la natura fossile
A18: SUS-OI-003 | B18: T002 | C18: Olio | E18: Parziale / mirata | F18: 600 | G18: gCO2e/kWh | H18: Sensoristica e sistemi di monitoraggio su flare e methane | I18: Non allineata | J18: Riduzione flaring e perdite aiuta soprattutto su emissioni fuggitive e reputazione
A19: SUS-GA-001 | B19: T003 | C19: Gas Naturale | E19: Si, ampia letteratura | F19: 450 | G19: gCO2e/kWh | H19: Gas naturale, infrastrutture pipeline/LNG, ammine CCS | I19: Parzialmente allineata solo come attivita transitoria a precise condizioni | J19: Migliore del carbone ma esposta a methane leakage e lock-in
A20: SUS-GA-002 | B20: T003 | C20: Gas Naturale | E20: Parziale / mirata | F20: 380 | G20: gCO2e/kWh | H20: Maggiore efficienza turbina e recupero calore | I20: Allineamento non automatico | J20: CCGT moderni riducono intensita ma restano fossili
A21: SUS-GA-003 | B21: T003 | C21: Gas Naturale | E21: Parziale / mirata | F21: 70 | G21: gCO2e/kWh | H21: Ammine, energia ausiliaria, infrastruttura CO2 | I21: Condizionata a capture rate e stoccaggio permanente | J21: Gas+CCS puo abbattere fortemente le emissioni ma con costi e complessita
A22: SUS-ST-001 | B22: T005 | C22: Solare Termico | E22: Si | F22: 30 | G22: gCO2e/kWh | H22: Acciaio, vetro, sali fusi, fluidi termovettori | I22: Allineata se rispetta DNSH e vincoli sito-specifici | J22: Impronta climatica bassa; attenzione a uso suolo, acqua e bird strike in torri CSP
A23: SUS-ST-002 | B23: T005 | C23: Solare Termico | E23: Si | F23: 20 | G23: gCO2e/kWh | H23: Collettori, piping e serbatoi | I23: Allineata | J23: Il calore solare sostituisce combustibili fossili a bassa-media temperatura
A24: SUS-ST-003 | B24: T005 | C24: Solare Termico | E24: Parziale / in sviluppo | F24: 30 | G24: gCO2e/kWh | H24: HTF, sali e componenti ad alta temperatura | I24: Allineata se gestiti correttamente rifiuti e sostanze | J24: Necessaria gestione del fine vita di sali, oli termici e materiali speciali
... A36: SUS-NU-003 | B36: T010 | C36: Nucleare da fissione | E36: Parziale / in sviluppo | F36: 12 | G36: gCO2e/kWh | H36: Modular manufacturing, acciai e supply chain qualificata | I36: Potenzialmente allineabile sotto i criteri UE | J36: Gli SMR mirano a ridurre rischio di costruzione ma sono ancora early market

Sheet 11_Best_Practice
A1: 11_Best_Practice | Casi e pratiche di riferimento
A2: Area 7 del brief: best practice mondiali che rappresentano stati di avanzamento significativi.
A3: Record_ID | B3: Tech_ID | C3: Tecnologia | D3: Comp_ID | E3: Paese / Regione | F3: Progetto / impianto / caso | G3: Organizzazione capofila | H3: Descrizione | I3: Perché è best practice | J3: Risultati / KPI chiave | K3: Anno | L3: Fonte_ID | M3: Note
A4: BP-FV-001 | B4: T004 | C4: Fotovoltaico | E4: EAU | F4: Al Dhafra Solar PV | G4: EWEC / EDF Renewables / Jinko Power | H4: Mega-impianto utility-scale da circa 2 GW con moduli bifacciali e inseguimento. | I4: Scala, bancabilita e tariffa estremamente competitiva in area MENA. | J4: Tariffa record di 1,32 US cent/kWh; produzione sufficiente per ~160.000 abitazioni. | K4: 2023 | L4: S023 | M4: riferimento utility-scale globale
A5: BP-FV-002 | B5: T004 | C5: Fotovoltaico | E5: EAU | F5: Noor Abu Dhabi | G5: EWEC / SPPC | H5: Impianto utility-scale da 1,2 GW in esercizio commerciale dal 30/04/2019. | I5: Mostra maturita industriale e capacita di esecuzione su scala GW. | J5: Oltre 3,3 milioni di pannelli; uno dei primi mega-impianti PV del Golfo. | K5: 2019 | L5: S024 | M5: caso benchmark per fase di ramp-up del settore
A6: BP-FV-003 | B6: T004 | C6: Fotovoltaico | E6: Indonesia | F6: Cirata Floating PV | G6: PLN Nusantara Renewables / Masdar | H6: Impianto floating PV realizzato su bacino artificiale. | I6: Dimostra integrazione FV su specchi d acqua e scalabilita del floating PV. | J6: 145 MWac / 192 MWp; maggiore del Sud-Est asiatico al momento dell avvio. | K6: 2023 | L6: S025 | M6: riferimento per mercati con vincoli di suolo
A7: BP-FV-004 | B7: T004 | C7: Fotovoltaico | D7: C-FV-007 | E7: Germania | F7: Heggelbach APV-RESOLA | G7: Fraunhofer ISE e partner di progetto | H7: Caso pilota agrivoltaico con coltivazioni e produzione elettrica sullo stesso terreno. | I7: Mostra il valore del dual land use e potenziali benefici su resilienza delle colture. | J7: Linee guida Fraunhofer indicano LCOE 7-12 eurocent/kWh e benefici su uso acqua/resa in condizioni di stress idrico. | K7: 2024 | L7: S026 | M7: rilevante per replicabilita in Italia
A8: BP-WI-001 | B8: T006 | C8: Eolico | E8: Regno Unito | F8: Dogger Bank | G8: SSE Renewables / Equinor / Vaargronn | H8: Progetto offshore in tre fasi destinato a diventare il piu grande parco eolico offshore al mondo. | I8: Scala multi-GW, supply chain complessa e utilizzo di turbine di grande taglia. | J8: Riferimento globale per taglia, industrializzazione e integrazione offshore. | K8: 2025 | L8: S042 | M8: best practice offshore di frontiera
A9: BP-WI-002 | B9: T006 | C9: Eolico | E9: Regno Unito | F9: Hornsea 2 | G9: Orsted | H9: Parco offshore pienamente operativo dal 2022, benchmark di esercizio commerciale su grande scala. | I9: Mostra maturita industriale e capacita di execution offshore. | J9: 1,3 GW e oltre 1,4 milioni di case equivalenti alimentate. | K9: 2022 | L9: S043 | M9: benchmark di piena operativita
A10: BP-WI-003 | B10: T006 | C10: Eolico | D10: C-WI-005 | E10: Norvegia | F10: Hywind Tampen | G10: Equinor | H10: Primo parco eolico floating costruito per alimentare installazioni offshore. | I10: Dimostra la transizione del floating da dimostrazione a progetto operativo complesso. | J10: Riferimento mondiale floating e uso in acque profonde. | K10: 2023 | L10: S044 | M10: caso icona per floating offshore
A11: BP-WI-004 | B11: T006 | C11: Eolico | E11: Paesi Bassi | F11: Hollandse Kust Zuid | G11: Vattenfall / BASF / Allianz | H11: Grande parco offshore sviluppato senza sussidi diretti. | I11: Best practice di competitivita e bancabilita in mercato maturo. | J11: Primo grande offshore subsidy-free; 139 turbine da 11 MW. | K11: 2024 | L11: S045 | M11: riferimento per maturita del modello di business
A12: BP-H2-001 | B12: T011 | C12: Idrogeno verde | E12: Arabia Saudita | F12: NEOM Green Hydrogen Project | G12: NGHC / Air Products / ACWA Power / NEOM | H12: Mega-progetto integrato con circa 4 GW di rinnovabili dedicati e produzione di ammoniaca verde. | I12: Rappresenta la frontiera della scala industriale e dell export di molecole verdi. | J12: Target fino a 1,2 Mt/anno di green ammonia. | K12: 2026 | L12: S058 | M12: best practice di scala globale
A13: BP-H2-002 | B13: T011 | C13: Idrogeno verde | E13: Svezia | F13: HYBRIT | G13: SSAB / LKAB / Vattenfall | H13: Uso di idrogeno per siderurgia fossil-free. | I13: Dimostra il ruolo del vettore nei settori hard-to-abate. | J13: Potenziale riduzione significativa delle emissioni dell industria siderurgica svedese. | K13: 2025 | L13: S059 | M13: riferimento industriale strategico
A14: BP-H2-003 | B14: T011 | C14: Idrogeno verde | D14: C-H2-002 | E14: Germania | F14: REFHYNE | G14: Shell / ITM Power e partner | H14: PEM electrolyser in raffineria, con evoluzione da 10 MW a 100 MW. | I14: Best practice di integrazione industriale e scale-up progressivo. | J14: Passaggio da dimostrazione a scala industriale. | K14: 2025 | L14: S060 | M14: caso molto rilevante in UE
A15: BP-H2-004 | B15: T011 | C15: Idrogeno verde | E15: Spagna | F15: Puertollano green hydrogen plant | G15: Iberdrola / Fertiberia | H15: Impianto integrato PV+battery+electrolyzer per uso industriale. | I15: Mostra integrazione tra rinnovabili, accumulo ed elettrolisi in un caso reale. | J15: 100 MW PV, 20 MW elettrolizzatore, 5 MW/20 MWh batteria. | K15: 2024 | L15: S061 | M15: best practice europea integrata
A16: BP-CO-001 | B16: T001 | C16: Carbone | E16: Giappone | F16: Isogo New Units | G16: JERA | H16: Impianto ultrasupercritico con standard ambientali molto elevati per un asset coal. | I16: Benchmark di efficienza e controllo emissioni locali. | J16: Efficienza netta ~45% HHV, basse emissioni locali. | K16: S120
A17: BP-CO-002 | B17: T001 | C17: Carbone | E17: USA | F17: Petra Nova | G17: Petra Nova | H17: Retrofit di cattura CO2 su impianto a carbone. | I17: Caso di riferimento per fattibilita CCS retrofit. | J17: Capture train su scala utility, lesson learned su affidabilita e economics. | K17: S118
A18: BP-CO-003 | B18: T001 | C18: Carbone | E18: Canada | F18: Boundary Dam Unit 3 CCS | G18: SaskPower | H18: Primo grande caso di CCS operativo su unita coal. | I18: Mostra integrazione impianto + trasporto/uso/stoccaggio CO2. | J18: Esperienza pluriennale di esercizio commerciale con CCS. | K18: S119
A19: BP-CO-004 | B19: T001 | C19: Carbone | E19: Cina | F19: Yuhuan ultrasupercritical plant | G19: China Energy | H19: Grande impianto ultrasupercritico di alta efficienza. | I19: Riferimento per scala e rendimento nel parco moderno. | J19: Unit size da 1 GW e rendimento superiore ai subcritical legacy. | K19: S121
A20: BP-OI-001 | B20: T002 | C20: Olio | E20: Corea del Sud | F20: Shaheen Project | G20: S-OIL | H20: Grande progetto di upgrading integrato per aumentare efficienza e valore prodotti. | I20: Riferimento per raffinazione avanzata e residue upgrading. | J20: Maggiore conversione di residui e resa su prodotti ad alto valore. | K20: S114
A21: BP-OI-002 | B21: T002 | C21: Olio | E21: Finlandia | F21: Porvoo transformation | G21: Neste | H21: Trasformazione del sito verso prodotti a minore intensita carbonica e maggiore flessibilita feedstock. | I21: Esempio di riconversione industriale della filiera oil. | J21: Roadmap di trasformazione e integrazione con nuovi prodotti. | K21: S115
A22: BP-OI-003 | B22: T002 | C22: Olio | E22: EAU | F22: ADNOC decarbonization program | G22: ADNOC | H22: Programmi su efficienza, riduzione flaring e metano. | I22: Benchmark di miglioramento operativo nella filiera upstream/downstream. | J22: Riduzione intensita emissiva e digitalizzazione asset. | K22: S116
A23: BP-OI-004 | B23: T002 | C23: Olio | E23: India | F23: Jamnagar refinery complex | G23: Reliance Industries | H23: Hub raffinazione integrato di grandissima scala. | I23: Riferimento per integrazione industriale, logistica e ottimizzazione. | J23: Elevata complessita e flessibilita di slate produttivo. | K23: S117
A24: BP-GA-001 | B24: T003 | C24: Gas Naturale | E24: Regno Unito | F24: Keadby 2 | G24: SSE Thermal | H24: CCGT di nuova generazione ad alta efficienza e flessibilita. | I24: Benchmark europeo per efficienza e fast response. | J24: Capacita >800 MW e avvio flessibile. | K24: S110
A25: BP-GA-002 | B25: T003 | C25: Gas Naturale | E25: USA | F25: NET Power La Porte | G25: NET Power | H25: Ciclo innovativo a gas con cattura CO2 integrata. | I25: Mostra una possibile frontiera low-carbon dispatchable. | J25: Architettura Allam-Fetvedt con CO2 ad alta purezza. | K25: S112
A26: BP-GA-003 | B26: T003 | C26: Gas Naturale | E26: USA | F26: Intermountain Power Project | G26: IPA / Mitsubishi Power | H26: Nuova centrale predisposta a crescente uso di idrogeno. | I26: Best practice transition-ready della generazione a gas. | J26: Roadmap verso combustione con blend H2 elevati. | K26: S111
A27: BP-GA-004 | B27: T003 | C27: Gas Naturale | E27: Belgio | F27: T-Power Tessenderlo | G27: ENGIE / T-Power | H27: CCGT efficiente in mercato europeo. | I27: Riferimento per esercizio merchant e flessibile. | J27: Alta efficienza e integrazione nel mercato elettrico. | K27: S113
... A47: BP-NU-004 | B47: T010 | C47: Nucleare da fissione | E47: Cina | F47: Linglong One SMR | G47: CNNC | H47: Uno dei principali progetti SMR dimostrativi al mondo. | I47: Riferimento per frontiera modulare. | J47: SMR avanzato orientato a deployment commerciale. | K47: S109

Sheet 12_Policy_Regolazione
A1: 12_Policy_Regolazione | Policy e regolazione
A2: Area 8 del brief: policy, regolamentazione, incentivi e standard rilevanti per la tecnologia.
A3: Record_ID | B3: Tech_ID | C3: Tecnologia | D3: Giurisdizione | E3: Tipo policy / regolazione | F3: Titolo atto / misura | G3: Stato | H3: Data entrata in vigore | I3: Impatto sulla tecnologia | J3: Fonte_ID | K3: Note
A4: POL-FV-001 | B4: T004 | C4: Fotovoltaico | D4: UE | E4: Direttiva | F4: Direttiva (UE) 2023/2413 - RED III | G4: In vigore; recepimento nazionale in corso | H4: 2023-11-20 | I4: Aumenta target rinnovabili al 42,5% con obiettivo 45% e accelera permitting; favorisce anche forme innovative come l agrisolar. | J4: S018 | K4: cornice UE per crescita FV
A5: POL-FV-002 | B5: T004 | C5: Fotovoltaico | D5: UE | E5: Regolamento | F5: Regolamento (UE) 2024/1735 - Net-Zero Industry Act | G5: In vigore; atti attuativi e implementazione 2025 | H5: 2024-06-29 | I5: Supporta manifattura UE di PV e componenti, introduce misure su permitting, resilience e criteri non-price in procurement/aste. | J5: S019 | K5: rilevante per rafforzare filiera europea
A6: POL-FV-003 | B6: T004 | C6: Fotovoltaico | D6: Italia | E6: Decreto / Incentivo | F6: Decreto CACER n. 414/2023 + Regole operative GSE | G6: Attivo; tariffa fino a 5 GW o 31/12/2027; finestra PNRR chiusa il 30/11/2025 | H6: 2024-01-24 | I6: Spinge rooftop PV, CER e autoconsumo collettivo con tariffa incentivante e contributi in conto capitale PNRR. | J6: S020 | K6: mercato distribuito e comunita energetiche
A7: POL-FV-004 | B7: T004 | C7: Fotovoltaico | D7: Italia | E7: Decreto / PNRR | F7: Sviluppo agro-voltaico (DM 436/2023; regole 2024; aggiornamenti 2025) | G7: Attivo e aggiornato nel 2025 | H7: 2024-02-14 | I7: Sostiene sistemi agrivoltaici innovativi e sperimentali, orientando layout, monitoraggio e requisiti di accesso. | J7: S028 | K7: rilevante per dual land use
A8: POL-FV-005 | B8: T004 | C8: Fotovoltaico | D8: UE | E8: Tassonomia | F8: EU Taxonomy - attivita di generazione/installazione FV | G8: Applicabile | H8: 2024-01-01 | I8: Facilita qualificazione della tecnologia come investimento sostenibile se rispettati TSC e DNSH. | J8: S022 | K8: rilevante per finanza sostenibile e reporting ESG
A9: POL-WI-001 | B9: T006 | C9: Eolico | D9: UE | E9: Direttiva | F9: Direttiva (UE) 2023/2413 - RED III | G9: In vigore; recepimento nazionale in corso | H9: 2023-11-20 | I9: Accelera deployment rinnovabili e permitting, con beneficio diretto per onshore e offshore wind. | J9: S018 | K9: cornice UE per crescita eolico
A10: POL-WI-002 | B10: T006 | C10: Eolico | D10: UE | E10: Regolamento / piano | F10: European Wind Power Action Plan | G10: Attivo | H10: 2023-10-24 | I10: Interviene su aste, finanziabilita, permitting, competenze e supply chain della manifattura eolica europea. | J10: S039 | K10: rilevante per competitivita industriale
A11: POL-WI-003 | B11: T006 | C11: Eolico | D11: UE | E11: Strategia | F11: Strategia UE sulle rinnovabili offshore | G11: Attiva | H11: 2020-11-19 | I11: Supporta la crescita dell offshore wind e la cooperazione infrastrutturale tra Stati Membri. | J11: S038 | K11: cornice di lungo termine per offshore e floating
A12: POL-WI-004 | B12: T006 | C12: Eolico | D12: Italia | E12: Programma / roadmap | F12: MASE - Eolico Offshore | G12: Attivo | H12: 2025-01-01 | I12: Orienta iter, sviluppo e posizionamento nazionale su offshore e floating. | J12: S040 | K12: rilevante per pipeline italiana
A13: POL-WI-005 | B13: T006 | C13: Eolico | D13: Italia | E13: Decreto / Incentivo | F13: FER X transitorio e graduatorie GSE | G13: Attivo | H13: 2025-01-01 | I13: Supporta nuova capacita eolica tramite aste e procedure competitive. | J13: S041 | K13: rilevante per nuovi impianti e repowering
A14: POL-H2-001 | B14: T011 | C14: Idrogeno verde | D14: UE | E14: Regola / atto delegato | F14: Renewable hydrogen rules e delegated acts RFNBO | G14: Applicabile | H14: 2023-06-20 | I14: Definisce criteri su addizionalita, correlazione temporale e soglie GHG per l accesso al mercato UE. | J14: S052; S053 | K14: atto chiave per bankability
... A18: POL-H2-005 | B18: T011 | C18: Idrogeno verde | D18: Italia | E18: Programma / PNRR | F18: Hydrogen Valleys | G18: Attivo | H18: 2024-01-01 | I18: Sostiene cluster territoriali e primi ecosistemi di produzione/uso in aree industriali dismesse. | J18: S057 | K18: rilevante per early market
A19: POL-CO-001 | B19: T001 | C19: Carbone | D19: UE | E19: Regolazione / ETS | F19: EU ETS e phase-out nazionali | G19: In vigore | H19: 2005-01-01 | I19: Alza il costo della CO2 e accelera uscita del carbone in molti mercati europei. | J19: S083
A20: POL-CO-002 | B20: T001 | C20: Carbone | D20: UE | E20: Tassonomia | F20: EU Taxonomy | G20: In vigore | H20: 2020-07-12 | I20: Nuovi asset coal non sono qualificati come sostenibili. | J20: S083
A21: POL-CO-003 | B21: T001 | C21: Carbone | D21: Globale | E21: Mercato | F21: Coal 2025 / policy outlook | G21: Attivo | H21: 2025-12-17 | I21: Le policy climatiche comprimono il ruolo di medio termine in molte economie avanzate. | J21: S089
A22: POL-CO-004 | B22: T001 | C22: Carbone | D22: Italia | E22: Strategia | F22: Piano energia e clima / phase-out coal | G22: In evoluzione | H22: 2019-01-01 | I22: Riduzione ruolo del carbone nella generazione nazionale. | J22: S077
A23: POL-CO-005 | B23: T001 | C23: Carbone | D23: Globale | E23: Incentivo / CCS | F23: Schemi CCfD/45Q e supporti CCUS | G23: In sviluppo | H23: 2025-01-01 | I23: Solo in presenza di forte supporto il coal+CCS torna bancabile. | J23: S118
A24: POL-OI-001 | B24: T002 | C24: Olio | D24: UE | E24: Regolazione | F24: Fuel quality, ETS e standard ambientali | G24: In vigore | H24: 2020-01-01 | I24: Aumentano pressione su intensita carbonica e qualita prodotti. | J24: S083
A25: POL-OI-002 | B25: T002 | C25: Olio | D25: Globale | E25: Mercato | F25: Oil 2025 / outlook | G25: Attivo | H25: 2025-06-01 | I25: La crescita della domanda rallenta in diversi segmenti e aree geografiche. | J25: S088
A26: POL-OI-003 | B26: T002 | C26: Olio | D26: UE | E26: Tassonomia | F26: EU Taxonomy | G26: In vigore | H26: 2020-07-12 | I26: Nuove attivita oil non qualificate come sostenibili. | J26: S083
A27: POL-OI-004 | B27: T002 | C27: Olio | D27: Globale | E27: Methane / flaring | F27: Iniziative methane abatement | G27: In sviluppo | H27: 2025-01-01 | I27: Spingono sensoristica, LDAR e riduzione flaring nelle operations. | J27: S116
A28: POL-OI-005 | B28: T002 | C28: Olio | D28: Italia / UE | E28: Transizione industriale | F28: Supporto a riconversione raffinerie e low-carbon fuels | G28: In evoluzione | H28: 2024-01-01 | I28: Premia efficienza, elettrificazione e prodotti alternativi. | J28: S115
A29: POL-GA-001 | B29: T003 | C29: Gas Naturale | D29: UE | E29: Direttiva / mercato | F29: RED III ed elettrificazione | G29: In vigore | H29: 2023-11-20 | I29: La crescita delle FER riduce il ruolo del gas nei load factor ma ne valorizza la flessibilita. | J29: S081
A30: POL-GA-002 | B30: T003 | C30: Gas Naturale | D30: UE | E30: Tassonomia | F30: Complementary Climate Delegated Act | G30: In vigore | H30: 2022-07-15 | I30: Classifica solo alcune attivita gas come transitorie e a condizioni rigorose. | J30: S078
... A58: POL-NU-005 | B58: T010 | C58: Nucleare da fissione | D58: Italia | E58: Strategia | F58: Percorso su nuovo nucleare sostenibile / PNNS | G58: In evoluzione | H58: 2025-01-01 | I58: Riapre spazio di analisi strategica e industriale nazionale. | J58: S072

Sheet 13_Barriere_Opp
A1: 13_Barriere_Opp | Barriere e opportunità
A2: Area 9 del brief: barriere tecnologiche, economiche, regolatorie e opportunità di sviluppo.
A3: Record_ID | B3: Tech_ID | C3: Tecnologia | D3: Comp_ID | E3: Categoria | F3: Barriera o opportunità | G3: Descrizione | H3: Severità / Priorità | I3: Azioni di mitigazione o leva | J3: Fonte_ID | K3: Note
A4: BAR-FV-001 | B4: T004 | C4: Fotovoltaico | E4: Regolatoria | F4: Permitting, uso del suolo e accettabilita locale | G4: I tempi autorizzativi e i conflitti territoriali possono rallentare utility-scale, floating e agrivoltaico. | H4: Alta | I4: Individuare aree idonee, semplificare permitting, curare engagement locale e progettazione paesaggistica. | J4: S018; S028 | K4: barriera chiave nei mercati europei
A5: BAR-FV-002 | B5: T004 | C5: Fotovoltaico | D5: C-FV-001 | E5: Supply chain | F5: Dipendenza da supply chain estere e materie prime critiche | G5: La filiera europea resta esposta a concentrazione geografica e disponibilita di argento, silicio, rame e altri materiali. | H5: Alta | I5: Riciclo, circolarita, reshoring/nearshoring e strumenti NZIA per rafforzare resilienza industriale. | J5: S021; S019 | K5: barriera industriale-strategica
A6: BAR-FV-003 | B6: T004 | C6: Fotovoltaico | D6: C-FV-003 | E6: Infrastrutturale | F6: Congestione di rete, interconnessioni e curtailment | G6: La rapida crescita del FV aumenta il bisogno di rete, storage e flessibilita. | H6: Alta | I6: Integrare PV+BESS, demand response, rinforzi di rete e pianificazione territoriale. | J6: S013; S014 | K6: barriera di sistema
A7: BAR-FV-004 | B7: T004 | C7: Fotovoltaico | D7: C-FV-001 | E7: Economica | F7: Riduzione dei prezzi di moduli e BOS | G7: La discesa dei costi amplia la competitivita del FV in molti segmenti. | H7: Alta priorita | I7: Accelerare repowering, aste, PPA e diffusione distribuita dove la rete lo consente. | J7: S017; S012 | K7: opportunita di mercato molto forte
A8: BAR-FV-005 | B8: T004 | C8: Fotovoltaico | D8: C-FV-006 | E8: Tecnologica | F8: Tandem perovskite-silicio come salto prestazionale | G8: Potenziale >30% di efficienza ma ancora da validare pienamente su affidabilita e bancabilita. | H8: Media-alta | I8: Finanziare piloti, test di durabilita e monitoraggio ravvicinato in horizon scanning. | J8: S017 | K8: opportunita ad alto potenziale
A9: BAR-FV-006 | B9: T004 | C9: Fotovoltaico | D9: C-FV-007 | E9: Sociale | F9: Agrivoltaico per ridurre conflitto sull uso del suolo | G9: Se ben progettato, l agrivoltaico puo creare consenso e valore addizionale per le aziende agricole. | H9: Media | I9: Standard progettuali, metriche energia-agricoltura e strumenti di supporto dedicati. | J9: S026; S028 | K9: opportunita rilevante per l Italia
A10: BAR-WI-001 | B10: T006 | C10: Eolico | E10: Regolatoria | F10: Permitting e accettabilita locale | G10: Iter autorizzativi lunghi e opposizioni territoriali restano tra i principali freni, specialmente onshore e offshore nearshore. | H10: Alta | I10: Semplificare permitting, aree idonee, engagement locale e qualita progettuale. | J10: S039; S040 | K10: barriera chiave
A11: BAR-WI-002 | B11: T006 | C11: Eolico | D11: C-WI-007 | E11: Infrastrutturale | F11: Connessione di rete e colli di bottiglia di sistema | G11: La velocita di sviluppo della rete e delle sottostazioni puo rallentare entrata in esercizio e repowering. | H11: Alta | I11: Pianificazione anticipata, investimenti rete e coordinamento porti/cavi/offtake. | J11: S038; S037 | K11: barriera di sistema
A12: BAR-WI-003 | B12: T006 | C12: Eolico | D12: C-WI-001 | E12: Supply chain | F12: Materiali, logistica e componenti oversize | G12: Pale lunghe, torri alte e navi specializzate aumentano complessita e rischio costi. | H12: Alta | I12: Rafforzare filiere, porti, standard modulari e produzione regionale. | J12: S039; S037 | K12: barriera industriale
A13: BAR-WI-004 | B13: T006 | C13: Eolico | D13: C-WI-005 | E13: Tecnologica | F13: Floating offshore come nuova frontiera | G13: L accesso a risorse profonde amplia drasticamente il potenziale tecnico disponibile. | H13: Alta priorita | I13: Sostenere dimostratori, aste dedicate e industrializzazione delle piattaforme. | J13: S044; S038 | K13: opportunita strategica
A14: BAR-WI-005 | B14: T006 | C14: Eolico | E14: Economica | F14: Repowering onshore | G14: Il repowering consente di aumentare produzione e ridurre LCOE su siti esistenti. | H14: Media-alta | I14: Allineare permitting, incentivi e pianificazione di rete. | J14: S036; S041 | K14: opportunita concreta nel breve
A15: BAR-WI-006 | B15: T006 | C15: Eolico | D15: C-WI-006 | E15: Tecnologica | F15: Digital O&M e aumento disponibilita | G15: Analytics e condition monitoring migliorano resa e contenimento OPEX. | H15: Media | I15: Sviluppare competenze dati, interoperabilita e manutenzione predittiva. | J15: S036 | K15: opportunita gestionale rilevante
A16: BAR-H2-001 | B16: T011 | C16: Idrogeno verde | E16: Economica | F16: Costo ancora elevato del green hydrogen | G16: Il business case resta fragile senza elettricita rinnovabile competitiva, load factor adeguato e sostegni pubblici. | H16: Alta | I16: PPA low-cost, scala, migliori utilization rates e aste dedicate. | J16: S049; S051; S054 | K16: barriera chiave
A17: BAR-H2-002 | B17: T011 | C17: Idrogeno verde | D17: C-H2-006 | E17: Infrastrutturale | F17: Infrastrutture di trasporto e off-take insufficienti | G17: Reti, stoccaggi e domanda certa sono ancora limitati in molti mercati. | H17: Alta | I17: Sviluppare cluster, hydrogen valleys, contratti di offtake e infrastrutture condivise. | J17: S049; S057 | K17: barriera di sistema
A18: BAR-H2-003 | B18: T011 | C18: Idrogeno verde | E18: Regolatoria | F18: Complessita regolatoria e certificazione RFNBO | G18: Le regole su addizionalita e correlazione temporale possono rallentare investimenti e strutturazione finanziaria. | H18: Alta | I18: Chiarezza regolatoria, standard di certificazione e supporto transitorio. | J18: S052; S053 | K18: barriera UE rilevante
A19: BAR-H2-004 | B19: T011 | C19: Idrogeno verde | D19: C-H2-002 | E19: Supply chain | F19: Dipendenza da materiali critici | G19: Per alcune tecnologie, soprattutto PEM, iridio e altri materiali possono essere colli di bottiglia. | H19: Media-alta | I19: Ridurre intensita materiale, sviluppare riciclo e alternative tecnologiche. | J19: S050; S055 | K19: barriera industriale
A20: BAR-H2-005 | B20: T011 | C20: Idrogeno verde | E20: Opportunita | F20: Early market nei cluster industriali | G20: Raffinerie, ammoniaca, acciaio e hydrogen valleys sono i primi segmenti dove si concentra la domanda credibile. | H20: Alta priorita | I20: Concentrare sforzi su hub industriali e casi d uso ad alta disponibilita a pagare. | J20: S049; S057; S060; S061 | K20: opportunita di go-to-market
A21: BAR-H2-006 | B21: T011 | C21: Idrogeno verde | D21: C-H2-003 | E21: Tecnologica | F21: SOEC e integrazione termica | G21: L alta temperatura puo offrire efficienze superiori in specifici contesti industriali. | H21: Media | I21: Finanziare piloti, validare durabilita e integrare con process heat. | J21: S055 | K21: opportunita ad alto potenziale
A22: BAR-CO-001 | B22: T001 | C22: Carbone | E22: Regolatoria | F22: Prezzo CO2 e phase-out | G22: L esposizione a carbon pricing e normative ambientali riduce la bancabilita dei nuovi impianti. | H22: Alta | I22: Limitare a gestione transizione, repowering o CCS in cluster industriali. | J22: S089
A23: BAR-CO-002 | B23: T001 | C23: Carbone | E23: Economica | F23: CAPEX e stranded assets | G23: Nuovi coal convenzionali hanno alto rischio di asset stranded. | H23: Alta | I23: Valutare solo retrofit selettivi o chiusura pianificata. | J23: S077
A24: BAR-CO-003 | B24: T001 | C24: Carbone | E24: Infrastrutturale | F24: Uso acqua e siti | G24: Molti impianti richiedono acqua, connessioni e logistica dedicate. | H24: Media | I24: Ottimizzare siti esistenti e reindustrializzazione aree brownfield. | J24: S075
A25: BAR-CO-004 | B25: T001 | C25: Carbone | E25: Tecnologica | F25: CCS retrofit complesso | G25: Penalty energetico e complessita impiantistica frenano retrofit. | H25: Alta | I25: Cluster CO2, incentivi e hub di trasporto/stoccaggio. | J25: S118
A26: BAR-CO-005 | B26: T001 | C26: Carbone | E26: Sociale | F26: Accettabilita locale | G26: Impatto su qualita aria, miniere e territori. | H26: Alta | I26: Just transition, remediation e riconversione industriale. | J26: S077
A27: BAR-CO-006 | B27: T001 | C27: Carbone | E27: Opportunita | F27: Flessibilizzazione / repurposing siti | G27: I siti coal possono ospitare storage, reti, CCS o nuove tecnologie. | H27: Media | I27: Strategie di riconversione e riuso asset. | J27: S119
A28: BAR-OI-001 | B28: T002 | C28: Olio | E28: Regolatoria | F28: Carbon policy e standard fuel | G28: Standard piu severi comprimono margini e asset oil-fired legacy. | H28: Alta | I28: Accelerare efficienza e diversificazione prodotti. | J28: S083
A29: BAR-OI-002 | B29: T002 | C29: Olio | E29: Economica | F29: Volatilita prezzi greggio | G29: Elevata volatilita impatta competitivita e pianificazione. | H29: Alta | I29: Hedging, flessibilita slate e integrazione industriale. | J29: S088
A30: BAR-OI-003 | B30: T002 | C30: Olio | E30: Infrastrutturale | F30: Dipendenza da logistica dedicata | G30: Terminali, shipping e storage restano centrali ma costosi. | H30: Media | I30: Ottimizzazione rete e digital supply chain. | J30: S076
A31: BAR-OI-004 | B31: T002 | C31: Olio | E31: Ambientale | F31: Sversamenti, flare, methane | G31: Rischi ambientali e reputazionali rilevanti. | H31: Alta | I31: LDAR, flare minimization, water management. | J31: S116
A32: BAR-OI-005 | B32: T002 | C32: Olio | E32: Tecnologica | F32: Electrification gap | G32: Difficile elettrificare completamente alcune utenze di raffineria nel breve. | H32: Media | I32: Heat integration, elettrificazione selettiva, H2 a basse emissioni. | J32: S115
A33: BAR-OI-006 | B33: T002 | C33: Olio | E33: Opportunita | F33: Riconversione industriale | G33: Siti oil possono evolvere in bioraffinerie o hub energetici. | H33: Media | I33: Piani di trasformazione e CAPEX selettivo. | J33: S115
... A69: BAR-NU-006 | B69: T010 | C69: Nucleare da fissione | E69: Opportunita | F69: Firm low-carbon power | G69: Valore elevato in sistemi elettrici molto decarbonizzati e power-hungry. | H69: Alta | I69: Market design che valorizzi capacity, reliability e heat/hydrogen co-products. | J69: S070

Sheet 14_Attori_Imprese
A1: 14_Attori_Imprese | Attori e imprese coinvolte
A2: Area 10 del brief: mappatura degli attori coinvolti nello sviluppo di tecnologie e componenti.
A3: Record_ID | B3: Tech_ID | C3: Tecnologia | D3: Comp_ID | E3: Attore / Impresa | F3: Tipo attore | G3: Paese | H3: Ruolo nella filiera | I3: Rilevanza strategica | J3: Sito web | K3: Fonte_ID | L3: Note
A4: ATT-FV-001 | B4: T004 | C4: Fotovoltaico | D4: C-FV-001 | E4: LONGi | F4: Azienda | G4: Cina | H4: Sviluppo e produzione di celle e moduli ad alta efficienza | I4: Alta | J4: https://www.longi.com/en/ | K4: S029 | L4: attore globale di riferimento lato moduli
A5: ATT-FV-002 | B5: T004 | C5: Fotovoltaico | D5: C-FV-001 | E5: Trina Solar | F5: Azienda | G5: Cina | H5: Produzione moduli, tracker e soluzioni smart energy | I5: Alta | J5: https://www.trinasolar.com/en-glb/ | K5: S031 | L5: attore globale integrato
A6: ATT-FV-003 | B6: T004 | C6: Fotovoltaico | D6: C-FV-002 | E6: Sungrow | F6: OEM | G6: Cina | H6: Inverter utility-scale e sistemi di accumulo | I6: Alta | J6: https://en.sungrowpower.com/ | K6: S027 | L6: riferimento lato power electronics
A7: ATT-FV-004 | B7: T004 | C7: Fotovoltaico | D7: C-FV-002 | E7: SMA Solar Technology | F7: OEM | G7: Germania | H7: Inverter, system integration e servizi energetici | I7: Alta | J7: https://www.sma-italia.com/ | K7: S030 | L7: attore europeo rilevante
A8: ATT-FV-005 | B8: T004 | C8: Fotovoltaico | D8: C-FV-007 | E8: Fraunhofer ISE | F8: Centro di ricerca | G8: Germania | H8: Ricerca applicata su integrated PV, agrivoltaico e prestazioni di sistema | I8: Alta | J8: https://www.ise.fraunhofer.de/en/ | K8: S026 | L8: riferimento scientifico UE
A9: ATT-FV-006 | B9: T004 | C9: Fotovoltaico | E9: NREL | F9: Centro di ricerca | G9: USA | H9: Benchmark costi, LCA, supply chain e roadmapping tecnologico | I9: Alta | J9: https://www.nrel.gov/ | K9: S013 | L9: fonte tecnica autorevole
A10: ATT-FV-007 | B10: T004 | C10: Fotovoltaico | E10: GSE | F10: Ente pubblico | G10: Italia | H10: Gestione incentivi, regole operative CER/autoconsumo e supporto mercato distribuito | I10: Alta | J10: https://www.gse.it/ | K10: S020 | L10: attore chiave per il mercato italiano
A11: ATT-WI-001 | B11: T006 | C11: Eolico | D11: C-WI-001 | E11: Vestas | F11: OEM | G11: Danimarca | H11: Sviluppo e produzione di turbine onshore e componenti chiave | I11: Alta | J11: https://www.vestas.com/ | K11: S047 | L11: attore globale di riferimento
A12: ATT-WI-002 | B12: T006 | C12: Eolico | D12: C-WI-002 | E12: GE Vernova | F12: OEM | G12: USA | H12: Turbine offshore di grande taglia e tecnologie Haliade-X | I12: Alta | J12: https://www.gevernova.com/ | K12: S046 | L12: riferimento lato offshore
A13: ATT-WI-003 | B13: T006 | C13: Eolico | E13: Orsted | F13: Sviluppatore / utility | G13: Danimarca | H13: Sviluppo, costruzione e gestione di parchi offshore | I13: Alta | J13: https://orsted.com/ | K13: S043 | L13: leader offshore europeo
A14: ATT-WI-004 | B14: T006 | C14: Eolico | D14: C-WI-005 | E14: Equinor | F14: Sviluppatore / utility | G14: Norvegia | H14: Sviluppo offshore e floating wind | I14: Alta | J14: https://www.equinor.com/ | K14: S044 | L14: attore chiave sul floating
A15: ATT-WI-005 | B15: T006 | C15: Eolico | E15: SSE Renewables | F15: Sviluppatore / utility | G15: Regno Unito | H15: Sviluppo di grandi progetti offshore e supply chain | I15: Alta | J15: https://www.sserenewables.com/ | K15: S042 | L15: rilevante lato execution
A16: ATT-WI-006 | B16: T006 | C16: Eolico | E16: WindEurope | F16: Associazione | G16: UE | H16: Rappresentanza di settore, dati di mercato e policy advocacy | I16: Media-alta | J16: https://windeurope.org/ | K16: S039 | L16: attore chiave sul contesto europeo
A17: ATT-WI-007 | B17: T006 | C17: Eolico | E17: NREL | F17: Centro di ricerca | G17: USA | H17: Benchmark costi, prestazioni e scenari tecnologici | I17: Alta | J17: https://www.nrel.gov/ | K17: S034; S035; S037 | L17: fonte tecnica autorevole
A18: ATT-H2-001 | B18: T011 | C18: Idrogeno verde | D18: C-H2-001 | E18: thyssenkrupp nucera | F18: OEM | G18: Germania | H18: Tecnologie e impianti per elettrolisi alcalina | I18: Alta | J18: https://www.thyssenkrupp-nucera.com/ | K18: S055 | L18: attore importante nella filiera UE
A19: ATT-H2-002 | B19: T011 | C19: Idrogeno verde | D19: C-H2-002 | E19: ITM Power | F19: OEM | G19: Regno Unito | H19: Tecnologia PEM ed elettrolizzatori per applicazioni industriali | I19: Alta | J19: https://itm-power.com/ | K19: S060 | L19: attore rilevante per PEM
